Workbook

Sheet 🏠 ACCUEIL
A1: 🏦 TONTINE SOLIDARITÉ PLUS 2027
A2: Système de Gestion Financière Professionnelle
A3: Bienvenue dans votre espace de gestion de tontine. Naviguez via les onglets ci-dessous.
B6: ⚙️ PARAMETRES | D6: 💰 COTISATIONS | F6: 🔄REMBOURSEMENT | H6: 🏧 CAISSE | J6: 📜 CONTRATS
B8: 👥 MEMBRES | D8: 🏦 PRÊTS | F8: ⚠️ PÉNALITÉS | H8: 📋 SOLDE MEMBRES | J8: 📊 TABLEAU DE BORD
B11: 📋 MODULES DISPONIBLES • Gestion des membres & identités • Suivi hebdomadaire des cotisations • Gestion des prêts & remboursements • Calcul automatique des pénalités • Tableau de bord dynamique | F11: ⚙️ PARAMÈTRES CLÉS • Taux d'intérêt : 12% (modifiable) • Cotisation standard : 2 500 FCFA/semaine • Pénalité retard : 100: FCFA • Pénalité absence : 500 FCFA • 23 membres actifs(modifiable)
B16: 💡 MODE D'EMPLOI : Toutes les feuilles sont reliées par ID_MEMBRE (TSP-2027-XXX). Ne jamais modifier les IDs. Généré le 13/05/2026

Sheet ⚙️ PARAMÈTRES
A1: ⚙️ PARAMÈTRES SYSTÈME — TONTINE SOLIDARITÉ PLUS 2027
A3: PARAMÈTRE | B3: VALEUR | C3: UNITÉ | D3: DESCRIPTION | E3: MODIFIÉ PAR
A4: Taux d'intérêt mensuel standard | B4: 0.1 | C4: % | D4: Taux appliqué aux prêts ≤ 2 mois | E4: Bureau
A5: Taux supplémentaire après 2 mois | B5: 0.015 | C5: % | D5: Intérêt additionnel si crédit impayé > 2 mois | E5: Bureau
A6: Cotisation minimum | B6: 500 | C6: FCFA | D6: Montant minimum d'engagement par semaine | E6: Bureau
A7: Cotisation hebdo standard | B7: 2500 | C7: FCFA | D7: Montant standard conseillé | E7: Bureau
A8: Pénalité retard cotisation (hors dim) | B8: 100 | C8: FCFA | D8: Cotisation effectuée un autre jour que dimanche | E8: Bureau
A9: Pénalité absence réunion | B9: 500 | C9: FCFA | D9: Par absence à la réunion mensuelle | E9: Bureau
A10: Frais de retrait prêt | B10: 0.02 | C10: % | D10: Frais prélevés sur le montant octroyé | E10: Bureau
A11: Durée max prêt (mois) | B11: 2 | C11: mois | D11: Au-delà : intérêt supplémentaire s'applique | E11: Bureau
A12: Nombre max de membres | B12: 50 | C12: membres | D12: Capacité maximale actuelle du système | E12: Bureau
A13: Année exercice | B13: 2027 | C13: année | D13: Exercice financier en cours | E13: Bureau
A14: 📌 RÉFÉRENCES : Taux intérêt = B4 | Taux supp = B5 | Cot.min = B6 | Cot.standard = B7 | Pén.retard = B8 | Pén.absence = B9 | Frais retrait = B10 | Durée max = B11

Sheet 👥 MEMBRES
A1: 👥 REGISTRE DES MEMBRES — TONTINE SOLIDARITÉ PLUS 2027
A2: =COUNTA(B5:B54)&" membres enregistrés | Mis à jour le "&TEXT(TODAY(),"DD/MM/YYYY") -> #VALUE!
A4: ID_MEMBRE | B4: NOM | C4: PRÉNOMS | D4: TÉLÉPHONE | E4: EMAIL | F4: SEXE | G4: N° CIP | H4: DATE NAISSANCE | I4: DATE ADHÉSION | J4: STATUT | K4: COT.ENGAGÉE/SEM (FCFA) | L4: ADRESSE | M4: PROFESSION | N4: PARRAIN/RÉFÉRENT | O4: OBSERVATIONS
A5: TSP-2027-001 | J5: Actif
A6: TSP-2027-002 | J6: Actif
A7: TSP-2027-003 | J7: Actif
A8: TSP-2027-004 | J8: Actif
A9: TSP-2027-005 | J9: Actif
A10: TSP-2027-006 | J10: Actif
A11: TSP-2027-007 | J11: Actif
A12: TSP-2027-008 | J12: Actif
A13: TSP-2027-009 | J13: Actif
A14: TSP-2027-010 | J14: Actif
A15: TSP-2027-011 | J15: Actif
A16: TSP-2027-012 | J16: Actif
... A54: TSP-2027-050 | J54: Actif

Sheet 💰 COTISATIONS
A1: 💰 REGISTRE DES COTISATIONS HEBDOMADAIRES — TONTINE SOLIDARITÉ PLUS 2027
E2: JANVIER | J2: FÉVRIER | N2: MARS | R2: AVRIL | V2: MAI | AA2: JUIN | AE2: JUILLET | AI2: AOÛT | AN2: SEPTEMBRE | AR2: OCTOBRE | AW2: NOVEMBRE | BA2: DÉCEMBRE
A3: ID_MEMBRE | B3: NOM | C3: PRÉNOMS | D3: CIBLE /SEM. | E3: 46390 | F3: 46397 | G3: 46404 | H3: 46411 | I3: 46418 | J3: 46425 | K3: 46432 | L3: 46439 | M3: 46446 | N3: 46453 | O3: 46460 | P3: 46467 | Q3: 46474 | R3: 46481 | S3: 46488 | T3: 46495 | U3: 46502 | V3: 46509 | W3: 46516 | X3: 46523 | Y3: 46530 | Z3: 46537 | AA3: 46544 | AB3: 46551 | AC3: 46558 | AD3: 46565 | AE3: 46572 | AF3: 46579 | AG3: 46586 | AH3: 46593 | AI3: 46600 | AJ3: 46607 | AK3: 46614 | AL3: 46621 | AM3: 46628 | AN3: 46635 | AO3: 46642 | AP3: 46649 | AQ3: 46656 | AR3: 46663 | AS3: 46670 | AT3: 46677 | AU3: 46684 | AV3: 46691 | AW3: 46698 | AX3: 46705 | AY3: 46712 | AZ3: 46719 | BA3: 46726 | BB3: 46733 | BC3: 46740 | BD3: 46747 | BE3: TOTAL VERSÉ | BF3: TOTAL ENGAGÉ | BG3: ÉCART (FCFA) | BH3: PÉN. DIMANCHE | BI3: STATUT
A4: ='👥 MEMBRES'!A5 -> TSP-2027-001 | B4: ='👥 MEMBRES'!B5 -> 0 | C4: ='👥 MEMBRES'!C5 -> 0 | D4: =IF('👥 MEMBRES'!K5="",0,'👥 MEMBRES'!K5) -> 0 | BE4: =SUM(E4:BD4) -> 0 | BF4: =D4*COUNTA(E4:BD4) -> 0 | BG4: =BE4-BF4 -> 0 | BH4: =SUMIF('⚠️ PÉNALITÉS'!B:B,A4,'⚠️ PÉNALITÉS'!G:G) -> 0 | BI4: =IF(D4=0,"— Non défini",IF(BG4>=0,"✅ Conforme","⚠️ Insuffisant")) -> — Non défini
A5: ='👥 MEMBRES'!A6 -> TSP-2027-002 | B5: ='👥 MEMBRES'!B6 -> 0 | C5: ='👥 MEMBRES'!C6 -> 0 | D5: =IF('👥 MEMBRES'!K6="",0,'👥 MEMBRES'!K6) -> 0 | BE5: =SUM(E5:BD5) -> 0 | BF5: =D5*COUNTA(E5:BD5) -> 0 | BG5: =BE5-BF5 -> 0 | BH5: =SUMIF('⚠️ PÉNALITÉS'!B:B,A5,'⚠️ PÉNALITÉS'!G:G) -> 0 | BI5: =IF(D5=0,"— Non défini",IF(BG5>=0,"✅ Conforme","⚠️ Insuffisant")) -> — Non défini
A6: ='👥 MEMBRES'!A7 -> TSP-2027-003 | B6: ='👥 MEMBRES'!B7 -> 0 | C6: ='👥 MEMBRES'!C7 -> 0 | D6: =IF('👥 MEMBRES'!K7="",0,'👥 MEMBRES'!K7) -> 0 | BE6: =SUM(E6:BD6) -> 0 | BF6: =D6*COUNTA(E6:BD6) -> 0 | BG6: =BE6-BF6 -> 0 | BH6: =SUMIF('⚠️ PÉNALITÉS'!B:B,A6,'⚠️ PÉNALITÉS'!G:G) -> 0 | BI6: =IF(D6=0,"— Non défini",IF(BG6>=0,"✅ Conforme","⚠️ Insuffisant")) -> — Non défini
A7: ='👥 MEMBRES'!A8 -> TSP-2027-004 | B7: ='👥 MEMBRES'!B8 -> 0 | C7: ='👥 MEMBRES'!C8 -> 0 | D7: =IF('👥 MEMBRES'!K8="",0,'👥 MEMBRES'!K8) -> 0 | BE7: =SUM(E7:BD7) -> 0 | BF7: =D7*COUNTA(E7:BD7) -> 0 | BG7: =BE7-BF7 -> 0 | BH7: =SUMIF('⚠️ PÉNALITÉS'!B:B,A7,'⚠️ PÉNALITÉS'!G:G) -> 0 | BI7: =IF(D7=0,"— Non défini",IF(BG7>=0,"✅ Conforme","⚠️ Insuffisant")) -> — Non défini
A8: ='👥 MEMBRES'!A9 -> TSP-2027-005 | B8: ='👥 MEMBRES'!B9 -> 0 | C8: ='👥 MEMBRES'!C9 -> 0 | D8: =IF('👥 MEMBRES'!K9="",0,'👥 MEMBRES'!K9) -> 0 | BE8: =SUM(E8:BD8) -> 0 | BF8: =D8*COUNTA(E8:BD8) -> 0 | BG8: =BE8-BF8 -> 0 | BH8: =SUMIF('⚠️ PÉNALITÉS'!B:B,A8,'⚠️ PÉNALITÉS'!G:G) -> 0 | BI8: =IF(D8=0,"— Non défini",IF(BG8>=0,"✅ Conforme","⚠️ Insuffisant")) -> — Non défini
A9: ='👥 MEMBRES'!A10 -> TSP-2027-006 | B9: ='👥 MEMBRES'!B10 -> 0 | C9: ='👥 MEMBRES'!C10 -> 0 | D9: =IF('👥 MEMBRES'!K10="",0,'👥 MEMBRES'!K10) -> 0 | BE9: =SUM(E9:BD9) -> 0 | BF9: =D9*COUNTA(E9:BD9) -> 0 | BG9: =BE9-BF9 -> 0 | BH9: =SUMIF('⚠️ PÉNALITÉS'!B:B,A9,'⚠️ PÉNALITÉS'!G:G) -> 0 | BI9: =IF(D9=0,"— Non défini",IF(BG9>=0,"✅ Conforme","⚠️ Insuffisant")) -> — Non défini
A10: ='👥 MEMBRES'!A11 -> TSP-2027-007 | B10: ='👥 MEMBRES'!B11 -> 0 | C10: ='👥 MEMBRES'!C11 -> 0 | D10: =IF('👥 MEMBRES'!K11="",0,'👥 MEMBRES'!K11) -> 0 | BE10: =SUM(E10:BD10) -> 0 | BF10: =D10*COUNTA(E10:BD10) -> 0 | BG10: =BE10-BF10 -> 0 | BH10: =SUMIF('⚠️ PÉNALITÉS'!B:B,A10,'⚠️ PÉNALITÉS'!G:G) -> 0 | BI10: =IF(D10=0,"— Non défini",IF(BG10>=0,"✅ Conforme","⚠️ Insuffisant")) -> — Non défini
A11: ='👥 MEMBRES'!A12 -> TSP-2027-008 | B11: ='👥 MEMBRES'!B12 -> 0 | C11: ='👥 MEMBRES'!C12 -> 0 | D11: =IF('👥 MEMBRES'!K12="",0,'👥 MEMBRES'!K12) -> 0 | BE11: =SUM(E11:BD11) -> 0 | BF11: =D11*COUNTA(E11:BD11) -> 0 | BG11: =BE11-BF11 -> 0 | BH11: =SUMIF('⚠️ PÉNALITÉS'!B:B,A11,'⚠️ PÉNALITÉS'!G:G) -> 0 | BI11: =IF(D11=0,"— Non défini",IF(BG11>=0,"✅ Conforme","⚠️ Insuffisant")) -> — Non défini
A12: ='👥 MEMBRES'!A13 -> TSP-2027-009 | B12: ='👥 MEMBRES'!B13 -> 0 | C12: ='👥 MEMBRES'!C13 -> 0 | D12: =IF('👥 MEMBRES'!K13="",0,'👥 MEMBRES'!K13) -> 0 | BE12: =SUM(E12:BD12) -> 0 | BF12: =D12*COUNTA(E12:BD12) -> 0 | BG12: =BE12-BF12 -> 0 | BH12: =SUMIF('⚠️ PÉNALITÉS'!B:B,A12,'⚠️ PÉNALITÉS'!G:G) -> 0 | BI12: =IF(D12=0,"— Non défini",IF(BG12>=0,"✅ Conforme","⚠️ Insuffisant")) -> — Non défini
A13: ='👥 MEMBRES'!A14 -> TSP-2027-010 | B13: ='👥 MEMBRES'!B14 -> 0 | C13: ='👥 MEMBRES'!C14 -> 0 | D13: =IF('👥 MEMBRES'!K14="",0,'👥 MEMBRES'!K14) -> 0 | BE13: =SUM(E13:BD13) -> 0 | BF13: =D13*COUNTA(E13:BD13) -> 0 | BG13: =BE13-BF13 -> 0 | BH13: =SUMIF('⚠️ PÉNALITÉS'!B:B,A13,'⚠️ PÉNALITÉS'!G:G) -> 0 | BI13: =IF(D13=0,"— Non défini",IF(BG13>=0,"✅ Conforme","⚠️ Insuffisant")) -> — Non défini
A14: ='👥 MEMBRES'!A15 -> TSP-2027-011 | B14: ='👥 MEMBRES'!B15 -> 0 | C14: ='👥 MEMBRES'!C15 -> 0 | D14: =IF('👥 MEMBRES'!K15="",0,'👥 MEMBRES'!K15) -> 0 | BE14: =SUM(E14:BD14) -> 0 | BF14: =D14*COUNTA(E14:BD14) -> 0 | BG14: =BE14-BF14 -> 0 | BH14: =SUMIF('⚠️ PÉNALITÉS'!B:B,A14,'⚠️ PÉNALITÉS'!G:G) -> 0 | BI14: =IF(D14=0,"— Non défini",IF(BG14>=0,"✅ Conforme","⚠️ Insuffisant")) -> — Non défini
A15: ='👥 MEMBRES'!A16 -> TSP-2027-012 | B15: ='👥 MEMBRES'!B16 -> 0 | C15: ='👥 MEMBRES'!C16 -> 0 | D15: =IF('👥 MEMBRES'!K16="",0,'👥 MEMBRES'!K16) -> 0 | BE15: =SUM(E15:BD15) -> 0 | BF15: =D15*COUNTA(E15:BD15) -> 0 | BG15: =BE15-BF15 -> 0 | BH15: =SUMIF('⚠️ PÉNALITÉS'!B:B,A15,'⚠️ PÉNALITÉS'!G:G) -> 0 | BI15: =IF(D15=0,"— Non défini",IF(BG15>=0,"✅ Conforme","⚠️ Insuffisant")) -> — Non défini
... A53: ='👥 MEMBRES'!A54 -> TSP-2027-050 | B53: ='👥 MEMBRES'!B54 -> 0 | C53: ='👥 MEMBRES'!C54 -> 0 | D53: =IF('👥 MEMBRES'!K54="",0,'👥 MEMBRES'!K54) -> 0 | BE53: =SUM(E53:BD53) -> 0 | BF53: =D53*COUNTA(E53:BD53) -> 0 | BG53: =BE53-BF53 -> 0 | BH53: =SUMIF('⚠️ PÉNALITÉS'!B:B,A53,'⚠️ PÉNALITÉS'!G:G) -> 0 | BI53: =IF(D53=0,"— Non défini",IF(BG53>=0,"✅ Conforme","⚠️ Insuffisant")) -> — Non défini
A54: 🏦 TOTAL GÉNÉRAL | E54: =SUM(E4:E53) -> 0 | F54: =SUM(F4:F53) -> 0 | G54: =SUM(G4:G53) -> 0 | H54: =SUM(H4:H53) -> 0 | I54: =SUM(I4:I53) -> 0 | J54: =SUM(J4:J53) -> 0 | K54: =SUM(K4:K53) -> 0 | L54: =SUM(L4:L53) -> 0 | ... BE54: =SUM(BE4:BE53) -> 0

Sheet 🏦 PRÊTS
A1: 🏦 REGISTRE DES PRÊTS — TONTINE SOLIDARITÉ PLUS 2027
A2: ⚙️ Taux 1er mois = B4 (PARAMÈTRES) | Taux supp. après 2 mois = B5 (PARAMÈTRES) | Frais retrait = B10 (PARAMÈTRES)
A3: ID_PRÊT | B3: ID_MEMBRE | C3: NOM | D3: PRÉNOMS | E3: DATE PRÊT | F3: MONTANT EMPRUNTÉ | G3: FRAIS RETRAIT | H3: TÉMOIN (si > épargne) | I3: TÉL TÉMOIN | J3: ADRESSE TÉMOIN | K3: DATE ÉCHÉANCE | L3: INTÉRÊTS (1 mois) | M3: INTÉRÊTS (2 mois) | N3: INTÉRÊTS SUPP. | O3: TOTAL DÛ | P3: REMBOURSÉ | Q3: SOLDE RESTANT | R3: STATUT
A4: PRE-2027-001 | G4: =IF(F4="",0,F4*'⚙️ PARAMÈTRES'!B10) -> 0 | L4: =IF(F4="",0,F4*'⚙️ PARAMÈTRES'!B4) -> 0 | M4: =IF(F4="",0,F4*'⚙️ PARAMÈTRES'!B4*2) -> 0 | N4: =IF(OR(F4="",K4=""),0,IF(AND(R4<>"Soldé",TODAY()>K4+60),(F4-P4)*'⚙️ PARAMÈTRES'!B5*MAX(0,DATEDIF(K4,TODAY(),"M")-2),0)) -> 0 | O4: =IF(F4="",0,F4+G4+L4+N4) -> 0 | P4: =SUMIF('🔄 REMBOURSEMENTS'!B:B,A4,'🔄 REMBOURSEMENTS'!F:F) -> 0 | Q4: =MAX(0,O4-P4) -> 0 | R4: =IF(F4="","—",IF(Q4=0,"✅ Soldé",IF(AND(K4<>"",TODAY()>K4+60),"🔴 Impayé",IF(AND(K4<>"",TODAY()>K4),"⚠️ En retard","🔵 En cours")))) -> —
A5: PRE-2027-002 | G5: =IF(F5="",0,F5*'⚙️ PARAMÈTRES'!B10) -> 0 | L5: =IF(F5="",0,F5*'⚙️ PARAMÈTRES'!B4) -> 0 | M5: =IF(F5="",0,F5*'⚙️ PARAMÈTRES'!B4*2) -> 0 | N5: =IF(OR(F5="",K5=""),0,IF(AND(R5<>"Soldé",TODAY()>K5+60),(F5-P5)*'⚙️ PARAMÈTRES'!B5*MAX(0,DATEDIF(K5,TODAY(),"M")-2),0)) -> 0 | O5: =IF(F5="",0,F5+G5+L5+N5) -> 0 | P5: =SUMIF('🔄 REMBOURSEMENTS'!B:B,A5,'🔄 REMBOURSEMENTS'!F:F) -> 0 | Q5: =MAX(0,O5-P5) -> 0 | R5: =IF(F5="","—",IF(Q5=0,"✅ Soldé",IF(AND(K5<>"",TODAY()>K5+60),"🔴 Impayé",IF(AND(K5<>"",TODAY()>K5),"⚠️ En retard","🔵 En cours")))) -> —
A6: PRE-2027-003 | G6: =IF(F6="",0,F6*'⚙️ PARAMÈTRES'!B10) -> 0 | L6: =IF(F6="",0,F6*'⚙️ PARAMÈTRES'!B4) -> 0 | M6: =IF(F6="",0,F6*'⚙️ PARAMÈTRES'!B4*2) -> 0 | N6: =IF(OR(F6="",K6=""),0,IF(AND(R6<>"Soldé",TODAY()>K6+60),(F6-P6)*'⚙️ PARAMÈTRES'!B5*MAX(0,DATEDIF(K6,TODAY(),"M")-2),0)) -> 0 | O6: =IF(F6="",0,F6+G6+L6+N6) -> 0 | P6: =SUMIF('🔄 REMBOURSEMENTS'!B:B,A6,'🔄 REMBOURSEMENTS'!F:F) -> 0 | Q6: =MAX(0,O6-P6) -> 0 | R6: =IF(F6="","—",IF(Q6=0,"✅ Soldé",IF(AND(K6<>"",TODAY()>K6+60),"🔴 Impayé",IF(AND(K6<>"",TODAY()>K6),"⚠️ En retard","🔵 En cours")))) -> —
A7: PRE-2027-004 | G7: =IF(F7="",0,F7*'⚙️ PARAMÈTRES'!B10) -> 0 | L7: =IF(F7="",0,F7*'⚙️ PARAMÈTRES'!B4) -> 0 | M7: =IF(F7="",0,F7*'⚙️ PARAMÈTRES'!B4*2) -> 0 | N7: =IF(OR(F7="",K7=""),0,IF(AND(R7<>"Soldé",TODAY()>K7+60),(F7-P7)*'⚙️ PARAMÈTRES'!B5*MAX(0,DATEDIF(K7,TODAY(),"M")-2),0)) -> 0 | O7: =IF(F7="",0,F7+G7+L7+N7) -> 0 | P7: =SUMIF('🔄 REMBOURSEMENTS'!B:B,A7,'🔄 REMBOURSEMENTS'!F:F) -> 0 | Q7: =MAX(0,O7-P7) -> 0 | R7: =IF(F7="","—",IF(Q7=0,"✅ Soldé",IF(AND(K7<>"",TODAY()>K7+60),"🔴 Impayé",IF(AND(K7<>"",TODAY()>K7),"⚠️ En retard","🔵 En cours")))) -> —
A8: PRE-2027-005 | G8: =IF(F8="",0,F8*'⚙️ PARAMÈTRES'!B10) -> 0 | L8: =IF(F8="",0,F8*'⚙️ PARAMÈTRES'!B4) -> 0 | M8: =IF(F8="",0,F8*'⚙️ PARAMÈTRES'!B4*2) -> 0 | N8: =IF(OR(F8="",K8=""),0,IF(AND(R8<>"Soldé",TODAY()>K8+60),(F8-P8)*'⚙️ PARAMÈTRES'!B5*MAX(0,DATEDIF(K8,TODAY(),"M")-2),0)) -> 0 | O8: =IF(F8="",0,F8+G8+L8+N8) -> 0 | P8: =SUMIF('🔄 REMBOURSEMENTS'!B:B,A8,'🔄 REMBOURSEMENTS'!F:F) -> 0 | Q8: =MAX(0,O8-P8) -> 0 | R8: =IF(F8="","—",IF(Q8=0,"✅ Soldé",IF(AND(K8<>"",TODAY()>K8+60),"🔴 Impayé",IF(AND(K8<>"",TODAY()>K8),"⚠️ En retard","🔵 En cours")))) -> —
A9: PRE-2027-006 | G9: =IF(F9="",0,F9*'⚙️ PARAMÈTRES'!B10) -> 0 | L9: =IF(F9="",0,F9*'⚙️ PARAMÈTRES'!B4) -> 0 | M9: =IF(F9="",0,F9*'⚙️ PARAMÈTRES'!B4*2) -> 0 | N9: =IF(OR(F9="",K9=""),0,IF(AND(R9<>"Soldé",TODAY()>K9+60),(F9-P9)*'⚙️ PARAMÈTRES'!B5*MAX(0,DATEDIF(K9,TODAY(),"M")-2),0)) -> 0 | O9: =IF(F9="",0,F9+G9+L9+N9) -> 0 | P9: =SUMIF('🔄 REMBOURSEMENTS'!B:B,A9,'🔄 REMBOURSEMENTS'!F:F) -> 0 | Q9: =MAX(0,O9-P9) -> 0 | R9: =IF(F9="","—",IF(Q9=0,"✅ Soldé",IF(AND(K9<>"",TODAY()>K9+60),"🔴 Impayé",IF(AND(K9<>"",TODAY()>K9),"⚠️ En retard","🔵 En cours")))) -> —
A10: PRE-2027-007 | G10: =IF(F10="",0,F10*'⚙️ PARAMÈTRES'!B10) -> 0 | L10: =IF(F10="",0,F10*'⚙️ PARAMÈTRES'!B4) -> 0 | M10: =IF(F10="",0,F10*'⚙️ PARAMÈTRES'!B4*2) -> 0 | N10: =IF(OR(F10="",K10=""),0,IF(AND(R10<>"Soldé",TODAY()>K10+60),(F10-P10)*'⚙️ PARAMÈTRES'!B5*MAX(0,DATEDIF(K10,TODAY(),"M")-2),0)) -> 0 | O10: =IF(F10="",0,F10+G10+L10+N10) -> 0 | P10: =SUMIF('🔄 REMBOURSEMENTS'!B:B,A10,'🔄 REMBOURSEMENTS'!F:F) -> 0 | Q10: =MAX(0,O10-P10) -> 0 | R10: =IF(F10="","—",IF(Q10=0,"✅ Soldé",IF(AND(K10<>"",TODAY()>K10+60),"🔴 Impayé",IF(AND(K10<>"",TODAY()>K10),"⚠️ En retard","🔵 En cours")))) -> —
A11: PRE-2027-008 | G11: =IF(F11="",0,F11*'⚙️ PARAMÈTRES'!B10) -> 0 | L11: =IF(F11="",0,F11*'⚙️ PARAMÈTRES'!B4) -> 0 | M11: =IF(F11="",0,F11*'⚙️ PARAMÈTRES'!B4*2) -> 0 | N11: =IF(OR(F11="",K11=""),0,IF(AND(R11<>"Soldé",TODAY()>K11+60),(F11-P11)*'⚙️ PARAMÈTRES'!B5*MAX(0,DATEDIF(K11,TODAY(),"M")-2),0)) -> 0 | O11: =IF(F11="",0,F11+G11+L11+N11) -> 0 | P11: =SUMIF('🔄 REMBOURSEMENTS'!B:B,A11,'🔄 REMBOURSEMENTS'!F:F) -> 0 | Q11: =MAX(0,O11-P11) -> 0 | R11: =IF(F11="","—",IF(Q11=0,"✅ Soldé",IF(AND(K11<>"",TODAY()>K11+60),"🔴 Impayé",IF(AND(K11<>"",TODAY()>K11),"⚠️ En retard","🔵 En cours")))) -> —
A12: PRE-2027-009 | G12: =IF(F12="",0,F12*'⚙️ PARAMÈTRES'!B10) -> 0 | L12: =IF(F12="",0,F12*'⚙️ PARAMÈTRES'!B4) -> 0 | M12: =IF(F12="",0,F12*'⚙️ PARAMÈTRES'!B4*2) -> 0 | N12: =IF(OR(F12="",K12=""),0,IF(AND(R12<>"Soldé",TODAY()>K12+60),(F12-P12)*'⚙️ PARAMÈTRES'!B5*MAX(0,DATEDIF(K12,TODAY(),"M")-2),0)) -> 0 | O12: =IF(F12="",0,F12+G12+L12+N12) -> 0 | P12: =SUMIF('🔄 REMBOURSEMENTS'!B:B,A12,'🔄 REMBOURSEMENTS'!F:F) -> 0 | Q12: =MAX(0,O12-P12) -> 0 | R12: =IF(F12="","—",IF(Q12=0,"✅ Soldé",IF(AND(K12<>"",TODAY()>K12+60),"🔴 Impayé",IF(AND(K12<>"",TODAY()>K12),"⚠️ En retard","🔵 En cours")))) -> —
A13: PRE-2027-010 | G13: =IF(F13="",0,F13*'⚙️ PARAMÈTRES'!B10) -> 0 | L13: =IF(F13="",0,F13*'⚙️ PARAMÈTRES'!B4) -> 0 | M13: =IF(F13="",0,F13*'⚙️ PARAMÈTRES'!B4*2) -> 0 | N13: =IF(OR(F13="",K13=""),0,IF(AND(R13<>"Soldé",TODAY()>K13+60),(F13-P13)*'⚙️ PARAMÈTRES'!B5*MAX(0,DATEDIF(K13,TODAY(),"M")-2),0)) -> 0 | O13: =IF(F13="",0,F13+G13+L13+N13) -> 0 | P13: =SUMIF('🔄 REMBOURSEMENTS'!B:B,A13,'🔄 REMBOURSEMENTS'!F:F) -> 0 | Q13: =MAX(0,O13-P13) -> 0 | R13: =IF(F13="","—",IF(Q13=0,"✅ Soldé",IF(AND(K13<>"",TODAY()>K13+60),"🔴 Impayé",IF(AND(K13<>"",TODAY()>K13),"⚠️ En retard","🔵 En cours")))) -> —
A14: PRE-2027-011 | G14: =IF(F14="",0,F14*'⚙️ PARAMÈTRES'!B10) -> 0 | L14: =IF(F14="",0,F14*'⚙️ PARAMÈTRES'!B4) -> 0 | M14: =IF(F14="",0,F14*'⚙️ PARAMÈTRES'!B4*2) -> 0 | N14: =IF(OR(F14="",K14=""),0,IF(AND(R14<>"Soldé",TODAY()>K14+60),(F14-P14)*'⚙️ PARAMÈTRES'!B5*MAX(0,DATEDIF(K14,TODAY(),"M")-2),0)) -> 0 | O14: =IF(F14="",0,F14+G14+L14+N14) -> 0 | P14: =SUMIF('🔄 REMBOURSEMENTS'!B:B,A14,'🔄 REMBOURSEMENTS'!F:F) -> 0 | Q14: =MAX(0,O14-P14) -> 0 | R14: =IF(F14="","—",IF(Q14=0,"✅ Soldé",IF(AND(K14<>"",TODAY()>K14+60),"🔴 Impayé",IF(AND(K14<>"",TODAY()>K14),"⚠️ En retard","🔵 En cours")))) -> —
A15: PRE-2027-012 | G15: =IF(F15="",0,F15*'⚙️ PARAMÈTRES'!B10) -> 0 | L15: =IF(F15="",0,F15*'⚙️ PARAMÈTRES'!B4) -> 0 | M15: =IF(F15="",0,F15*'⚙️ PARAMÈTRES'!B4*2) -> 0 | N15: =IF(OR(F15="",K15=""),0,IF(AND(R15<>"Soldé",TODAY()>K15+60),(F15-P15)*'⚙️ PARAMÈTRES'!B5*MAX(0,DATEDIF(K15,TODAY(),"M")-2),0)) -> 0 | O15: =IF(F15="",0,F15+G15+L15+N15) -> 0 | P15: =SUMIF('🔄 REMBOURSEMENTS'!B:B,A15,'🔄 REMBOURSEMENTS'!F:F) -> 0 | Q15: =MAX(0,O15-P15) -> 0 | R15: =IF(F15="","—",IF(Q15=0,"✅ Soldé",IF(AND(K15<>"",TODAY()>K15+60),"🔴 Impayé",IF(AND(K15<>"",TODAY()>K15),"⚠️ En retard","🔵 En cours")))) -> —
A16: PRE-2027-013 | G16: =IF(F16="",0,F16*'⚙️ PARAMÈTRES'!B10) -> 0 | L16: =IF(F16="",0,F16*'⚙️ PARAMÈTRES'!B4) -> 0 | M16: =IF(F16="",0,F16*'⚙️ PARAMÈTRES'!B4*2) -> 0 | N16: =IF(OR(F16="",K16=""),0,IF(AND(R16<>"Soldé",TODAY()>K16+60),(F16-P16)*'⚙️ PARAMÈTRES'!B5*MAX(0,DATEDIF(K16,TODAY(),"M")-2),0)) -> 0 | O16: =IF(F16="",0,F16+G16+L16+N16) -> 0 | P16: =SUMIF('🔄 REMBOURSEMENTS'!B:B,A16,'🔄 REMBOURSEMENTS'!F:F) -> 0 | Q16: =MAX(0,O16-P16) -> 0 | R16: =IF(F16="","—",IF(Q16=0,"✅ Soldé",IF(AND(K16<>"",TODAY()>K16+60),"🔴 Impayé",IF(AND(K16<>"",TODAY()>K16),"⚠️ En retard","🔵 En cours")))) -> —
A17: PRE-2027-014 | G17: =IF(F17="",0,F17*'⚙️ PARAMÈTRES'!B10) -> 0 | L17: =IF(F17="",0,F17*'⚙️ PARAMÈTRES'!B4) -> 0 | M17: =IF(F17="",0,F17*'⚙️ PARAMÈTRES'!B4*2) -> 0 | N17: =IF(OR(F17="",K17=""),0,IF(AND(R17<>"Soldé",TODAY()>K17+60),(F17-P17)*'⚙️ PARAMÈTRES'!B5*MAX(0,DATEDIF(K17,TODAY(),"M")-2),0)) -> 0 | O17: =IF(F17="",0,F17+G17+L17+N17) -> 0 | P17: =SUMIF('🔄 REMBOURSEMENTS'!B:B,A17,'🔄 REMBOURSEMENTS'!F:F) -> 0 | Q17: =MAX(0,O17-P17) -> 0 | R17: =IF(F17="","—",IF(Q17=0,"✅ Soldé",IF(AND(K17<>"",TODAY()>K17+60),"🔴 Impayé",IF(AND(K17<>"",TODAY()>K17),"⚠️ En retard","🔵 En cours")))) -> —
A18: PRE-2027-015 | G18: =IF(F18="",0,F18*'⚙️ PARAMÈTRES'!B10) -> 0 | L18: =IF(F18="",0,F18*'⚙️ PARAMÈTRES'!B4) -> 0 | M18: =IF(F18="",0,F18*'⚙️ PARAMÈTRES'!B4*2) -> 0 | N18: =IF(OR(F18="",K18=""),0,IF(AND(R18<>"Soldé",TODAY()>K18+60),(F18-P18)*'⚙️ PARAMÈTRES'!B5*MAX(0,DATEDIF(K18,TODAY(),"M")-2),0)) -> 0 | O18: =IF(F18="",0,F18+G18+L18+N18) -> 0 | P18: =SUMIF('🔄 REMBOURSEMENTS'!B:B,A18,'🔄 REMBOURSEMENTS'!F:F) -> 0 | Q18: =MAX(0,O18-P18) -> 0 | R18: =IF(F18="","—",IF(Q18=0,"✅ Soldé",IF(AND(K18<>"",TODAY()>K18+60),"🔴 Impayé",IF(AND(K18<>"",TODAY()>K18),"⚠️ En retard","🔵 En cours")))) -> —
A19: PRE-2027-016 | G19: =IF(F19="",0,F19*'⚙️ PARAMÈTRES'!B10) -> 0 | L19: =IF(F19="",0,F19*'⚙️ PARAMÈTRES'!B4) -> 0 | M19: =IF(F19="",0,F19*'⚙️ PARAMÈTRES'!B4*2) -> 0 | N19: =IF(OR(F19="",K19=""),0,IF(AND(R19<>"Soldé",TODAY()>K19+60),(F19-P19)*'⚙️ PARAMÈTRES'!B5*MAX(0,DATEDIF(K19,TODAY(),"M")-2),0)) -> 0 | O19: =IF(F19="",0,F19+G19+L19+N19) -> 0 | P19: =SUMIF('🔄 REMBOURSEMENTS'!B:B,A19,'🔄 REMBOURSEMENTS'!F:F) -> 0 | Q19: =MAX(0,O19-P19) -> 0 | R19: =IF(F19="","—",IF(Q19=0,"✅ Soldé",IF(AND(K19<>"",TODAY()>K19+60),"🔴 Impayé",IF(AND(K19<>"",TODAY()>K19),"⚠️ En retard","🔵 En cours")))) -> —
A20: PRE-2027-017 | G20: =IF(F20="",0,F20*'⚙️ PARAMÈTRES'!B10) -> 0 | L20: =IF(F20="",0,F20*'⚙️ PARAMÈTRES'!B4) -> 0 | M20: =IF(F20="",0,F20*'⚙️ PARAMÈTRES'!B4*2) -> 0 | N20: =IF(OR(F20="",K20=""),0,IF(AND(R20<>"Soldé",TODAY()>K20+60),(F20-P20)*'⚙️ PARAMÈTRES'!B5*MAX(0,DATEDIF(K20,TODAY(),"M")-2),0)) -> 0 | O20: =IF(F20="",0,F20+G20+L20+N20) -> 0 | P20: =SUMIF('🔄 REMBOURSEMENTS'!B:B,A20,'🔄 REMBOURSEMENTS'!F:F) -> 0 | Q20: =MAX(0,O20-P20) -> 0 | R20: =IF(F20="","—",IF(Q20=0,"✅ Soldé",IF(AND(K20<>"",TODAY()>K20+60),"🔴 Impayé",IF(AND(K20<>"",TODAY()>K20),"⚠️ En retard","🔵 En cours")))) -> —
A21: PRE-2027-018 | G21: =IF(F21="",0,F21*'⚙️ PARAMÈTRES'!B10) -> 0 | L21: =IF(F21="",0,F21*'⚙️ PARAMÈTRES'!B4) -> 0 | M21: =IF(F21="",0,F21*'⚙️ PARAMÈTRES'!B4*2) -> 0 | N21: =IF(OR(F21="",K21=""),0,IF(AND(R21<>"Soldé",TODAY()>K21+60),(F21-P21)*'⚙️ PARAMÈTRES'!B5*MAX(0,DATEDIF(K21,TODAY(),"M")-2),0)) -> 0 | O21: =IF(F21="",0,F21+G21+L21+N21) -> 0 | P21: =SUMIF('🔄 REMBOURSEMENTS'!B:B,A21,'🔄 REMBOURSEMENTS'!F:F) -> 0 | Q21: =MAX(0,O21-P21) -> 0 | R21: =IF(F21="","—",IF(Q21=0,"✅ Soldé",IF(AND(K21<>"",TODAY()>K21+60),"🔴 Impayé",IF(AND(K21<>"",TODAY()>K21),"⚠️ En retard","🔵 En cours")))) -> —
A22: PRE-2027-019 | G22: =IF(F22="",0,F22*'⚙️ PARAMÈTRES'!B10) -> 0 | L22: =IF(F22="",0,F22*'⚙️ PARAMÈTRES'!B4) -> 0 | M22: =IF(F22="",0,F22*'⚙️ PARAMÈTRES'!B4*2) -> 0 | N22: =IF(OR(F22="",K22=""),0,IF(AND(R22<>"Soldé",TODAY()>K22+60),(F22-P22)*'⚙️ PARAMÈTRES'!B5*MAX(0,DATEDIF(K22,TODAY(),"M")-2),0)) -> 0 | O22: =IF(F22="",0,F22+G22+L22+N22) -> 0 | P22: =SUMIF('🔄 REMBOURSEMENTS'!B:B,A22,'🔄 REMBOURSEMENTS'!F:F) -> 0 | Q22: =MAX(0,O22-P22) -> 0 | R22: =IF(F22="","—",IF(Q22=0,"✅ Soldé",IF(AND(K22<>"",TODAY()>K22+60),"🔴 Impayé",IF(AND(K22<>"",TODAY()>K22),"⚠️ En retard","🔵 En cours")))) -> —
A23: PRE-2027-020 | G23: =IF(F23="",0,F23*'⚙️ PARAMÈTRES'!B10) -> 0 | L23: =IF(F23="",0,F23*'⚙️ PARAMÈTRES'!B4) -> 0 | M23: =IF(F23="",0,F23*'⚙️ PARAMÈTRES'!B4*2) -> 0 | N23: =IF(OR(F23="",K23=""),0,IF(AND(R23<>"Soldé",TODAY()>K23+60),(F23-P23)*'⚙️ PARAMÈTRES'!B5*MAX(0,DATEDIF(K23,TODAY(),"M")-2),0)) -> 0 | O23: =IF(F23="",0,F23+G23+L23+N23) -> 0 | P23: =SUMIF('🔄 REMBOURSEMENTS'!B:B,A23,'🔄 REMBOURSEMENTS'!F:F) -> 0 | Q23: =MAX(0,O23-P23) -> 0 | R23: =IF(F23="","—",IF(Q23=0,"✅ Soldé",IF(AND(K23<>"",TODAY()>K23+60),"🔴 Impayé",IF(AND(K23<>"",TODAY()>K23),"⚠️ En retard","🔵 En cours")))) -> —
A24: PRE-2027-021 | G24: =IF(F24="",0,F24*'⚙️ PARAMÈTRES'!B10) -> 0 | L24: =IF(F24="",0,F24*'⚙️ PARAMÈTRES'!B4) -> 0 | M24: =IF(F24="",0,F24*'⚙️ PARAMÈTRES'!B4*2) -> 0 | N24: =IF(OR(F24="",K24=""),0,IF(AND(R24<>"Soldé",TODAY()>K24+60),(F24-P24)*'⚙️ PARAMÈTRES'!B5*MAX(0,DATEDIF(K24,TODAY(),"M")-2),0)) -> 0 | O24: =IF(F24="",0,F24+G24+L24+N24) -> 0 | P24: =SUMIF('🔄 REMBOURSEMENTS'!B:B,A24,'🔄 REMBOURSEMENTS'!F:F) -> 0 | Q24: =MAX(0,O24-P24) -> 0 | R24: =IF(F24="","—",IF(Q24=0,"✅ Soldé",IF(AND(K24<>"",TODAY()>K24+60),"🔴 Impayé",IF(AND(K24<>"",TODAY()>K24),"⚠️ En retard","🔵 En cours")))) -> —
A25: PRE-2027-022 | G25: =IF(F25="",0,F25*'⚙️ PARAMÈTRES'!B10) -> 0 | L25: =IF(F25="",0,F25*'⚙️ PARAMÈTRES'!B4) -> 0 | M25: =IF(F25="",0,F25*'⚙️ PARAMÈTRES'!B4*2) -> 0 | N25: =IF(OR(F25="",K25=""),0,IF(AND(R25<>"Soldé",TODAY()>K25+60),(F25-P25)*'⚙️ PARAMÈTRES'!B5*MAX(0,DATEDIF(K25,TODAY(),"M")-2),0)) -> 0 | O25: =IF(F25="",0,F25+G25+L25+N25) -> 0 | P25: =SUMIF('🔄 REMBOURSEMENTS'!B:B,A25,'🔄 REMBOURSEMENTS'!F:F) -> 0 | Q25: =MAX(0,O25-P25) -> 0 | R25: =IF(F25="","—",IF(Q25=0,"✅ Soldé",IF(AND(K25<>"",TODAY()>K25+60),"🔴 Impayé",IF(AND(K25<>"",TODAY()>K25),"⚠️ En retard","🔵 En cours")))) -> —
A26: PRE-2027-023 | G26: =IF(F26="",0,F26*'⚙️ PARAMÈTRES'!B10) -> 0 | L26: =IF(F26="",0,F26*'⚙️ PARAMÈTRES'!B4) -> 0 | M26: =IF(F26="",0,F26*'⚙️ PARAMÈTRES'!B4*2) -> 0 | N26: =IF(OR(F26="",K26=""),0,IF(AND(R26<>"Soldé",TODAY()>K26+60),(F26-P26)*'⚙️ PARAMÈTRES'!B5*MAX(0,DATEDIF(K26,TODAY(),"M")-2),0)) -> 0 | O26: =IF(F26="",0,F26+G26+L26+N26) -> 0 | P26: =SUMIF('🔄 REMBOURSEMENTS'!B:B,A26,'🔄 REMBOURSEMENTS'!F:F) -> 0 | Q26: =MAX(0,O26-P26) -> 0 | R26: =IF(F26="","—",IF(Q26=0,"✅ Soldé",IF(AND(K26<>"",TODAY()>K26+60),"🔴 Impayé",IF(AND(K26<>"",TODAY()>K26),"⚠️ En retard","🔵 En cours")))) -> —
A27: PRE-2027-024 | G27: =IF(F27="",0,F27*'⚙️ PARAMÈTRES'!B10) -> 0 | L27: =IF(F27="",0,F27*'⚙️ PARAMÈTRES'!B4) -> 0 | M27: =IF(F27="",0,F27*'⚙️ PARAMÈTRES'!B4*2) -> 0 | N27: =IF(OR(F27="",K27=""),0,IF(AND(R27<>"Soldé",TODAY()>K27+60),(F27-P27)*'⚙️ PARAMÈTRES'!B5*MAX(0,DATEDIF(K27,TODAY(),"M")-2),0)) -> 0 | O27: =IF(F27="",0,F27+G27+L27+N27) -> 0 | P27: =SUMIF('🔄 REMBOURSEMENTS'!B:B,A27,'🔄 REMBOURSEMENTS'!F:F) -> 0 | Q27: =MAX(0,O27-P27) -> 0 | R27: =IF(F27="","—",IF(Q27=0,"✅ Soldé",IF(AND(K27<>"",TODAY()>K27+60),"🔴 Impayé",IF(AND(K27<>"",TODAY()>K27),"⚠️ En retard","🔵 En cours")))) -> —
A28: PRE-2027-025 | G28: =IF(F28="",0,F28*'⚙️ PARAMÈTRES'!B10) -> 0 | L28: =IF(F28="",0,F28*'⚙️ PARAMÈTRES'!B4) -> 0 | M28: =IF(F28="",0,F28*'⚙️ PARAMÈTRES'!B4*2) -> 0 | N28: =IF(OR(F28="",K28=""),0,IF(AND(R28<>"Soldé",TODAY()>K28+60),(F28-P28)*'⚙️ PARAMÈTRES'!B5*MAX(0,DATEDIF(K28,TODAY(),"M")-2),0)) -> 0 | O28: =IF(F28="",0,F28+G28+L28+N28) -> 0 | P28: =SUMIF('🔄 REMBOURSEMENTS'!B:B,A28,'🔄 REMBOURSEMENTS'!F:F) -> 0 | Q28: =MAX(0,O28-P28) -> 0 | R28: =IF(F28="","—",IF(Q28=0,"✅ Soldé",IF(AND(K28<>"",TODAY()>K28+60),"🔴 Impayé",IF(AND(K28<>"",TODAY()>K28),"⚠️ En retard","🔵 En cours")))) -> —
A29: PRE-2027-026 | G29: =IF(F29="",0,F29*'⚙️ PARAMÈTRES'!B10) -> 0 | L29: =IF(F29="",0,F29*'⚙️ PARAMÈTRES'!B4) -> 0 | M29: =IF(F29="",0,F29*'⚙️ PARAMÈTRES'!B4*2) -> 0 | N29: =IF(OR(F29="",K29=""),0,IF(AND(R29<>"Soldé",TODAY()>K29+60),(F29-P29)*'⚙️ PARAMÈTRES'!B5*MAX(0,DATEDIF(K29,TODAY(),"M")-2),0)) -> 0 | O29: =IF(F29="",0,F29+G29+L29+N29) -> 0 | P29: =SUMIF('🔄 REMBOURSEMENTS'!B:B,A29,'🔄 REMBOURSEMENTS'!F:F) -> 0 | Q29: =MAX(0,O29-P29) -> 0 | R29: =IF(F29="","—",IF(Q29=0,"✅ Soldé",IF(AND(K29<>"",TODAY()>K29+60),"🔴 Impayé",IF(AND(K29<>"",TODAY()>K29),"⚠️ En retard","🔵 En cours")))) -> —
A30: PRE-2027-027 | G30: =IF(F30="",0,F30*'⚙️ PARAMÈTRES'!B10) -> 0 | L30: =IF(F30="",0,F30*'⚙️ PARAMÈTRES'!B4) -> 0 | M30: =IF(F30="",0,F30*'⚙️ PARAMÈTRES'!B4*2) -> 0 | N30: =IF(OR(F30="",K30=""),0,IF(AND(R30<>"Soldé",TODAY()>K30+60),(F30-P30)*'⚙️ PARAMÈTRES'!B5*MAX(0,DATEDIF(K30,TODAY(),"M")-2),0)) -> 0 | O30: =IF(F30="",0,F30+G30+L30+N30) -> 0 | P30: =SUMIF('🔄 REMBOURSEMENTS'!B:B,A30,'🔄 REMBOURSEMENTS'!F:F) -> 0 | Q30: =MAX(0,O30-P30) -> 0 | R30: =IF(F30="","—",IF(Q30=0,"✅ Soldé",IF(AND(K30<>"",TODAY()>K30+60),"🔴 Impayé",IF(AND(K30<>"",TODAY()>K30),"⚠️ En retard","🔵 En cours")))) -> —
A31: PRE-2027-028 | G31: =IF(F31="",0,F31*'⚙️ PARAMÈTRES'!B10) -> 0 | L31: =IF(F31="",0,F31*'⚙️ PARAMÈTRES'!B4) -> 0 | M31: =IF(F31="",0,F31*'⚙️ PARAMÈTRES'!B4*2) -> 0 | N31: =IF(OR(F31="",K31=""),0,IF(AND(R31<>"Soldé",TODAY()>K31+60),(F31-P31)*'⚙️ PARAMÈTRES'!B5*MAX(0,DATEDIF(K31,TODAY(),"M")-2),0)) -> 0 | O31: =IF(F31="",0,F31+G31+L31+N31) -> 0 | P31: =SUMIF('🔄 REMBOURSEMENTS'!B:B,A31,'🔄 REMBOURSEMENTS'!F:F) -> 0 | Q31: =MAX(0,O31-P31) -> 0 | R31: =IF(F31="","—",IF(Q31=0,"✅ Soldé",IF(AND(K31<>"",TODAY()>K31+60),"🔴 Impayé",IF(AND(K31<>"",TODAY()>K31),"⚠️ En retard","🔵 En cours")))) -> —
A32: PRE-2027-029 | G32: =IF(F32="",0,F32*'⚙️ PARAMÈTRES'!B10) -> 0 | L32: =IF(F32="",0,F32*'⚙️ PARAMÈTRES'!B4) -> 0 | M32: =IF(F32="",0,F32*'⚙️ PARAMÈTRES'!B4*2) -> 0 | N32: =IF(OR(F32="",K32=""),0,IF(AND(R32<>"Soldé",TODAY()>K32+60),(F32-P32)*'⚙️ PARAMÈTRES'!B5*MAX(0,DATEDIF(K32,TODAY(),"M")-2),0)) -> 0 | O32: =IF(F32="",0,F32+G32+L32+N32) -> 0 | P32: =SUMIF('🔄 REMBOURSEMENTS'!B:B,A32,'🔄 REMBOURSEMENTS'!F:F) -> 0 | Q32: =MAX(0,O32-P32) -> 0 | R32: =IF(F32="","—",IF(Q32=0,"✅ Soldé",IF(AND(K32<>"",TODAY()>K32+60),"🔴 Impayé",IF(AND(K32<>"",TODAY()>K32),"⚠️ En retard","🔵 En cours")))) -> —
A33: PRE-2027-030 | G33: =IF(F33="",0,F33*'⚙️ PARAMÈTRES'!B10) -> 0 | L33: =IF(F33="",0,F33*'⚙️ PARAMÈTRES'!B4) -> 0 | M33: =IF(F33="",0,F33*'⚙️ PARAMÈTRES'!B4*2) -> 0 | N33: =IF(OR(F33="",K33=""),0,IF(AND(R33<>"Soldé",TODAY()>K33+60),(F33-P33)*'⚙️ PARAMÈTRES'!B5*MAX(0,DATEDIF(K33,TODAY(),"M")-2),0)) -> 0 | O33: =IF(F33="",0,F33+G33+L33+N33) -> 0 | P33: =SUMIF('🔄 REMBOURSEMENTS'!B:B,A33,'🔄 REMBOURSEMENTS'!F:F) -> 0 | Q33: =MAX(0,O33-P33) -> 0 | R33: =IF(F33="","—",IF(Q33=0,"✅ Soldé",IF(AND(K33<>"",TODAY()>K33+60),"🔴 Impayé",IF(AND(K33<>"",TODAY()>K33),"⚠️ En retard","🔵 En cours")))) -> —
A34: PRE-2027-031 | G34: =IF(F34="",0,F34*'⚙️ PARAMÈTRES'!B10) -> 0 | L34: =IF(F34="",0,F34*'⚙️ PARAMÈTRES'!B4) -> 0 | M34: =IF(F34="",0,F34*'⚙️ PARAMÈTRES'!B4*2) -> 0 | N34: =IF(OR(F34="",K34=""),0,IF(AND(R34<>"Soldé",TODAY()>K34+60),(F34-P34)*'⚙️ PARAMÈTRES'!B5*MAX(0,DATEDIF(K34,TODAY(),"M")-2),0)) -> 0 | O34: =IF(F34="",0,F34+G34+L34+N34) -> 0 | P34: =SUMIF('🔄 REMBOURSEMENTS'!B:B,A34,'🔄 REMBOURSEMENTS'!F:F) -> 0 | Q34: =MAX(0,O34-P34) -> 0 | R34: =IF(F34="","—",IF(Q34=0,"✅ Soldé",IF(AND(K34<>"",TODAY()>K34+60),"🔴 Impayé",IF(AND(K34<>"",TODAY()>K34),"⚠️ En retard","🔵 En cours")))) -> —
A35: PRE-2027-032 | G35: =IF(F35="",0,F35*'⚙️ PARAMÈTRES'!B10) -> 0 | L35: =IF(F35="",0,F35*'⚙️ PARAMÈTRES'!B4) -> 0 | M35: =IF(F35="",0,F35*'⚙️ PARAMÈTRES'!B4*2) -> 0 | N35: =IF(OR(F35="",K35=""),0,IF(AND(R35<>"Soldé",TODAY()>K35+60),(F35-P35)*'⚙️ PARAMÈTRES'!B5*MAX(0,DATEDIF(K35,TODAY(),"M")-2),0)) -> 0 | O35: =IF(F35="",0,F35+G35+L35+N35) -> 0 | P35: =SUMIF('🔄 REMBOURSEMENTS'!B:B,A35,'🔄 REMBOURSEMENTS'!F:F) -> 0 | Q35: =MAX(0,O35-P35) -> 0 | R35: =IF(F35="","—",IF(Q35=0,"✅ Soldé",IF(AND(K35<>"",TODAY()>K35+60),"🔴 Impayé",IF(AND(K35<>"",TODAY()>K35),"⚠️ En retard","🔵 En cours")))) -> —
A36: PRE-2027-033 | G36: =IF(F36="",0,F36*'⚙️ PARAMÈTRES'!B10) -> 0 | L36: =IF(F36="",0,F36*'⚙️ PARAMÈTRES'!B4) -> 0 | M36: =IF(F36="",0,F36*'⚙️ PARAMÈTRES'!B4*2) -> 0 | N36: =IF(OR(F36="",K36=""),0,IF(AND(R36<>"Soldé",TODAY()>K36+60),(F36-P36)*'⚙️ PARAMÈTRES'!B5*MAX(0,DATEDIF(K36,TODAY(),"M")-2),0)) -> 0 | O36: =IF(F36="",0,F36+G36+L36+N36) -> 0 | P36: =SUMIF('🔄 REMBOURSEMENTS'!B:B,A36,'🔄 REMBOURSEMENTS'!F:F) -> 0 | Q36: =MAX(0,O36-P36) -> 0 | R36: =IF(F36="","—",IF(Q36=0,"✅ Soldé",IF(AND(K36<>"",TODAY()>K36+60),"🔴 Impayé",IF(AND(K36<>"",TODAY()>K36),"⚠️ En retard","🔵 En cours")))) -> —
A37: PRE-2027-034 | G37: =IF(F37="",0,F37*'⚙️ PARAMÈTRES'!B10) -> 0 | L37: =IF(F37="",0,F37*'⚙️ PARAMÈTRES'!B4) -> 0 | M37: =IF(F37="",0,F37*'⚙️ PARAMÈTRES'!B4*2) -> 0 | N37: =IF(OR(F37="",K37=""),0,IF(AND(R37<>"Soldé",TODAY()>K37+60),(F37-P37)*'⚙️ PARAMÈTRES'!B5*MAX(0,DATEDIF(K37,TODAY(),"M")-2),0)) -> 0 | O37: =IF(F37="",0,F37+G37+L37+N37) -> 0 | P37: =SUMIF('🔄 REMBOURSEMENTS'!B:B,A37,'🔄 REMBOURSEMENTS'!F:F) -> 0 | Q37: =MAX(0,O37-P37) -> 0 | R37: =IF(F37="","—",IF(Q37=0,"✅ Soldé",IF(AND(K37<>"",TODAY()>K37+60),"🔴 Impayé",IF(AND(K37<>"",TODAY()>K37),"⚠️ En retard","🔵 En cours")))) -> —
A38: PRE-2027-035 | G38: =IF(F38="",0,F38*'⚙️ PARAMÈTRES'!B10) -> 0 | L38: =IF(F38="",0,F38*'⚙️ PARAMÈTRES'!B4) -> 0 | M38: =IF(F38="",0,F38*'⚙️ PARAMÈTRES'!B4*2) -> 0 | N38: =IF(OR(F38="",K38=""),0,IF(AND(R38<>"Soldé",TODAY()>K38+60),(F38-P38)*'⚙️ PARAMÈTRES'!B5*MAX(0,DATEDIF(K38,TODAY(),"M")-2),0)) -> 0 | O38: =IF(F38="",0,F38+G38+L38+N38) -> 0 | P38: =SUMIF('🔄 REMBOURSEMENTS'!B:B,A38,'🔄 REMBOURSEMENTS'!F:F) -> 0 | Q38: =MAX(0,O38-P38) -> 0 | R38: =IF(F38="","—",IF(Q38=0,"✅ Soldé",IF(AND(K38<>"",TODAY()>K38+60),"🔴 Impayé",IF(AND(K38<>"",TODAY()>K38),"⚠️ En retard","🔵 En cours")))) -> —
A39: PRE-2027-036 | G39: =IF(F39="",0,F39*'⚙️ PARAMÈTRES'!B10) -> 0 | L39: =IF(F39="",0,F39*'⚙️ PARAMÈTRES'!B4) -> 0 | M39: =IF(F39="",0,F39*'⚙️ PARAMÈTRES'!B4*2) -> 0 | N39: =IF(OR(F39="",K39=""),0,IF(AND(R39<>"Soldé",TODAY()>K39+60),(F39-P39)*'⚙️ PARAMÈTRES'!B5*MAX(0,DATEDIF(K39,TODAY(),"M")-2),0)) -> 0 | O39: =IF(F39="",0,F39+G39+L39+N39) -> 0 | P39: =SUMIF('🔄 REMBOURSEMENTS'!B:B,A39,'🔄 REMBOURSEMENTS'!F:F) -> 0 | Q39: =MAX(0,O39-P39) -> 0 | R39: =IF(F39="","—",IF(Q39=0,"✅ Soldé",IF(AND(K39<>"",TODAY()>K39+60),"🔴 Impayé",IF(AND(K39<>"",TODAY()>K39),"⚠️ En retard","🔵 En cours")))) -> —
A40: PRE-2027-037 | G40: =IF(F40="",0,F40*'⚙️ PARAMÈTRES'!B10) -> 0 | L40: =IF(F40="",0,F40*'⚙️ PARAMÈTRES'!B4) -> 0 | M40: =IF(F40="",0,F40*'⚙️ PARAMÈTRES'!B4*2) -> 0 | N40: =IF(OR(F40="",K40=""),0,IF(AND(R40<>"Soldé",TODAY()>K40+60),(F40-P40)*'⚙️ PARAMÈTRES'!B5*MAX(0,DATEDIF(K40,TODAY(),"M")-2),0)) -> 0 | O40: =IF(F40="",0,F40+G40+L40+N40) -> 0 | P40: =SUMIF('🔄 REMBOURSEMENTS'!B:B,A40,'🔄 REMBOURSEMENTS'!F:F) -> 0 | Q40: =MAX(0,O40-P40) -> 0 | R40: =IF(F40="","—",IF(Q40=0,"✅ Soldé",IF(AND(K40<>"",TODAY()>K40+60),"🔴 Impayé",IF(AND(K40<>"",TODAY()>K40),"⚠️ En retard","🔵 En cours")))) -> —
A41: PRE-2027-038 | G41: =IF(F41="",0,F41*'⚙️ PARAMÈTRES'!B10) -> 0 | L41: =IF(F41="",0,F41*'⚙️ PARAMÈTRES'!B4) -> 0 | M41: =IF(F41="",0,F41*'⚙️ PARAMÈTRES'!B4*2) -> 0 | N41: =IF(OR(F41="",K41=""),0,IF(AND(R41<>"Soldé",TODAY()>K41+60),(F41-P41)*'⚙️ PARAMÈTRES'!B5*MAX(0,DATEDIF(K41,TODAY(),"M")-2),0)) -> 0 | O41: =IF(F41="",0,F41+G41+L41+N41) -> 0 | P41: =SUMIF('🔄 REMBOURSEMENTS'!B:B,A41,'🔄 REMBOURSEMENTS'!F:F) -> 0 | Q41: =MAX(0,O41-P41) -> 0 | R41: =IF(F41="","—",IF(Q41=0,"✅ Soldé",IF(AND(K41<>"",TODAY()>K41+60),"🔴 Impayé",IF(AND(K41<>"",TODAY()>K41),"⚠️ En retard","🔵 En cours")))) -> —
A42: PRE-2027-039 | G42: =IF(F42="",0,F42*'⚙️ PARAMÈTRES'!B10) -> 0 | L42: =IF(F42="",0,F42*'⚙️ PARAMÈTRES'!B4) -> 0 | M42: =IF(F42="",0,F42*'⚙️ PARAMÈTRES'!B4*2) -> 0 | N42: =IF(OR(F42="",K42=""),0,IF(AND(R42<>"Soldé",TODAY()>K42+60),(F42-P42)*'⚙️ PARAMÈTRES'!B5*MAX(0,DATEDIF(K42,TODAY(),"M")-2),0)) -> 0 | O42: =IF(F42="",0,F42+G42+L42+N42) -> 0 | P42: =SUMIF('🔄 REMBOURSEMENTS'!B:B,A42,'🔄 REMBOURSEMENTS'!F:F) -> 0 | Q42: =MAX(0,O42-P42) -> 0 | R42: =IF(F42="","—",IF(Q42=0,"✅ Soldé",IF(AND(K42<>"",TODAY()>K42+60),"🔴 Impayé",IF(AND(K42<>"",TODAY()>K42),"⚠️ En retard","🔵 En cours")))) -> —
A43: PRE-2027-040 | G43: =IF(F43="",0,F43*'⚙️ PARAMÈTRES'!B10) -> 0 | L43: =IF(F43="",0,F43*'⚙️ PARAMÈTRES'!B4) -> 0 | M43: =IF(F43="",0,F43*'⚙️ PARAMÈTRES'!B4*2) -> 0 | N43: =IF(OR(F43="",K43=""),0,IF(AND(R43<>"Soldé",TODAY()>K43+60),(F43-P43)*'⚙️ PARAMÈTRES'!B5*MAX(0,DATEDIF(K43,TODAY(),"M")-2),0)) -> 0 | O43: =IF(F43="",0,F43+G43+L43+N43) -> 0 | P43: =SUMIF('🔄 REMBOURSEMENTS'!B:B,A43,'🔄 REMBOURSEMENTS'!F:F) -> 0 | Q43: =MAX(0,O43-P43) -> 0 | R43: =IF(F43="","—",IF(Q43=0,"✅ Soldé",IF(AND(K43<>"",TODAY()>K43+60),"🔴 Impayé",IF(AND(K43<>"",TODAY()>K43),"⚠️ En retard","🔵 En cours")))) -> —
A44: PRE-2027-041 | G44: =IF(F44="",0,F44*'⚙️ PARAMÈTRES'!B10) -> 0 | L44: =IF(F44="",0,F44*'⚙️ PARAMÈTRES'!B4) -> 0 | M44: =IF(F44="",0,F44*'⚙️ PARAMÈTRES'!B4*2) -> 0 | N44: =IF(OR(F44="",K44=""),0,IF(AND(R44<>"Soldé",TODAY()>K44+60),(F44-P44)*'⚙️ PARAMÈTRES'!B5*MAX(0,DATEDIF(K44,TODAY(),"M")-2),0)) -> 0 | O44: =IF(F44="",0,F44+G44+L44+N44) -> 0 | P44: =SUMIF('🔄 REMBOURSEMENTS'!B:B,A44,'🔄 REMBOURSEMENTS'!F:F) -> 0 | Q44: =MAX(0,O44-P44) -> 0 | R44: =IF(F44="","—",IF(Q44=0,"✅ Soldé",IF(AND(K44<>"",TODAY()>K44+60),"🔴 Impayé",IF(AND(K44<>"",TODAY()>K44),"⚠️ En retard","🔵 En cours")))) -> —
A45: PRE-2027-042 | G45: =IF(F45="",0,F45*'⚙️ PARAMÈTRES'!B10) -> 0 | L45: =IF(F45="",0,F45*'⚙️ PARAMÈTRES'!B4) -> 0 | M45: =IF(F45="",0,F45*'⚙️ PARAMÈTRES'!B4*2) -> 0 | N45: =IF(OR(F45="",K45=""),0,IF(AND(R45<>"Soldé",TODAY()>K45+60),(F45-P45)*'⚙️ PARAMÈTRES'!B5*MAX(0,DATEDIF(K45,TODAY(),"M")-2),0)) -> 0 | O45: =IF(F45="",0,F45+G45+L45+N45) -> 0 | P45: =SUMIF('🔄 REMBOURSEMENTS'!B:B,A45,'🔄 REMBOURSEMENTS'!F:F) -> 0 | Q45: =MAX(0,O45-P45) -> 0 | R45: =IF(F45="","—",IF(Q45=0,"✅ Soldé",IF(AND(K45<>"",TODAY()>K45+60),"🔴 Impayé",IF(AND(K45<>"",TODAY()>K45),"⚠️ En retard","🔵 En cours")))) -> —
A46: PRE-2027-043 | G46: =IF(F46="",0,F46*'⚙️ PARAMÈTRES'!B10) -> 0 | L46: =IF(F46="",0,F46*'⚙️ PARAMÈTRES'!B4) -> 0 | M46: =IF(F46="",0,F46*'⚙️ PARAMÈTRES'!B4*2) -> 0 | N46: =IF(OR(F46="",K46=""),0,IF(AND(R46<>"Soldé",TODAY()>K46+60),(F46-P46)*'⚙️ PARAMÈTRES'!B5*MAX(0,DATEDIF(K46,TODAY(),"M")-2),0)) -> 0 | O46: =IF(F46="",0,F46+G46+L46+N46) -> 0 | P46: =SUMIF('🔄 REMBOURSEMENTS'!B:B,A46,'🔄 REMBOURSEMENTS'!F:F) -> 0 | Q46: =MAX(0,O46-P46) -> 0 | R46: =IF(F46="","—",IF(Q46=0,"✅ Soldé",IF(AND(K46<>"",TODAY()>K46+60),"🔴 Impayé",IF(AND(K46<>"",TODAY()>K46),"⚠️ En retard","🔵 En cours")))) -> —
A47: PRE-2027-044 | G47: =IF(F47="",0,F47*'⚙️ PARAMÈTRES'!B10) -> 0 | L47: =IF(F47="",0,F47*'⚙️ PARAMÈTRES'!B4) -> 0 | M47: =IF(F47="",0,F47*'⚙️ PARAMÈTRES'!B4*2) -> 0 | N47: =IF(OR(F47="",K47=""),0,IF(AND(R47<>"Soldé",TODAY()>K47+60),(F47-P47)*'⚙️ PARAMÈTRES'!B5*MAX(0,DATEDIF(K47,TODAY(),"M")-2),0)) -> 0 | O47: =IF(F47="",0,F47+G47+L47+N47) -> 0 | P47: =SUMIF('🔄 REMBOURSEMENTS'!B:B,A47,'🔄 REMBOURSEMENTS'!F:F) -> 0 | Q47: =MAX(0,O47-P47) -> 0 | R47: =IF(F47="","—",IF(Q47=0,"✅ Soldé",IF(AND(K47<>"",TODAY()>K47+60),"🔴 Impayé",IF(AND(K47<>"",TODAY()>K47),"⚠️ En retard","🔵 En cours")))) -> —
A48: PRE-2027-045 | G48: =IF(F48="",0,F48*'⚙️ PARAMÈTRES'!B10) -> 0 | L48: =IF(F48="",0,F48*'⚙️ PARAMÈTRES'!B4) -> 0 | M48: =IF(F48="",0,F48*'⚙️ PARAMÈTRES'!B4*2) -> 0 | N48: =IF(OR(F48="",K48=""),0,IF(AND(R48<>"Soldé",TODAY()>K48+60),(F48-P48)*'⚙️ PARAMÈTRES'!B5*MAX(0,DATEDIF(K48,TODAY(),"M")-2),0)) -> 0 | O48: =IF(F48="",0,F48+G48+L48+N48) -> 0 | P48: =SUMIF('🔄 REMBOURSEMENTS'!B:B,A48,'🔄 REMBOURSEMENTS'!F:F) -> 0 | Q48: =MAX(0,O48-P48) -> 0 | R48: =IF(F48="","—",IF(Q48=0,"✅ Soldé",IF(AND(K48<>"",TODAY()>K48+60),"🔴 Impayé",IF(AND(K48<>"",TODAY()>K48),"⚠️ En retard","🔵 En cours")))) -> —
A49: PRE-2027-046 | G49: =IF(F49="",0,F49*'⚙️ PARAMÈTRES'!B10) -> 0 | L49: =IF(F49="",0,F49*'⚙️ PARAMÈTRES'!B4) -> 0 | M49: =IF(F49="",0,F49*'⚙️ PARAMÈTRES'!B4*2) -> 0 | N49: =IF(OR(F49="",K49=""),0,IF(AND(R49<>"Soldé",TODAY()>K49+60),(F49-P49)*'⚙️ PARAMÈTRES'!B5*MAX(0,DATEDIF(K49,TODAY(),"M")-2),0)) -> 0 | O49: =IF(F49="",0,F49+G49+L49+N49) -> 0 | P49: =SUMIF('🔄 REMBOURSEMENTS'!B:B,A49,'🔄 REMBOURSEMENTS'!F:F) -> 0 | Q49: =MAX(0,O49-P49) -> 0 | R49: =IF(F49="","—",IF(Q49=0,"✅ Soldé",IF(AND(K49<>"",TODAY()>K49+60),"🔴 Impayé",IF(AND(K49<>"",TODAY()>K49),"⚠️ En retard","🔵 En cours")))) -> —
A50: PRE-2027-047 | G50: =IF(F50="",0,F50*'⚙️ PARAMÈTRES'!B10) -> 0 | L50: =IF(F50="",0,F50*'⚙️ PARAMÈTRES'!B4) -> 0 | M50: =IF(F50="",0,F50*'⚙️ PARAMÈTRES'!B4*2) -> 0 | N50: =IF(OR(F50="",K50=""),0,IF(AND(R50<>"Soldé",TODAY()>K50+60),(F50-P50)*'⚙️ PARAMÈTRES'!B5*MAX(0,DATEDIF(K50,TODAY(),"M")-2),0)) -> 0 | O50: =IF(F50="",0,F50+G50+L50+N50) -> 0 | P50: =SUMIF('🔄 REMBOURSEMENTS'!B:B,A50,'🔄 REMBOURSEMENTS'!F:F) -> 0 | Q50: =MAX(0,O50-P50) -> 0 | R50: =IF(F50="","—",IF(Q50=0,"✅ Soldé",IF(AND(K50<>"",TODAY()>K50+60),"🔴 Impayé",IF(AND(K50<>"",TODAY()>K50),"⚠️ En retard","🔵 En cours")))) -> —
A51: PRE-2027-048 | G51: =IF(F51="",0,F51*'⚙️ PARAMÈTRES'!B10) -> 0 | L51: =IF(F51="",0,F51*'⚙️ PARAMÈTRES'!B4) -> 0 | M51: =IF(F51="",0,F51*'⚙️ PARAMÈTRES'!B4*2) -> 0 | N51: =IF(OR(F51="",K51=""),0,IF(AND(R51<>"Soldé",TODAY()>K51+60),(F51-P51)*'⚙️ PARAMÈTRES'!B5*MAX(0,DATEDIF(K51,TODAY(),"M")-2),0)) -> 0 | O51: =IF(F51="",0,F51+G51+L51+N51) -> 0 | P51: =SUMIF('🔄 REMBOURSEMENTS'!B:B,A51,'🔄 REMBOURSEMENTS'!F:F) -> 0 | Q51: =MAX(0,O51-P51) -> 0 | R51: =IF(F51="","—",IF(Q51=0,"✅ Soldé",IF(AND(K51<>"",TODAY()>K51+60),"🔴 Impayé",IF(AND(K51<>"",TODAY()>K51),"⚠️ En retard","🔵 En cours")))) -> —
A52: PRE-2027-049 | G52: =IF(F52="",0,F52*'⚙️ PARAMÈTRES'!B10) -> 0 | L52: =IF(F52="",0,F52*'⚙️ PARAMÈTRES'!B4) -> 0 | M52: =IF(F52="",0,F52*'⚙️ PARAMÈTRES'!B4*2) -> 0 | N52: =IF(OR(F52="",K52=""),0,IF(AND(R52<>"Soldé",TODAY()>K52+60),(F52-P52)*'⚙️ PARAMÈTRES'!B5*MAX(0,DATEDIF(K52,TODAY(),"M")-2),0)) -> 0 | O52: =IF(F52="",0,F52+G52+L52+N52) -> 0 | P52: =SUMIF('🔄 REMBOURSEMENTS'!B:B,A52,'🔄 REMBOURSEMENTS'!F:F) -> 0 | Q52: =MAX(0,O52-P52) -> 0 | R52: =IF(F52="","—",IF(Q52=0,"✅ Soldé",IF(AND(K52<>"",TODAY()>K52+60),"🔴 Impayé",IF(AND(K52<>"",TODAY()>K52),"⚠️ En retard","🔵 En cours")))) -> —
A53: PRE-2027-050 | G53: =IF(F53="",0,F53*'⚙️ PARAMÈTRES'!B10) -> 0 | L53: =IF(F53="",0,F53*'⚙️ PARAMÈTRES'!B4) -> 0 | M53: =IF(F53="",0,F53*'⚙️ PARAMÈTRES'!B4*2) -> 0 | N53: =IF(OR(F53="",K53=""),0,IF(AND(R53<>"Soldé",TODAY()>K53+60),(F53-P53)*'⚙️ PARAMÈTRES'!B5*MAX(0,DATEDIF(K53,TODAY(),"M")-2),0)) -> 0 | O53: =IF(F53="",0,F53+G53+L53+N53) -> 0 | P53: =SUMIF('🔄 REMBOURSEMENTS'!B:B,A53,'🔄 REMBOURSEMENTS'!F:F) -> 0 | Q53: =MAX(0,O53-P53) -> 0 | R53: =IF(F53="","—",IF(Q53=0,"✅ Soldé",IF(AND(K53<>"",TODAY()>K53+60),"🔴 Impayé",IF(AND(K53<>"",TODAY()>K53),"⚠️ En retard","🔵 En cours")))) -> —
A54: PRE-2027-051 | G54: =IF(F54="",0,F54*'⚙️ PARAMÈTRES'!B10) -> 0 | L54: =IF(F54="",0,F54*'⚙️ PARAMÈTRES'!B4) -> 0 | M54: =IF(F54="",0,F54*'⚙️ PARAMÈTRES'!B4*2) -> 0 | N54: =IF(OR(F54="",K54=""),0,IF(AND(R54<>"Soldé",TODAY()>K54+60),(F54-P54)*'⚙️ PARAMÈTRES'!B5*MAX(0,DATEDIF(K54,TODAY(),"M")-2),0)) -> 0 | O54: =IF(F54="",0,F54+G54+L54+N54) -> 0 | P54: =SUMIF('🔄 REMBOURSEMENTS'!B:B,A54,'🔄 REMBOURSEMENTS'!F:F) -> 0 | Q54: =MAX(0,O54-P54) -> 0 | R54: =IF(F54="","—",IF(Q54=0,"✅ Soldé",IF(AND(K54<>"",TODAY()>K54+60),"🔴 Impayé",IF(AND(K54<>"",TODAY()>K54),"⚠️ En retard","🔵 En cours")))) -> —
A55: PRE-2027-052 | G55: =IF(F55="",0,F55*'⚙️ PARAMÈTRES'!B10) -> 0 | L55: =IF(F55="",0,F55*'⚙️ PARAMÈTRES'!B4) -> 0 | M55: =IF(F55="",0,F55*'⚙️ PARAMÈTRES'!B4*2) -> 0 | N55: =IF(OR(F55="",K55=""),0,IF(AND(R55<>"Soldé",TODAY()>K55+60),(F55-P55)*'⚙️ PARAMÈTRES'!B5*MAX(0,DATEDIF(K55,TODAY(),"M")-2),0)) -> 0 | O55: =IF(F55="",0,F55+G55+L55+N55) -> 0 | P55: =SUMIF('🔄 REMBOURSEMENTS'!B:B,A55,'🔄 REMBOURSEMENTS'!F:F) -> 0 | Q55: =MAX(0,O55-P55) -> 0 | R55: =IF(F55="","—",IF(Q55=0,"✅ Soldé",IF(AND(K55<>"",TODAY()>K55+60),"🔴 Impayé",IF(AND(K55<>"",TODAY()>K55),"⚠️ En retard","🔵 En cours")))) -> —
A56: PRE-2027-053 | G56: =IF(F56="",0,F56*'⚙️ PARAMÈTRES'!B10) -> 0 | L56: =IF(F56="",0,F56*'⚙️ PARAMÈTRES'!B4) -> 0 | M56: =IF(F56="",0,F56*'⚙️ PARAMÈTRES'!B4*2) -> 0 | N56: =IF(OR(F56="",K56=""),0,IF(AND(R56<>"Soldé",TODAY()>K56+60),(F56-P56)*'⚙️ PARAMÈTRES'!B5*MAX(0,DATEDIF(K56,TODAY(),"M")-2),0)) -> 0 | O56: =IF(F56="",0,F56+G56+L56+N56) -> 0 | P56: =SUMIF('🔄 REMBOURSEMENTS'!B:B,A56,'🔄 REMBOURSEMENTS'!F:F) -> 0 | Q56: =MAX(0,O56-P56) -> 0 | R56: =IF(F56="","—",IF(Q56=0,"✅ Soldé",IF(AND(K56<>"",TODAY()>K56+60),"🔴 Impayé",IF(AND(K56<>"",TODAY()>K56),"⚠️ En retard","🔵 En cours")))) -> —
A57: PRE-2027-054 | G57: =IF(F57="",0,F57*'⚙️ PARAMÈTRES'!B10) -> 0 | L57: =IF(F57="",0,F57*'⚙️ PARAMÈTRES'!B4) -> 0 | M57: =IF(F57="",0,F57*'⚙️ PARAMÈTRES'!B4*2) -> 0 | N57: =IF(OR(F57="",K57=""),0,IF(AND(R57<>"Soldé",TODAY()>K57+60),(F57-P57)*'⚙️ PARAMÈTRES'!B5*MAX(0,DATEDIF(K57,TODAY(),"M")-2),0)) -> 0 | O57: =IF(F57="",0,F57+G57+L57+N57) -> 0 | P57: =SUMIF('🔄 REMBOURSEMENTS'!B:B,A57,'🔄 REMBOURSEMENTS'!F:F) -> 0 | Q57: =MAX(0,O57-P57) -> 0 | R57: =IF(F57="","—",IF(Q57=0,"✅ Soldé",IF(AND(K57<>"",TODAY()>K57+60),"🔴 Impayé",IF(AND(K57<>"",TODAY()>K57),"⚠️ En retard","🔵 En cours")))) -> —
A58: PRE-2027-055 | G58: =IF(F58="",0,F58*'⚙️ PARAMÈTRES'!B10) -> 0 | L58: =IF(F58="",0,F58*'⚙️ PARAMÈTRES'!B4) -> 0 | M58: =IF(F58="",0,F58*'⚙️ PARAMÈTRES'!B4*2) -> 0 | N58: =IF(OR(F58="",K58=""),0,IF(AND(R58<>"Soldé",TODAY()>K58+60),(F58-P58)*'⚙️ PARAMÈTRES'!B5*MAX(0,DATEDIF(K58,TODAY(),"M")-2),0)) -> 0 | O58: =IF(F58="",0,F58+G58+L58+N58) -> 0 | P58: =SUMIF('🔄 REMBOURSEMENTS'!B:B,A58,'🔄 REMBOURSEMENTS'!F:F) -> 0 | Q58: =MAX(0,O58-P58) -> 0 | R58: =IF(F58="","—",IF(Q58=0,"✅ Soldé",IF(AND(K58<>"",TODAY()>K58+60),"🔴 Impayé",IF(AND(K58<>"",TODAY()>K58),"⚠️ En retard","🔵 En cours")))) -> —
A59: PRE-2027-056 | G59: =IF(F59="",0,F59*'⚙️ PARAMÈTRES'!B10) -> 0 | L59: =IF(F59="",0,F59*'⚙️ PARAMÈTRES'!B4) -> 0 | M59: =IF(F59="",0,F59*'⚙️ PARAMÈTRES'!B4*2) -> 0 | N59: =IF(OR(F59="",K59=""),0,IF(AND(R59<>"Soldé",TODAY()>K59+60),(F59-P59)*'⚙️ PARAMÈTRES'!B5*MAX(0,DATEDIF(K59,TODAY(),"M")-2),0)) -> 0 | O59: =IF(F59="",0,F59+G59+L59+N59) -> 0 | P59: =SUMIF('🔄 REMBOURSEMENTS'!B:B,A59,'🔄 REMBOURSEMENTS'!F:F) -> 0 | Q59: =MAX(0,O59-P59) -> 0 | R59: =IF(F59="","—",IF(Q59=0,"✅ Soldé",IF(AND(K59<>"",TODAY()>K59+60),"🔴 Impayé",IF(AND(K59<>"",TODAY()>K59),"⚠️ En retard","🔵 En cours")))) -> —
A60: PRE-2027-057 | G60: =IF(F60="",0,F60*'⚙️ PARAMÈTRES'!B10) -> 0 | L60: =IF(F60="",0,F60*'⚙️ PARAMÈTRES'!B4) -> 0 | M60: =IF(F60="",0,F60*'⚙️ PARAMÈTRES'!B4*2) -> 0 | N60: =IF(OR(F60="",K60=""),0,IF(AND(R60<>"Soldé",TODAY()>K60+60),(F60-P60)*'⚙️ PARAMÈTRES'!B5*MAX(0,DATEDIF(K60,TODAY(),"M")-2),0)) -> 0 | O60: =IF(F60="",0,F60+G60+L60+N60) -> 0 | P60: =SUMIF('🔄 REMBOURSEMENTS'!B:B,A60,'🔄 REMBOURSEMENTS'!F:F) -> 0 | Q60: =MAX(0,O60-P60) -> 0 | R60: =IF(F60="","—",IF(Q60=0,"✅ Soldé",IF(AND(K60<>"",TODAY()>K60+60),"🔴 Impayé",IF(AND(K60<>"",TODAY()>K60),"⚠️ En retard","🔵 En cours")))) -> —
A61: PRE-2027-058 | G61: =IF(F61="",0,F61*'⚙️ PARAMÈTRES'!B10) -> 0 | L61: =IF(F61="",0,F61*'⚙️ PARAMÈTRES'!B4) -> 0 | M61: =IF(F61="",0,F61*'⚙️ PARAMÈTRES'!B4*2) -> 0 | N61: =IF(OR(F61="",K61=""),0,IF(AND(R61<>"Soldé",TODAY()>K61+60),(F61-P61)*'⚙️ PARAMÈTRES'!B5*MAX(0,DATEDIF(K61,TODAY(),"M")-2),0)) -> 0 | O61: =IF(F61="",0,F61+G61+L61+N61) -> 0 | P61: =SUMIF('🔄 REMBOURSEMENTS'!B:B,A61,'🔄 REMBOURSEMENTS'!F:F) -> 0 | Q61: =MAX(0,O61-P61) -> 0 | R61: =IF(F61="","—",IF(Q61=0,"✅ Soldé",IF(AND(K61<>"",TODAY()>K61+60),"🔴 Impayé",IF(AND(K61<>"",TODAY()>K61),"⚠️ En retard","🔵 En cours")))) -> —
A62: PRE-2027-059 | G62: =IF(F62="",0,F62*'⚙️ PARAMÈTRES'!B10) -> 0 | L62: =IF(F62="",0,F62*'⚙️ PARAMÈTRES'!B4) -> 0 | M62: =IF(F62="",0,F62*'⚙️ PARAMÈTRES'!B4*2) -> 0 | N62: =IF(OR(F62="",K62=""),0,IF(AND(R62<>"Soldé",TODAY()>K62+60),(F62-P62)*'⚙️ PARAMÈTRES'!B5*MAX(0,DATEDIF(K62,TODAY(),"M")-2),0)) -> 0 | O62: =IF(F62="",0,F62+G62+L62+N62) -> 0 | P62: =SUMIF('🔄 REMBOURSEMENTS'!B:B,A62,'🔄 REMBOURSEMENTS'!F:F) -> 0 | Q62: =MAX(0,O62-P62) -> 0 | R62: =IF(F62="","—",IF(Q62=0,"✅ Soldé",IF(AND(K62<>"",TODAY()>K62+60),"🔴 Impayé",IF(AND(K62<>"",TODAY()>K62),"⚠️ En retard","🔵 En cours")))) -> —
A63: PRE-2027-060 | G63: =IF(F63="",0,F63*'⚙️ PARAMÈTRES'!B10) -> 0 | L63: =IF(F63="",0,F63*'⚙️ PARAMÈTRES'!B4) -> 0 | M63: =IF(F63="",0,F63*'⚙️ PARAMÈTRES'!B4*2) -> 0 | N63: =IF(OR(F63="",K63=""),0,IF(AND(R63<>"Soldé",TODAY()>K63+60),(F63-P63)*'⚙️ PARAMÈTRES'!B5*MAX(0,DATEDIF(K63,TODAY(),"M")-2),0)) -> 0 | O63: =IF(F63="",0,F63+G63+L63+N63) -> 0 | P63: =SUMIF('🔄 REMBOURSEMENTS'!B:B,A63,'🔄 REMBOURSEMENTS'!F:F) -> 0 | Q63: =MAX(0,O63-P63) -> 0 | R63: =IF(F63="","—",IF(Q63=0,"✅ Soldé",IF(AND(K63<>"",TODAY()>K63+60),"🔴 Impayé",IF(AND(K63<>"",TODAY()>K63),"⚠️ En retard","🔵 En cours")))) -> —
A64: 🏦 TOTAUX | F64: =SUM(F4:F63) -> 0 | G64: =SUM(G4:G63) -> 0 | L64: =SUM(L4:L63) -> 0 | M64: =SUM(M4:M63) -> 0 | N64: =SUM(N4:N63) -> 0 | O64: =SUM(O4:O63) -> 0 | P64: =SUM(P4:P63) -> 0 | Q64: =SUM(Q4:Q63) -> 0

Sheet 🔄 REMBOURSEMENTS
A1: 🔄 SUIVI DES REMBOURSEMENTS — TONTINE SOLIDARITÉ PLUS 2027
A3: ID_REM | B3: ID_PRÊT | C3: ID_MEMBRE | D3: NOM | E3: PRÉNOMS | F3: DATE REMB. | G3: MONTANT REMB. | H3: CAPITAL | I3: INTÉRÊTS | J3: SOLDE RESTANT | K3: STATUT | L3: SAISI PAR
A4: REM-2027-001 | C4: =IF(B4="","",IFERROR(VLOOKUP(B4,'🏦 PRÊTS'!A:B,2,0),"?")) | E4: =IF(B4="","",IFERROR(VLOOKUP(B4,'🏦 PRÊTS'!A:D,4,0),"?")) | J4: =IF(B4="","",IFERROR(VLOOKUP(B4,'🏦 PRÊTS'!A:Q,17,0),"")) | K4: =IF(J4="","—",IF(J4=0,"✅ K8Soldé","🔄 Partiel")) -> —
A5: REM-2027-002 | C5: =IF(B5="","",IFERROR(VLOOKUP(B5,'🏦 PRÊTS'!A:B,2,0),"?")) | D5: =IF(B5="","",IFERROR(VLOOKUP(B5,'🏦 PRÊTS'!A:C,3,0),"?")) | E5: =IF(B5="","",IFERROR(VLOOKUP(B5,'🏦 PRÊTS'!A:D,4,0),"?")) | J5: =IF(B5="","",IFERROR(VLOOKUP(B5,'🏦 PRÊTS'!A:Q,17,0),"")) | K5: =IF(J5="","—",IF(J5=0,"✅ Soldé","🔄 Partiel")) -> —
A6: REM-2027-003 | C6: =IF(B6="","",IFERROR(VLOOKUP(B6,'🏦 PRÊTS'!A:B,2,0),"?")) | D6: =IF(B6="","",IFERROR(VLOOKUP(B6,'🏦 PRÊTS'!A:C,3,0),"?")) | E6: =IF(B6="","",IFERROR(VLOOKUP(B6,'🏦 PRÊTS'!A:D,4,0),"?")) | J6: =IF(B6="","",IFERROR(VLOOKUP(B6,'🏦 PRÊTS'!A:Q,17,0),"")) | K6: =IF(J6="","—",IF(J6=0,"✅ Soldé","🔄 Partiel")) -> —
A7: REM-2027-004 | C7: =IF(B7="","",IFERROR(VLOOKUP(B7,'🏦 PRÊTS'!A:B,2,0),"?")) | D7: =IF(B7="","",IFERROR(VLOOKUP(B7,'🏦 PRÊTS'!A:C,3,0),"?")) | E7: =IF(B7="","",IFERROR(VLOOKUP(B7,'🏦 PRÊTS'!A:D,4,0),"?")) | J7: =IF(B7="","",IFERROR(VLOOKUP(B7,'🏦 PRÊTS'!A:Q,17,0),"")) | K7: =IF(J7="","—",IF(J7=0,"✅ Soldé","🔄 Partiel")) -> —
A8: REM-2027-005 | C8: =IF(B8="","",IFERROR(VLOOKUP(B8,'🏦 PRÊTS'!A:B,2,0),"?")) | D8: =IF(B8="","",IFERROR(VLOOKUP(B8,'🏦 PRÊTS'!A:C,3,0),"?")) | E8: =IF(B8="","",IFERROR(VLOOKUP(B8,'🏦 PRÊTS'!A:D,4,0),"?")) | J8: =IF(B8="","",IFERROR(VLOOKUP(B8,'🏦 PRÊTS'!A:Q,17,0),"")) | K8: =IF(J8="","—",IF(J8=0,"✅ Soldé","🔄 Partiel")) -> —
A9: REM-2027-006 | C9: =IF(B9="","",IFERROR(VLOOKUP(B9,'🏦 PRÊTS'!A:B,2,0),"?")) | D9: =IF(B9="","",IFERROR(VLOOKUP(B9,'🏦 PRÊTS'!A:C,3,0),"?")) | E9: =IF(B9="","",IFERROR(VLOOKUP(B9,'🏦 PRÊTS'!A:D,4,0),"?")) | J9: =IF(B9="","",IFERROR(VLOOKUP(B9,'🏦 PRÊTS'!A:Q,17,0),"")) | K9: =IF(J9="","—",IF(J9=0,"✅ Soldé","🔄 Partiel")) -> —
A10: REM-2027-007 | C10: =IF(B10="","",IFERROR(VLOOKUP(B10,'🏦 PRÊTS'!A:B,2,0),"?")) | D10: =IF(B10="","",IFERROR(VLOOKUP(B10,'🏦 PRÊTS'!A:C,3,0),"?")) | E10: =IF(B10="","",IFERROR(VLOOKUP(B10,'🏦 PRÊTS'!A:D,4,0),"?")) | J10: =IF(B10="","",IFERROR(VLOOKUP(B10,'🏦 PRÊTS'!A:Q,17,0),"")) | K10: =IF(J10="","—",IF(J10=0,"✅ Soldé","🔄 Partiel")) -> —
A11: REM-2027-008 | C11: =IF(B11="","",IFERROR(VLOOKUP(B11,'🏦 PRÊTS'!A:B,2,0),"?")) | D11: =IF(B11="","",IFERROR(VLOOKUP(B11,'🏦 PRÊTS'!A:C,3,0),"?")) | E11: =IF(B11="","",IFERROR(VLOOKUP(B11,'🏦 PRÊTS'!A:D,4,0),"?")) | J11: =IF(B11="","",IFERROR(VLOOKUP(B11,'🏦 PRÊTS'!A:Q,17,0),"")) | K11: =IF(J11="","—",IF(J11=0,"✅ Soldé","🔄 Partiel")) -> —
A12: REM-2027-009 | C12: =IF(B12="","",IFERROR(VLOOKUP(B12,'🏦 PRÊTS'!A:B,2,0),"?")) | D12: =IF(B12="","",IFERROR(VLOOKUP(B12,'🏦 PRÊTS'!A:C,3,0),"?")) | E12: =IF(B12="","",IFERROR(VLOOKUP(B12,'🏦 PRÊTS'!A:D,4,0),"?")) | J12: =IF(B12="","",IFERROR(VLOOKUP(B12,'🏦 PRÊTS'!A:Q,17,0),"")) | K12: =IF(J12="","—",IF(J12=0,"✅ Soldé","🔄 Partiel")) -> —
A13: REM-2027-010 | C13: =IF(B13="","",IFERROR(VLOOKUP(B13,'🏦 PRÊTS'!A:B,2,0),"?")) | D13: =IF(B13="","",IFERROR(VLOOKUP(B13,'🏦 PRÊTS'!A:C,3,0),"?")) | E13: =IF(B13="","",IFERROR(VLOOKUP(B13,'🏦 PRÊTS'!A:D,4,0),"?")) | J13: =IF(B13="","",IFERROR(VLOOKUP(B13,'🏦 PRÊTS'!A:Q,17,0),"")) | K13: =IF(J13="","—",IF(J13=0,"✅ Soldé","🔄 Partiel")) -> —
A14: REM-2027-011 | C14: =IF(B14="","",IFERROR(VLOOKUP(B14,'🏦 PRÊTS'!A:B,2,0),"?")) | D14: =IF(B14="","",IFERROR(VLOOKUP(B14,'🏦 PRÊTS'!A:C,3,0),"?")) | E14: =IF(B14="","",IFERROR(VLOOKUP(B14,'🏦 PRÊTS'!A:D,4,0),"?")) | J14: =IF(B14="","",IFERROR(VLOOKUP(B14,'🏦 PRÊTS'!A:Q,17,0),"")) | K14: =IF(J14="","—",IF(J14=0,"✅ Soldé","🔄 Partiel")) -> —
A15: REM-2027-012 | C15: =IF(B15="","",IFERROR(VLOOKUP(B15,'🏦 PRÊTS'!A:B,2,0),"?")) | D15: =IF(B15="","",IFERROR(VLOOKUP(B15,'🏦 PRÊTS'!A:C,3,0),"?")) | E15: =IF(B15="","",IFERROR(VLOOKUP(B15,'🏦 PRÊTS'!A:D,4,0),"?")) | J15: =IF(B15="","",IFERROR(VLOOKUP(B15,'🏦 PRÊTS'!A:Q,17,0),"")) | K15: =IF(J15="","—",IF(J15=0,"✅ Soldé","🔄 Partiel")) -> —
A16: REM-2027-013 | C16: =IF(B16="","",IFERROR(VLOOKUP(B16,'🏦 PRÊTS'!A:B,2,0),"?")) | D16: =IF(B16="","",IFERROR(VLOOKUP(B16,'🏦 PRÊTS'!A:C,3,0),"?")) | E16: =IF(B16="","",IFERROR(VLOOKUP(B16,'🏦 PRÊTS'!A:D,4,0),"?")) | J16: =IF(B16="","",IFERROR(VLOOKUP(B16,'🏦 PRÊTS'!A:Q,17,0),"")) | K16: =IF(J16="","—",IF(J16=0,"✅ Soldé","🔄 Partiel")) -> —
... A203: REM-2027-200 | C203: =IF(B203="","",IFERROR(VLOOKUP(B203,'🏦 PRÊTS'!A:B,2,0),"?")) | D203: =IF(B203="","",IFERROR(VLOOKUP(B203,'🏦 PRÊTS'!A:C,3,0),"?")) | E203: =IF(B203="","",IFERROR(VLOOKUP(B203,'🏦 PRÊTS'!A:D,4,0),"?")) | J203: =IF(B203="","",IFERROR(VLOOKUP(B203,'🏦 PRÊTS'!A:Q,17,0),"")) | K203: =IF(J203="","—",IF(J203=0,"✅ Soldé","🔄 Partiel")) -> —

Sheet ⚠️ PÉNALITÉS
A1: ⚠️ REGISTRE DES PÉNALITÉS — TONTINE SOLIDARITÉ PLUS 2027
A2: Pénalité retard cotisation (hors dimanche) : 100 FCFA | Absence réunion : 1 000 FCFA — Taux liés aux PARAMÈTRES
A3: ID_PEN | B3: ID_MEMBRE | C3: NOM | D3: PRÉNOMS | E3: DATE | F3: MOTIF | G3: MONTANT (FCFA) | H3: PAYÉ ? | I3: SOLDE PEN.
A4: PEN-2027-001 | C4: =IF(B4="","",IFERROR(VLOOKUP(B4,'👥 MEMBRES'!A:B,2,0),"?")) | D4: =IF(B4="","",IFERROR(VLOOKUP(B4,'👥 MEMBRES'!A:C,3,0),"?")) | G4: =IF(F4="","",IF(F4="Retard cotisation",'⚙️ PARAMÈTRES'!B8,IF(F4="Absence réunion",'⚙️ PARAMÈTRES'!B9,0))) | I4: =IF(G4="",0,IF(H4="Oui",0,G4)) -> 0
A5: PEN-2027-002 | C5: =IF(B5="","",IFERROR(VLOOKUP(B5,'👥 MEMBRES'!A:B,2,0),"?")) | D5: =IF(B5="","",IFERROR(VLOOKUP(B5,'👥 MEMBRES'!A:C,3,0),"?")) | G5: =IF(F5="","",IF(F5="Retard cotisation",'⚙️ PARAMÈTRES'!B8,IF(F5="Absence réunion",'⚙️ PARAMÈTRES'!B9,0))) | I5: =IF(G5="",0,IF(H5="Oui",0,G5)) -> 0
A6: PEN-2027-003 | C6: =IF(B6="","",IFERROR(VLOOKUP(B6,'👥 MEMBRES'!A:B,2,0),"?")) | D6: =IF(B6="","",IFERROR(VLOOKUP(B6,'👥 MEMBRES'!A:C,3,0),"?")) | G6: =IF(F6="","",IF(F6="Retard cotisation",'⚙️ PARAMÈTRES'!B8,IF(F6="Absence réunion",'⚙️ PARAMÈTRES'!B9,0))) | I6: =IF(G6="",0,IF(H6="Oui",0,G6)) -> 0
A7: PEN-2027-004 | C7: =IF(B7="","",IFERROR(VLOOKUP(B7,'👥 MEMBRES'!A:B,2,0),"?")) | D7: =IF(B7="","",IFERROR(VLOOKUP(B7,'👥 MEMBRES'!A:C,3,0),"?")) | G7: =IF(F7="","",IF(F7="Retard cotisation",'⚙️ PARAMÈTRES'!B8,IF(F7="Absence réunion",'⚙️ PARAMÈTRES'!B9,0))) | I7: =IF(G7="",0,IF(H7="Oui",0,G7)) -> 0
A8: PEN-2027-005 | C8: =IF(B8="","",IFERROR(VLOOKUP(B8,'👥 MEMBRES'!A:B,2,0),"?")) | D8: =IF(B8="","",IFERROR(VLOOKUP(B8,'👥 MEMBRES'!A:C,3,0),"?")) | G8: =IF(F8="","",IF(F8="Retard cotisation",'⚙️ PARAMÈTRES'!B8,IF(F8="Absence réunion",'⚙️ PARAMÈTRES'!B9,0))) | I8: =IF(G8="",0,IF(H8="Oui",0,G8)) -> 0
A9: PEN-2027-006 | C9: =IF(B9="","",IFERROR(VLOOKUP(B9,'👥 MEMBRES'!A:B,2,0),"?")) | D9: =IF(B9="","",IFERROR(VLOOKUP(B9,'👥 MEMBRES'!A:C,3,0),"?")) | G9: =IF(F9="","",IF(F9="Retard cotisation",'⚙️ PARAMÈTRES'!B8,IF(F9="Absence réunion",'⚙️ PARAMÈTRES'!B9,0))) | I9: =IF(G9="",0,IF(H9="Oui",0,G9)) -> 0
A10: PEN-2027-007 | C10: =IF(B10="","",IFERROR(VLOOKUP(B10,'👥 MEMBRES'!A:B,2,0),"?")) | D10: =IF(B10="","",IFERROR(VLOOKUP(B10,'👥 MEMBRES'!A:C,3,0),"?")) | G10: =IF(F10="","",IF(F10="Retard cotisation",'⚙️ PARAMÈTRES'!B8,IF(F10="Absence réunion",'⚙️ PARAMÈTRES'!B9,0))) | I10: =IF(G10="",0,IF(H10="Oui",0,G10)) -> 0
A11: PEN-2027-008 | C11: =IF(B11="","",IFERROR(VLOOKUP(B11,'👥 MEMBRES'!A:B,2,0),"?")) | D11: =IF(B11="","",IFERROR(VLOOKUP(B11,'👥 MEMBRES'!A:C,3,0),"?")) | G11: =IF(F11="","",IF(F11="Retard cotisation",'⚙️ PARAMÈTRES'!B8,IF(F11="Absence réunion",'⚙️ PARAMÈTRES'!B9,0))) | I11: =IF(G11="",0,IF(H11="Oui",0,G11)) -> 0
A12: PEN-2027-009 | C12: =IF(B12="","",IFERROR(VLOOKUP(B12,'👥 MEMBRES'!A:B,2,0),"?")) | D12: =IF(B12="","",IFERROR(VLOOKUP(B12,'👥 MEMBRES'!A:C,3,0),"?")) | G12: =IF(F12="","",IF(F12="Retard cotisation",'⚙️ PARAMÈTRES'!B8,IF(F12="Absence réunion",'⚙️ PARAMÈTRES'!B9,0))) | I12: =IF(G12="",0,IF(H12="Oui",0,G12)) -> 0
A13: PEN-2027-010 | C13: =IF(B13="","",IFERROR(VLOOKUP(B13,'👥 MEMBRES'!A:B,2,0),"?")) | D13: =IF(B13="","",IFERROR(VLOOKUP(B13,'👥 MEMBRES'!A:C,3,0),"?")) | G13: =IF(F13="","",IF(F13="Retard cotisation",'⚙️ PARAMÈTRES'!B8,IF(F13="Absence réunion",'⚙️ PARAMÈTRES'!B9,0))) | I13: =IF(G13="",0,IF(H13="Oui",0,G13)) -> 0
A14: PEN-2027-011 | C14: =IF(B14="","",IFERROR(VLOOKUP(B14,'👥 MEMBRES'!A:B,2,0),"?")) | D14: =IF(B14="","",IFERROR(VLOOKUP(B14,'👥 MEMBRES'!A:C,3,0),"?")) | G14: =IF(F14="","",IF(F14="Retard cotisation",'⚙️ PARAMÈTRES'!B8,IF(F14="Absence réunion",'⚙️ PARAMÈTRES'!B9,0))) | I14: =IF(G14="",0,IF(H14="Oui",0,G14)) -> 0
A15: PEN-2027-012 | C15: =IF(B15="","",IFERROR(VLOOKUP(B15,'👥 MEMBRES'!A:B,2,0),"?")) | D15: =IF(B15="","",IFERROR(VLOOKUP(B15,'👥 MEMBRES'!A:C,3,0),"?")) | G15: =IF(F15="","",IF(F15="Retard cotisation",'⚙️ PARAMÈTRES'!B8,IF(F15="Absence réunion",'⚙️ PARAMÈTRES'!B9,0))) | I15: =IF(G15="",0,IF(H15="Oui",0,G15)) -> 0
A16: PEN-2027-013 | C16: =IF(B16="","",IFERROR(VLOOKUP(B16,'👥 MEMBRES'!A:B,2,0),"?")) | D16: =IF(B16="","",IFERROR(VLOOKUP(B16,'👥 MEMBRES'!A:C,3,0),"?")) | G16: =IF(F16="","",IF(F16="Retard cotisation",'⚙️ PARAMÈTRES'!B8,IF(F16="Absence réunion",'⚙️ PARAMÈTRES'!B9,0))) | I16: =IF(G16="",0,IF(H16="Oui",0,G16)) -> 0
A17: PEN-2027-014 | C17: =IF(B17="","",IFERROR(VLOOKUP(B17,'👥 MEMBRES'!A:B,2,0),"?")) | D17: =IF(B17="","",IFERROR(VLOOKUP(B17,'👥 MEMBRES'!A:C,3,0),"?")) | G17: =IF(F17="","",IF(F17="Retard cotisation",'⚙️ PARAMÈTRES'!B8,IF(F17="Absence réunion",'⚙️ PARAMÈTRES'!B9,0))) | I17: =IF(G17="",0,IF(H17="Oui",0,G17)) -> 0
A18: PEN-2027-015 | C18: =IF(B18="","",IFERROR(VLOOKUP(B18,'👥 MEMBRES'!A:B,2,0),"?")) | D18: =IF(B18="","",IFERROR(VLOOKUP(B18,'👥 MEMBRES'!A:C,3,0),"?")) | G18: =IF(F18="","",IF(F18="Retard cotisation",'⚙️ PARAMÈTRES'!B8,IF(F18="Absence réunion",'⚙️ PARAMÈTRES'!B9,0))) | I18: =IF(G18="",0,IF(H18="Oui",0,G18)) -> 0
A19: PEN-2027-016 | C19: =IF(B19="","",IFERROR(VLOOKUP(B19,'👥 MEMBRES'!A:B,2,0),"?")) | D19: =IF(B19="","",IFERROR(VLOOKUP(B19,'👥 MEMBRES'!A:C,3,0),"?")) | G19: =IF(F19="","",IF(F19="Retard cotisation",'⚙️ PARAMÈTRES'!B8,IF(F19="Absence réunion",'⚙️ PARAMÈTRES'!B9,0))) | I19: =IF(G19="",0,IF(H19="Oui",0,G19)) -> 0
A20: PEN-2027-017 | C20: =IF(B20="","",IFERROR(VLOOKUP(B20,'👥 MEMBRES'!A:B,2,0),"?")) | D20: =IF(B20="","",IFERROR(VLOOKUP(B20,'👥 MEMBRES'!A:C,3,0),"?")) | G20: =IF(F20="","",IF(F20="Retard cotisation",'⚙️ PARAMÈTRES'!B8,IF(F20="Absence réunion",'⚙️ PARAMÈTRES'!B9,0))) | I20: =IF(G20="",0,IF(H20="Oui",0,G20)) -> 0
A21: PEN-2027-018 | C21: =IF(B21="","",IFERROR(VLOOKUP(B21,'👥 MEMBRES'!A:B,2,0),"?")) | D21: =IF(B21="","",IFERROR(VLOOKUP(B21,'👥 MEMBRES'!A:C,3,0),"?")) | G21: =IF(F21="","",IF(F21="Retard cotisation",'⚙️ PARAMÈTRES'!B8,IF(F21="Absence réunion",'⚙️ PARAMÈTRES'!B9,0))) | I21: =IF(G21="",0,IF(H21="Oui",0,G21)) -> 0
A22: PEN-2027-019 | C22: =IF(B22="","",IFERROR(VLOOKUP(B22,'👥 MEMBRES'!A:B,2,0),"?")) | D22: =IF(B22="","",IFERROR(VLOOKUP(B22,'👥 MEMBRES'!A:C,3,0),"?")) | G22: =IF(F22="","",IF(F22="Retard cotisation",'⚙️ PARAMÈTRES'!B8,IF(F22="Absence réunion",'⚙️ PARAMÈTRES'!B9,0))) | I22: =IF(G22="",0,IF(H22="Oui",0,G22)) -> 0
A23: PEN-2027-020 | C23: =IF(B23="","",IFERROR(VLOOKUP(B23,'👥 MEMBRES'!A:B,2,0),"?")) | D23: =IF(B23="","",IFERROR(VLOOKUP(B23,'👥 MEMBRES'!A:C,3,0),"?")) | G23: =IF(F23="","",IF(F23="Retard cotisation",'⚙️ PARAMÈTRES'!B8,IF(F23="Absence réunion",'⚙️ PARAMÈTRES'!B9,0))) | I23: =IF(G23="",0,IF(H23="Oui",0,G23)) -> 0
A24: PEN-2027-021 | C24: =IF(B24="","",IFERROR(VLOOKUP(B24,'👥 MEMBRES'!A:B,2,0),"?")) | D24: =IF(B24="","",IFERROR(VLOOKUP(B24,'👥 MEMBRES'!A:C,3,0),"?")) | G24: =IF(F24="","",IF(F24="Retard cotisation",'⚙️ PARAMÈTRES'!B8,IF(F24="Absence réunion",'⚙️ PARAMÈTRES'!B9,0))) | I24: =IF(G24="",0,IF(H24="Oui",0,G24)) -> 0
A25: PEN-2027-022 | C25: =IF(B25="","",IFERROR(VLOOKUP(B25,'👥 MEMBRES'!A:B,2,0),"?")) | D25: =IF(B25="","",IFERROR(VLOOKUP(B25,'👥 MEMBRES'!A:C,3,0),"?")) | G25: =IF(F25="","",IF(F25="Retard cotisation",'⚙️ PARAMÈTRES'!B8,IF(F25="Absence réunion",'⚙️ PARAMÈTRES'!B9,0))) | I25: =IF(G25="",0,IF(H25="Oui",0,G25)) -> 0
A26: PEN-2027-023 | C26: =IF(B26="","",IFERROR(VLOOKUP(B26,'👥 MEMBRES'!A:B,2,0),"?")) | D26: =IF(B26="","",IFERROR(VLOOKUP(B26,'👥 MEMBRES'!A:C,3,0),"?")) | G26: =IF(F26="","",IF(F26="Retard cotisation",'⚙️ PARAMÈTRES'!B8,IF(F26="Absence réunion",'⚙️ PARAMÈTRES'!B9,0))) | I26: =IF(G26="",0,IF(H26="Oui",0,G26)) -> 0
A27: PEN-2027-024 | C27: =IF(B27="","",IFERROR(VLOOKUP(B27,'👥 MEMBRES'!A:B,2,0),"?")) | D27: =IF(B27="","",IFERROR(VLOOKUP(B27,'👥 MEMBRES'!A:C,3,0),"?")) | G27: =IF(F27="","",IF(F27="Retard cotisation",'⚙️ PARAMÈTRES'!B8,IF(F27="Absence réunion",'⚙️ PARAMÈTRES'!B9,0))) | I27: =IF(G27="",0,IF(H27="Oui",0,G27)) -> 0
A28: PEN-2027-025 | C28: =IF(B28="","",IFERROR(VLOOKUP(B28,'👥 MEMBRES'!A:B,2,0),"?")) | D28: =IF(B28="","",IFERROR(VLOOKUP(B28,'👥 MEMBRES'!A:C,3,0),"?")) | G28: =IF(F28="","",IF(F28="Retard cotisation",'⚙️ PARAMÈTRES'!B8,IF(F28="Absence réunion",'⚙️ PARAMÈTRES'!B9,0))) | I28: =IF(G28="",0,IF(H28="Oui",0,G28)) -> 0
A29: PEN-2027-026 | C29: =IF(B29="","",IFERROR(VLOOKUP(B29,'👥 MEMBRES'!A:B,2,0),"?")) | D29: =IF(B29="","",IFERROR(VLOOKUP(B29,'👥 MEMBRES'!A:C,3,0),"?")) | G29: =IF(F29="","",IF(F29="Retard cotisation",'⚙️ PARAMÈTRES'!B8,IF(F29="Absence réunion",'⚙️ PARAMÈTRES'!B9,0))) | I29: =IF(G29="",0,IF(H29="Oui",0,G29)) -> 0
A30: PEN-2027-027 | C30: =IF(B30="","",IFERROR(VLOOKUP(B30,'👥 MEMBRES'!A:B,2,0),"?")) | D30: =IF(B30="","",IFERROR(VLOOKUP(B30,'👥 MEMBRES'!A:C,3,0),"?")) | G30: =IF(F30="","",IF(F30="Retard cotisation",'⚙️ PARAMÈTRES'!B8,IF(F30="Absence réunion",'⚙️ PARAMÈTRES'!B9,0))) | I30: =IF(G30="",0,IF(H30="Oui",0,G30)) -> 0
A31: PEN-2027-028 | C31: =IF(B31="","",IFERROR(VLOOKUP(B31,'👥 MEMBRES'!A:B,2,0),"?")) | D31: =IF(B31="","",IFERROR(VLOOKUP(B31,'👥 MEMBRES'!A:C,3,0),"?")) | G31: =IF(F31="","",IF(F31="Retard cotisation",'⚙️ PARAMÈTRES'!B8,IF(F31="Absence réunion",'⚙️ PARAMÈTRES'!B9,0))) | I31: =IF(G31="",0,IF(H31="Oui",0,G31)) -> 0
A32: PEN-2027-029 | C32: =IF(B32="","",IFERROR(VLOOKUP(B32,'👥 MEMBRES'!A:B,2,0),"?")) | D32: =IF(B32="","",IFERROR(VLOOKUP(B32,'👥 MEMBRES'!A:C,3,0),"?")) | G32: =IF(F32="","",IF(F32="Retard cotisation",'⚙️ PARAMÈTRES'!B8,IF(F32="Absence réunion",'⚙️ PARAMÈTRES'!B9,0))) | I32: =IF(G32="",0,IF(H32="Oui",0,G32)) -> 0
A33: PEN-2027-030 | C33: =IF(B33="","",IFERROR(VLOOKUP(B33,'👥 MEMBRES'!A:B,2,0),"?")) | D33: =IF(B33="","",IFERROR(VLOOKUP(B33,'👥 MEMBRES'!A:C,3,0),"?")) | G33: =IF(F33="","",IF(F33="Retard cotisation",'⚙️ PARAMÈTRES'!B8,IF(F33="Absence réunion",'⚙️ PARAMÈTRES'!B9,0))) | I33: =IF(G33="",0,IF(H33="Oui",0,G33)) -> 0
A34: PEN-2027-031 | C34: =IF(B34="","",IFERROR(VLOOKUP(B34,'👥 MEMBRES'!A:B,2,0),"?")) | D34: =IF(B34="","",IFERROR(VLOOKUP(B34,'👥 MEMBRES'!A:C,3,0),"?")) | G34: =IF(F34="","",IF(F34="Retard cotisation",'⚙️ PARAMÈTRES'!B8,IF(F34="Absence réunion",'⚙️ PARAMÈTRES'!B9,0))) | I34: =IF(G34="",0,IF(H34="Oui",0,G34)) -> 0
A35: PEN-2027-032 | C35: =IF(B35="","",IFERROR(VLOOKUP(B35,'👥 MEMBRES'!A:B,2,0),"?")) | D35: =IF(B35="","",IFERROR(VLOOKUP(B35,'👥 MEMBRES'!A:C,3,0),"?")) | G35: =IF(F35="","",IF(F35="Retard cotisation",'⚙️ PARAMÈTRES'!B8,IF(F35="Absence réunion",'⚙️ PARAMÈTRES'!B9,0))) | I35: =IF(G35="",0,IF(H35="Oui",0,G35)) -> 0
A36: PEN-2027-033 | C36: =IF(B36="","",IFERROR(VLOOKUP(B36,'👥 MEMBRES'!A:B,2,0),"?")) | D36: =IF(B36="","",IFERROR(VLOOKUP(B36,'👥 MEMBRES'!A:C,3,0),"?")) | G36: =IF(F36="","",IF(F36="Retard cotisation",'⚙️ PARAMÈTRES'!B8,IF(F36="Absence réunion",'⚙️ PARAMÈTRES'!B9,0))) | I36: =IF(G36="",0,IF(H36="Oui",0,G36)) -> 0
A37: PEN-2027-034 | C37: =IF(B37="","",IFERROR(VLOOKUP(B37,'👥 MEMBRES'!A:B,2,0),"?")) | D37: =IF(B37="","",IFERROR(VLOOKUP(B37,'👥 MEMBRES'!A:C,3,0),"?")) | G37: =IF(F37="","",IF(F37="Retard cotisation",'⚙️ PARAMÈTRES'!B8,IF(F37="Absence réunion",'⚙️ PARAMÈTRES'!B9,0))) | I37: =IF(G37="",0,IF(H37="Oui",0,G37)) -> 0
A38: PEN-2027-035 | C38: =IF(B38="","",IFERROR(VLOOKUP(B38,'👥 MEMBRES'!A:B,2,0),"?")) | D38: =IF(B38="","",IFERROR(VLOOKUP(B38,'👥 MEMBRES'!A:C,3,0),"?")) | G38: =IF(F38="","",IF(F38="Retard cotisation",'⚙️ PARAMÈTRES'!B8,IF(F38="Absence réunion",'⚙️ PARAMÈTRES'!B9,0))) | I38: =IF(G38="",0,IF(H38="Oui",0,G38)) -> 0
A39: PEN-2027-036 | C39: =IF(B39="","",IFERROR(VLOOKUP(B39,'👥 MEMBRES'!A:B,2,0),"?")) | D39: =IF(B39="","",IFERROR(VLOOKUP(B39,'👥 MEMBRES'!A:C,3,0),"?")) | G39: =IF(F39="","",IF(F39="Retard cotisation",'⚙️ PARAMÈTRES'!B8,IF(F39="Absence réunion",'⚙️ PARAMÈTRES'!B9,0))) | I39: =IF(G39="",0,IF(H39="Oui",0,G39)) -> 0
A40: PEN-2027-037 | C40: =IF(B40="","",IFERROR(VLOOKUP(B40,'👥 MEMBRES'!A:B,2,0),"?")) | D40: =IF(B40="","",IFERROR(VLOOKUP(B40,'👥 MEMBRES'!A:C,3,0),"?")) | G40: =IF(F40="","",IF(F40="Retard cotisation",'⚙️ PARAMÈTRES'!B8,IF(F40="Absence réunion",'⚙️ PARAMÈTRES'!B9,0))) | I40: =IF(G40="",0,IF(H40="Oui",0,G40)) -> 0
A41: PEN-2027-038 | C41: =IF(B41="","",IFERROR(VLOOKUP(B41,'👥 MEMBRES'!A:B,2,0),"?")) | D41: =IF(B41="","",IFERROR(VLOOKUP(B41,'👥 MEMBRES'!A:C,3,0),"?")) | G41: =IF(F41="","",IF(F41="Retard cotisation",'⚙️ PARAMÈTRES'!B8,IF(F41="Absence réunion",'⚙️ PARAMÈTRES'!B9,0))) | I41: =IF(G41="",0,IF(H41="Oui",0,G41)) -> 0
A42: PEN-2027-039 | C42: =IF(B42="","",IFERROR(VLOOKUP(B42,'👥 MEMBRES'!A:B,2,0),"?")) | D42: =IF(B42="","",IFERROR(VLOOKUP(B42,'👥 MEMBRES'!A:C,3,0),"?")) | G42: =IF(F42="","",IF(F42="Retard cotisation",'⚙️ PARAMÈTRES'!B8,IF(F42="Absence réunion",'⚙️ PARAMÈTRES'!B9,0))) | I42: =IF(G42="",0,IF(H42="Oui",0,G42)) -> 0
A43: PEN-2027-040 | C43: =IF(B43="","",IFERROR(VLOOKUP(B43,'👥 MEMBRES'!A:B,2,0),"?")) | D43: =IF(B43="","",IFERROR(VLOOKUP(B43,'👥 MEMBRES'!A:C,3,0),"?")) | G43: =IF(F43="","",IF(F43="Retard cotisation",'⚙️ PARAMÈTRES'!B8,IF(F43="Absence réunion",'⚙️ PARAMÈTRES'!B9,0))) | I43: =IF(G43="",0,IF(H43="Oui",0,G43)) -> 0
A44: PEN-2027-041 | C44: =IF(B44="","",IFERROR(VLOOKUP(B44,'👥 MEMBRES'!A:B,2,0),"?")) | D44: =IF(B44="","",IFERROR(VLOOKUP(B44,'👥 MEMBRES'!A:C,3,0),"?")) | G44: =IF(F44="","",IF(F44="Retard cotisation",'⚙️ PARAMÈTRES'!B8,IF(F44="Absence réunion",'⚙️ PARAMÈTRES'!B9,0))) | I44: =IF(G44="",0,IF(H44="Oui",0,G44)) -> 0
A45: PEN-2027-042 | C45: =IF(B45="","",IFERROR(VLOOKUP(B45,'👥 MEMBRES'!A:B,2,0),"?")) | D45: =IF(B45="","",IFERROR(VLOOKUP(B45,'👥 MEMBRES'!A:C,3,0),"?")) | G45: =IF(F45="","",IF(F45="Retard cotisation",'⚙️ PARAMÈTRES'!B8,IF(F45="Absence réunion",'⚙️ PARAMÈTRES'!B9,0))) | I45: =IF(G45="",0,IF(H45="Oui",0,G45)) -> 0
A46: PEN-2027-043 | C46: =IF(B46="","",IFERROR(VLOOKUP(B46,'👥 MEMBRES'!A:B,2,0),"?")) | D46: =IF(B46="","",IFERROR(VLOOKUP(B46,'👥 MEMBRES'!A:C,3,0),"?")) | G46: =IF(F46="","",IF(F46="Retard cotisation",'⚙️ PARAMÈTRES'!B8,IF(F46="Absence réunion",'⚙️ PARAMÈTRES'!B9,0))) | I46: =IF(G46="",0,IF(H46="Oui",0,G46)) -> 0
A47: PEN-2027-044 | C47: =IF(B47="","",IFERROR(VLOOKUP(B47,'👥 MEMBRES'!A:B,2,0),"?")) | D47: =IF(B47="","",IFERROR(VLOOKUP(B47,'👥 MEMBRES'!A:C,3,0),"?")) | G47: =IF(F47="","",IF(F47="Retard cotisation",'⚙️ PARAMÈTRES'!B8,IF(F47="Absence réunion",'⚙️ PARAMÈTRES'!B9,0))) | I47: =IF(G47="",0,IF(H47="Oui",0,G47)) -> 0
A48: PEN-2027-045 | C48: =IF(B48="","",IFERROR(VLOOKUP(B48,'👥 MEMBRES'!A:B,2,0),"?")) | D48: =IF(B48="","",IFERROR(VLOOKUP(B48,'👥 MEMBRES'!A:C,3,0),"?")) | G48: =IF(F48="","",IF(F48="Retard cotisation",'⚙️ PARAMÈTRES'!B8,IF(F48="Absence réunion",'⚙️ PARAMÈTRES'!B9,0))) | I48: =IF(G48="",0,IF(H48="Oui",0,G48)) -> 0
A49: PEN-2027-046 | C49: =IF(B49="","",IFERROR(VLOOKUP(B49,'👥 MEMBRES'!A:B,2,0),"?")) | D49: =IF(B49="","",IFERROR(VLOOKUP(B49,'👥 MEMBRES'!A:C,3,0),"?")) | G49: =IF(F49="","",IF(F49="Retard cotisation",'⚙️ PARAMÈTRES'!B8,IF(F49="Absence réunion",'⚙️ PARAMÈTRES'!B9,0))) | I49: =IF(G49="",0,IF(H49="Oui",0,G49)) -> 0
A50: PEN-2027-047 | C50: =IF(B50="","",IFERROR(VLOOKUP(B50,'👥 MEMBRES'!A:B,2,0),"?")) | D50: =IF(B50="","",IFERROR(VLOOKUP(B50,'👥 MEMBRES'!A:C,3,0),"?")) | G50: =IF(F50="","",IF(F50="Retard cotisation",'⚙️ PARAMÈTRES'!B8,IF(F50="Absence réunion",'⚙️ PARAMÈTRES'!B9,0))) | I50: =IF(G50="",0,IF(H50="Oui",0,G50)) -> 0
A51: PEN-2027-048 | C51: =IF(B51="","",IFERROR(VLOOKUP(B51,'👥 MEMBRES'!A:B,2,0),"?")) | D51: =IF(B51="","",IFERROR(VLOOKUP(B51,'👥 MEMBRES'!A:C,3,0),"?")) | G51: =IF(F51="","",IF(F51="Retard cotisation",'⚙️ PARAMÈTRES'!B8,IF(F51="Absence réunion",'⚙️ PARAMÈTRES'!B9,0))) | I51: =IF(G51="",0,IF(H51="Oui",0,G51)) -> 0
A52: PEN-2027-049 | C52: =IF(B52="","",IFERROR(VLOOKUP(B52,'👥 MEMBRES'!A:B,2,0),"?")) | D52: =IF(B52="","",IFERROR(VLOOKUP(B52,'👥 MEMBRES'!A:C,3,0),"?")) | G52: =IF(F52="","",IF(F52="Retard cotisation",'⚙️ PARAMÈTRES'!B8,IF(F52="Absence réunion",'⚙️ PARAMÈTRES'!B9,0))) | I52: =IF(G52="",0,IF(H52="Oui",0,G52)) -> 0
A53: PEN-2027-050 | C53: =IF(B53="","",IFERROR(VLOOKUP(B53,'👥 MEMBRES'!A:B,2,0),"?")) | D53: =IF(B53="","",IFERROR(VLOOKUP(B53,'👥 MEMBRES'!A:C,3,0),"?")) | G53: =IF(F53="","",IF(F53="Retard cotisation",'⚙️ PARAMÈTRES'!B8,IF(F53="Absence réunion",'⚙️ PARAMÈTRES'!B9,0))) | I53: =IF(G53="",0,IF(H53="Oui",0,G53)) -> 0
A54: PEN-2027-051 | C54: =IF(B54="","",IFERROR(VLOOKUP(B54,'👥 MEMBRES'!A:B,2,0),"?")) | D54: =IF(B54="","",IFERROR(VLOOKUP(B54,'👥 MEMBRES'!A:C,3,0),"?")) | G54: =IF(F54="","",IF(F54="Retard cotisation",'⚙️ PARAMÈTRES'!B8,IF(F54="Absence réunion",'⚙️ PARAMÈTRES'!B9,0))) | I54: =IF(G54="",0,IF(H54="Oui",0,G54)) -> 0
A55: PEN-2027-052 | C55: =IF(B55="","",IFERROR(VLOOKUP(B55,'👥 MEMBRES'!A:B,2,0),"?")) | D55: =IF(B55="","",IFERROR(VLOOKUP(B55,'👥 MEMBRES'!A:C,3,0),"?")) | G55: =IF(F55="","",IF(F55="Retard cotisation",'⚙️ PARAMÈTRES'!B8,IF(F55="Absence réunion",'⚙️ PARAMÈTRES'!B9,0))) | I55: =IF(G55="",0,IF(H55="Oui",0,G55)) -> 0
A56: PEN-2027-053 | C56: =IF(B56="","",IFERROR(VLOOKUP(B56,'👥 MEMBRES'!A:B,2,0),"?")) | D56: =IF(B56="","",IFERROR(VLOOKUP(B56,'👥 MEMBRES'!A:C,3,0),"?")) | G56: =IF(F56="","",IF(F56="Retard cotisation",'⚙️ PARAMÈTRES'!B8,IF(F56="Absence réunion",'⚙️ PARAMÈTRES'!B9,0))) | I56: =IF(G56="",0,IF(H56="Oui",0,G56)) -> 0
A57: PEN-2027-054 | C57: =IF(B57="","",IFERROR(VLOOKUP(B57,'👥 MEMBRES'!A:B,2,0),"?")) | D57: =IF(B57="","",IFERROR(VLOOKUP(B57,'👥 MEMBRES'!A:C,3,0),"?")) | G57: =IF(F57="","",IF(F57="Retard cotisation",'⚙️ PARAMÈTRES'!B8,IF(F57="Absence réunion",'⚙️ PARAMÈTRES'!B9,0))) | I57: =IF(G57="",0,IF(H57="Oui",0,G57)) -> 0
A58: PEN-2027-055 | C58: =IF(B58="","",IFERROR(VLOOKUP(B58,'👥 MEMBRES'!A:B,2,0),"?")) | D58: =IF(B58="","",IFERROR(VLOOKUP(B58,'👥 MEMBRES'!A:C,3,0),"?")) | G58: =IF(F58="","",IF(F58="Retard cotisation",'⚙️ PARAMÈTRES'!B8,IF(F58="Absence réunion",'⚙️ PARAMÈTRES'!B9,0))) | I58: =IF(G58="",0,IF(H58="Oui",0,G58)) -> 0
A59: PEN-2027-056 | C59: =IF(B59="","",IFERROR(VLOOKUP(B59,'👥 MEMBRES'!A:B,2,0),"?")) | D59: =IF(B59="","",IFERROR(VLOOKUP(B59,'👥 MEMBRES'!A:C,3,0),"?")) | G59: =IF(F59="","",IF(F59="Retard cotisation",'⚙️ PARAMÈTRES'!B8,IF(F59="Absence réunion",'⚙️ PARAMÈTRES'!B9,0))) | I59: =IF(G59="",0,IF(H59="Oui",0,G59)) -> 0
A60: PEN-2027-057 | C60: =IF(B60="","",IFERROR(VLOOKUP(B60,'👥 MEMBRES'!A:B,2,0),"?")) | D60: =IF(B60="","",IFERROR(VLOOKUP(B60,'👥 MEMBRES'!A:C,3,0),"?")) | G60: =IF(F60="","",IF(F60="Retard cotisation",'⚙️ PARAMÈTRES'!B8,IF(F60="Absence réunion",'⚙️ PARAMÈTRES'!B9,0))) | I60: =IF(G60="",0,IF(H60="Oui",0,G60)) -> 0
A61: PEN-2027-058 | C61: =IF(B61="","",IFERROR(VLOOKUP(B61,'👥 MEMBRES'!A:B,2,0),"?")) | D61: =IF(B61="","",IFERROR(VLOOKUP(B61,'👥 MEMBRES'!A:C,3,0),"?")) | G61: =IF(F61="","",IF(F61="Retard cotisation",'⚙️ PARAMÈTRES'!B8,IF(F61="Absence réunion",'⚙️ PARAMÈTRES'!B9,0))) | I61: =IF(G61="",0,IF(H61="Oui",0,G61)) -> 0
A62: PEN-2027-059 | C62: =IF(B62="","",IFERROR(VLOOKUP(B62,'👥 MEMBRES'!A:B,2,0),"?")) | D62: =IF(B62="","",IFERROR(VLOOKUP(B62,'👥 MEMBRES'!A:C,3,0),"?")) | G62: =IF(F62="","",IF(F62="Retard cotisation",'⚙️ PARAMÈTRES'!B8,IF(F62="Absence réunion",'⚙️ PARAMÈTRES'!B9,0))) | I62: =IF(G62="",0,IF(H62="Oui",0,G62)) -> 0
A63: PEN-2027-060 | C63: =IF(B63="","",IFERROR(VLOOKUP(B63,'👥 MEMBRES'!A:B,2,0),"?")) | D63: =IF(B63="","",IFERROR(VLOOKUP(B63,'👥 MEMBRES'!A:C,3,0),"?")) | G63: =IF(F63="","",IF(F63="Retard cotisation",'⚙️ PARAMÈTRES'!B8,IF(F63="Absence réunion",'⚙️ PARAMÈTRES'!B9,0))) | I63: =IF(G63="",0,IF(H63="Oui",0,G63)) -> 0
A64: PEN-2027-061 | C64: =IF(B64="","",IFERROR(VLOOKUP(B64,'👥 MEMBRES'!A:B,2,0),"?")) | D64: =IF(B64="","",IFERROR(VLOOKUP(B64,'👥 MEMBRES'!A:C,3,0),"?")) | G64: =IF(F64="","",IF(F64="Retard cotisation",'⚙️ PARAMÈTRES'!B8,IF(F64="Absence réunion",'⚙️ PARAMÈTRES'!B9,0))) | I64: =IF(G64="",0,IF(H64="Oui",0,G64)) -> 0
A65: PEN-2027-062 | C65: =IF(B65="","",IFERROR(VLOOKUP(B65,'👥 MEMBRES'!A:B,2,0),"?")) | D65: =IF(B65="","",IFERROR(VLOOKUP(B65,'👥 MEMBRES'!A:C,3,0),"?")) | G65: =IF(F65="","",IF(F65="Retard cotisation",'⚙️ PARAMÈTRES'!B8,IF(F65="Absence réunion",'⚙️ PARAMÈTRES'!B9,0))) | I65: =IF(G65="",0,IF(H65="Oui",0,G65)) -> 0
A66: PEN-2027-063 | C66: =IF(B66="","",IFERROR(VLOOKUP(B66,'👥 MEMBRES'!A:B,2,0),"?")) | D66: =IF(B66="","",IFERROR(VLOOKUP(B66,'👥 MEMBRES'!A:C,3,0),"?")) | G66: =IF(F66="","",IF(F66="Retard cotisation",'⚙️ PARAMÈTRES'!B8,IF(F66="Absence réunion",'⚙️ PARAMÈTRES'!B9,0))) | I66: =IF(G66="",0,IF(H66="Oui",0,G66)) -> 0
A67: PEN-2027-064 | C67: =IF(B67="","",IFERROR(VLOOKUP(B67,'👥 MEMBRES'!A:B,2,0),"?")) | D67: =IF(B67="","",IFERROR(VLOOKUP(B67,'👥 MEMBRES'!A:C,3,0),"?")) | G67: =IF(F67="","",IF(F67="Retard cotisation",'⚙️ PARAMÈTRES'!B8,IF(F67="Absence réunion",'⚙️ PARAMÈTRES'!B9,0))) | I67: =IF(G67="",0,IF(H67="Oui",0,G67)) -> 0
A68: PEN-2027-065 | C68: =IF(B68="","",IFERROR(VLOOKUP(B68,'👥 MEMBRES'!A:B,2,0),"?")) | D68: =IF(B68="","",IFERROR(VLOOKUP(B68,'👥 MEMBRES'!A:C,3,0),"?")) | G68: =IF(F68="","",IF(F68="Retard cotisation",'⚙️ PARAMÈTRES'!B8,IF(F68="Absence réunion",'⚙️ PARAMÈTRES'!B9,0))) | I68: =IF(G68="",0,IF(H68="Oui",0,G68)) -> 0
A69: PEN-2027-066 | C69: =IF(B69="","",IFERROR(VLOOKUP(B69,'👥 MEMBRES'!A:B,2,0),"?")) | D69: =IF(B69="","",IFERROR(VLOOKUP(B69,'👥 MEMBRES'!A:C,3,0),"?")) | G69: =IF(F69="","",IF(F69="Retard cotisation",'⚙️ PARAMÈTRES'!B8,IF(F69="Absence réunion",'⚙️ PARAMÈTRES'!B9,0))) | I69: =IF(G69="",0,IF(H69="Oui",0,G69)) -> 0
A70: PEN-2027-067 | C70: =IF(B70="","",IFERROR(VLOOKUP(B70,'👥 MEMBRES'!A:B,2,0),"?")) | D70: =IF(B70="","",IFERROR(VLOOKUP(B70,'👥 MEMBRES'!A:C,3,0),"?")) | G70: =IF(F70="","",IF(F70="Retard cotisation",'⚙️ PARAMÈTRES'!B8,IF(F70="Absence réunion",'⚙️ PARAMÈTRES'!B9,0))) | I70: =IF(G70="",0,IF(H70="Oui",0,G70)) -> 0
A71: PEN-2027-068 | C71: =IF(B71="","",IFERROR(VLOOKUP(B71,'👥 MEMBRES'!A:B,2,0),"?")) | D71: =IF(B71="","",IFERROR(VLOOKUP(B71,'👥 MEMBRES'!A:C,3,0),"?")) | G71: =IF(F71="","",IF(F71="Retard cotisation",'⚙️ PARAMÈTRES'!B8,IF(F71="Absence réunion",'⚙️ PARAMÈTRES'!B9,0))) | I71: =IF(G71="",0,IF(H71="Oui",0,G71)) -> 0
A72: PEN-2027-069 | C72: =IF(B72="","",IFERROR(VLOOKUP(B72,'👥 MEMBRES'!A:B,2,0),"?")) | D72: =IF(B72="","",IFERROR(VLOOKUP(B72,'👥 MEMBRES'!A:C,3,0),"?")) | G72: =IF(F72="","",IF(F72="Retard cotisation",'⚙️ PARAMÈTRES'!B8,IF(F72="Absence réunion",'⚙️ PARAMÈTRES'!B9,0))) | I72: =IF(G72="",0,IF(H72="Oui",0,G72)) -> 0
A73: PEN-2027-070 | C73: =IF(B73="","",IFERROR(VLOOKUP(B73,'👥 MEMBRES'!A:B,2,0),"?")) | D73: =IF(B73="","",IFERROR(VLOOKUP(B73,'👥 MEMBRES'!A:C,3,0),"?")) | G73: =IF(F73="","",IF(F73="Retard cotisation",'⚙️ PARAMÈTRES'!B8,IF(F73="Absence réunion",'⚙️ PARAMÈTRES'!B9,0))) | I73: =IF(G73="",0,IF(H73="Oui",0,G73)) -> 0
A74: PEN-2027-071 | C74: =IF(B74="","",IFERROR(VLOOKUP(B74,'👥 MEMBRES'!A:B,2,0),"?")) | D74: =IF(B74="","",IFERROR(VLOOKUP(B74,'👥 MEMBRES'!A:C,3,0),"?")) | G74: =IF(F74="","",IF(F74="Retard cotisation",'⚙️ PARAMÈTRES'!B8,IF(F74="Absence réunion",'⚙️ PARAMÈTRES'!B9,0))) | I74: =IF(G74="",0,IF(H74="Oui",0,G74)) -> 0
A75: PEN-2027-072 | C75: =IF(B75="","",IFERROR(VLOOKUP(B75,'👥 MEMBRES'!A:B,2,0),"?")) | D75: =IF(B75="","",IFERROR(VLOOKUP(B75,'👥 MEMBRES'!A:C,3,0),"?")) | G75: =IF(F75="","",IF(F75="Retard cotisation",'⚙️ PARAMÈTRES'!B8,IF(F75="Absence réunion",'⚙️ PARAMÈTRES'!B9,0))) | I75: =IF(G75="",0,IF(H75="Oui",0,G75)) -> 0
A76: PEN-2027-073 | C76: =IF(B76="","",IFERROR(VLOOKUP(B76,'👥 MEMBRES'!A:B,2,0),"?")) | D76: =IF(B76="","",IFERROR(VLOOKUP(B76,'👥 MEMBRES'!A:C,3,0),"?")) | G76: =IF(F76="","",IF(F76="Retard cotisation",'⚙️ PARAMÈTRES'!B8,IF(F76="Absence réunion",'⚙️ PARAMÈTRES'!B9,0))) | I76: =IF(G76="",0,IF(H76="Oui",0,G76)) -> 0
A77: PEN-2027-074 | C77: =IF(B77="","",IFERROR(VLOOKUP(B77,'👥 MEMBRES'!A:B,2,0),"?")) | D77: =IF(B77="","",IFERROR(VLOOKUP(B77,'👥 MEMBRES'!A:C,3,0),"?")) | G77: =IF(F77="","",IF(F77="Retard cotisation",'⚙️ PARAMÈTRES'!B8,IF(F77="Absence réunion",'⚙️ PARAMÈTRES'!B9,0))) | I77: =IF(G77="",0,IF(H77="Oui",0,G77)) -> 0
A78: PEN-2027-075 | C78: =IF(B78="","",IFERROR(VLOOKUP(B78,'👥 MEMBRES'!A:B,2,0),"?")) | D78: =IF(B78="","",IFERROR(VLOOKUP(B78,'👥 MEMBRES'!A:C,3,0),"?")) | G78: =IF(F78="","",IF(F78="Retard cotisation",'⚙️ PARAMÈTRES'!B8,IF(F78="Absence réunion",'⚙️ PARAMÈTRES'!B9,0))) | I78: =IF(G78="",0,IF(H78="Oui",0,G78)) -> 0
A79: PEN-2027-076 | C79: =IF(B79="","",IFERROR(VLOOKUP(B79,'👥 MEMBRES'!A:B,2,0),"?")) | D79: =IF(B79="","",IFERROR(VLOOKUP(B79,'👥 MEMBRES'!A:C,3,0),"?")) | G79: =IF(F79="","",IF(F79="Retard cotisation",'⚙️ PARAMÈTRES'!B8,IF(F79="Absence réunion",'⚙️ PARAMÈTRES'!B9,0))) | I79: =IF(G79="",0,IF(H79="Oui",0,G79)) -> 0
A80: PEN-2027-077 | C80: =IF(B80="","",IFERROR(VLOOKUP(B80,'👥 MEMBRES'!A:B,2,0),"?")) | D80: =IF(B80="","",IFERROR(VLOOKUP(B80,'👥 MEMBRES'!A:C,3,0),"?")) | G80: =IF(F80="","",IF(F80="Retard cotisation",'⚙️ PARAMÈTRES'!B8,IF(F80="Absence réunion",'⚙️ PARAMÈTRES'!B9,0))) | I80: =IF(G80="",0,IF(H80="Oui",0,G80)) -> 0
A81: PEN-2027-078 | C81: =IF(B81="","",IFERROR(VLOOKUP(B81,'👥 MEMBRES'!A:B,2,0),"?")) | D81: =IF(B81="","",IFERROR(VLOOKUP(B81,'👥 MEMBRES'!A:C,3,0),"?")) | G81: =IF(F81="","",IF(F81="Retard cotisation",'⚙️ PARAMÈTRES'!B8,IF(F81="Absence réunion",'⚙️ PARAMÈTRES'!B9,0))) | I81: =IF(G81="",0,IF(H81="Oui",0,G81)) -> 0
A82: PEN-2027-079 | C82: =IF(B82="","",IFERROR(VLOOKUP(B82,'👥 MEMBRES'!A:B,2,0),"?")) | D82: =IF(B82="","",IFERROR(VLOOKUP(B82,'👥 MEMBRES'!A:C,3,0),"?")) | G82: =IF(F82="","",IF(F82="Retard cotisation",'⚙️ PARAMÈTRES'!B8,IF(F82="Absence réunion",'⚙️ PARAMÈTRES'!B9,0))) | I82: =IF(G82="",0,IF(H82="Oui",0,G82)) -> 0
A83: PEN-2027-080 | C83: =IF(B83="","",IFERROR(VLOOKUP(B83,'👥 MEMBRES'!A:B,2,0),"?")) | D83: =IF(B83="","",IFERROR(VLOOKUP(B83,'👥 MEMBRES'!A:C,3,0),"?")) | G83: =IF(F83="","",IF(F83="Retard cotisation",'⚙️ PARAMÈTRES'!B8,IF(F83="Absence réunion",'⚙️ PARAMÈTRES'!B9,0))) | I83: =IF(G83="",0,IF(H83="Oui",0,G83)) -> 0
A84: PEN-2027-081 | C84: =IF(B84="","",IFERROR(VLOOKUP(B84,'👥 MEMBRES'!A:B,2,0),"?")) | D84: =IF(B84="","",IFERROR(VLOOKUP(B84,'👥 MEMBRES'!A:C,3,0),"?")) | G84: =IF(F84="","",IF(F84="Retard cotisation",'⚙️ PARAMÈTRES'!B8,IF(F84="Absence réunion",'⚙️ PARAMÈTRES'!B9,0))) | I84: =IF(G84="",0,IF(H84="Oui",0,G84)) -> 0
A85: PEN-2027-082 | C85: =IF(B85="","",IFERROR(VLOOKUP(B85,'👥 MEMBRES'!A:B,2,0),"?")) | D85: =IF(B85="","",IFERROR(VLOOKUP(B85,'👥 MEMBRES'!A:C,3,0),"?")) | G85: =IF(F85="","",IF(F85="Retard cotisation",'⚙️ PARAMÈTRES'!B8,IF(F85="Absence réunion",'⚙️ PARAMÈTRES'!B9,0))) | I85: =IF(G85="",0,IF(H85="Oui",0,G85)) -> 0
A86: PEN-2027-083 | C86: =IF(B86="","",IFERROR(VLOOKUP(B86,'👥 MEMBRES'!A:B,2,0),"?")) | D86: =IF(B86="","",IFERROR(VLOOKUP(B86,'👥 MEMBRES'!A:C,3,0),"?")) | G86: =IF(F86="","",IF(F86="Retard cotisation",'⚙️ PARAMÈTRES'!B8,IF(F86="Absence réunion",'⚙️ PARAMÈTRES'!B9,0))) | I86: =IF(G86="",0,IF(H86="Oui",0,G86)) -> 0
A87: PEN-2027-084 | C87: =IF(B87="","",IFERROR(VLOOKUP(B87,'👥 MEMBRES'!A:B,2,0),"?")) | D87: =IF(B87="","",IFERROR(VLOOKUP(B87,'👥 MEMBRES'!A:C,3,0),"?")) | G87: =IF(F87="","",IF(F87="Retard cotisation",'⚙️ PARAMÈTRES'!B8,IF(F87="Absence réunion",'⚙️ PARAMÈTRES'!B9,0))) | I87: =IF(G87="",0,IF(H87="Oui",0,G87)) -> 0
A88: PEN-2027-085 | C88: =IF(B88="","",IFERROR(VLOOKUP(B88,'👥 MEMBRES'!A:B,2,0),"?")) | D88: =IF(B88="","",IFERROR(VLOOKUP(B88,'👥 MEMBRES'!A:C,3,0),"?")) | G88: =IF(F88="","",IF(F88="Retard cotisation",'⚙️ PARAMÈTRES'!B8,IF(F88="Absence réunion",'⚙️ PARAMÈTRES'!B9,0))) | I88: =IF(G88="",0,IF(H88="Oui",0,G88)) -> 0
A89: PEN-2027-086 | C89: =IF(B89="","",IFERROR(VLOOKUP(B89,'👥 MEMBRES'!A:B,2,0),"?")) | D89: =IF(B89="","",IFERROR(VLOOKUP(B89,'👥 MEMBRES'!A:C,3,0),"?")) | G89: =IF(F89="","",IF(F89="Retard cotisation",'⚙️ PARAMÈTRES'!B8,IF(F89="Absence réunion",'⚙️ PARAMÈTRES'!B9,0))) | I89: =IF(G89="",0,IF(H89="Oui",0,G89)) -> 0
A90: PEN-2027-087 | C90: =IF(B90="","",IFERROR(VLOOKUP(B90,'👥 MEMBRES'!A:B,2,0),"?")) | D90: =IF(B90="","",IFERROR(VLOOKUP(B90,'👥 MEMBRES'!A:C,3,0),"?")) | G90: =IF(F90="","",IF(F90="Retard cotisation",'⚙️ PARAMÈTRES'!B8,IF(F90="Absence réunion",'⚙️ PARAMÈTRES'!B9,0))) | I90: =IF(G90="",0,IF(H90="Oui",0,G90)) -> 0
A91: PEN-2027-088 | C91: =IF(B91="","",IFERROR(VLOOKUP(B91,'👥 MEMBRES'!A:B,2,0),"?")) | D91: =IF(B91="","",IFERROR(VLOOKUP(B91,'👥 MEMBRES'!A:C,3,0),"?")) | G91: =IF(F91="","",IF(F91="Retard cotisation",'⚙️ PARAMÈTRES'!B8,IF(F91="Absence réunion",'⚙️ PARAMÈTRES'!B9,0))) | I91: =IF(G91="",0,IF(H91="Oui",0,G91)) -> 0
A92: PEN-2027-089 | C92: =IF(B92="","",IFERROR(VLOOKUP(B92,'👥 MEMBRES'!A:B,2,0),"?")) | D92: =IF(B92="","",IFERROR(VLOOKUP(B92,'👥 MEMBRES'!A:C,3,0),"?")) | G92: =IF(F92="","",IF(F92="Retard cotisation",'⚙️ PARAMÈTRES'!B8,IF(F92="Absence réunion",'⚙️ PARAMÈTRES'!B9,0))) | I92: =IF(G92="",0,IF(H92="Oui",0,G92)) -> 0
A93: PEN-2027-090 | C93: =IF(B93="","",IFERROR(VLOOKUP(B93,'👥 MEMBRES'!A:B,2,0),"?")) | D93: =IF(B93="","",IFERROR(VLOOKUP(B93,'👥 MEMBRES'!A:C,3,0),"?")) | G93: =IF(F93="","",IF(F93="Retard cotisation",'⚙️ PARAMÈTRES'!B8,IF(F93="Absence réunion",'⚙️ PARAMÈTRES'!B9,0))) | I93: =IF(G93="",0,IF(H93="Oui",0,G93)) -> 0
A94: PEN-2027-091 | C94: =IF(B94="","",IFERROR(VLOOKUP(B94,'👥 MEMBRES'!A:B,2,0),"?")) | D94: =IF(B94="","",IFERROR(VLOOKUP(B94,'👥 MEMBRES'!A:C,3,0),"?")) | G94: =IF(F94="","",IF(F94="Retard cotisation",'⚙️ PARAMÈTRES'!B8,IF(F94="Absence réunion",'⚙️ PARAMÈTRES'!B9,0))) | I94: =IF(G94="",0,IF(H94="Oui",0,G94)) -> 0
A95: PEN-2027-092 | C95: =IF(B95="","",IFERROR(VLOOKUP(B95,'👥 MEMBRES'!A:B,2,0),"?")) | D95: =IF(B95="","",IFERROR(VLOOKUP(B95,'👥 MEMBRES'!A:C,3,0),"?")) | G95: =IF(F95="","",IF(F95="Retard cotisation",'⚙️ PARAMÈTRES'!B8,IF(F95="Absence réunion",'⚙️ PARAMÈTRES'!B9,0))) | I95: =IF(G95="",0,IF(H95="Oui",0,G95)) -> 0
A96: PEN-2027-093 | C96: =IF(B96="","",IFERROR(VLOOKUP(B96,'👥 MEMBRES'!A:B,2,0),"?")) | D96: =IF(B96="","",IFERROR(VLOOKUP(B96,'👥 MEMBRES'!A:C,3,0),"?")) | G96: =IF(F96="","",IF(F96="Retard cotisation",'⚙️ PARAMÈTRES'!B8,IF(F96="Absence réunion",'⚙️ PARAMÈTRES'!B9,0))) | I96: =IF(G96="",0,IF(H96="Oui",0,G96)) -> 0
A97: PEN-2027-094 | C97: =IF(B97="","",IFERROR(VLOOKUP(B97,'👥 MEMBRES'!A:B,2,0),"?")) | D97: =IF(B97="","",IFERROR(VLOOKUP(B97,'👥 MEMBRES'!A:C,3,0),"?")) | G97: =IF(F97="","",IF(F97="Retard cotisation",'⚙️ PARAMÈTRES'!B8,IF(F97="Absence réunion",'⚙️ PARAMÈTRES'!B9,0))) | I97: =IF(G97="",0,IF(H97="Oui",0,G97)) -> 0
A98: PEN-2027-095 | C98: =IF(B98="","",IFERROR(VLOOKUP(B98,'👥 MEMBRES'!A:B,2,0),"?")) | D98: =IF(B98="","",IFERROR(VLOOKUP(B98,'👥 MEMBRES'!A:C,3,0),"?")) | G98: =IF(F98="","",IF(F98="Retard cotisation",'⚙️ PARAMÈTRES'!B8,IF(F98="Absence réunion",'⚙️ PARAMÈTRES'!B9,0))) | I98: =IF(G98="",0,IF(H98="Oui",0,G98)) -> 0
A99: PEN-2027-096 | C99: =IF(B99="","",IFERROR(VLOOKUP(B99,'👥 MEMBRES'!A:B,2,0),"?")) | D99: =IF(B99="","",IFERROR(VLOOKUP(B99,'👥 MEMBRES'!A:C,3,0),"?")) | G99: =IF(F99="","",IF(F99="Retard cotisation",'⚙️ PARAMÈTRES'!B8,IF(F99="Absence réunion",'⚙️ PARAMÈTRES'!B9,0))) | I99: =IF(G99="",0,IF(H99="Oui",0,G99)) -> 0
A100: PEN-2027-097 | C100: =IF(B100="","",IFERROR(VLOOKUP(B100,'👥 MEMBRES'!A:B,2,0),"?")) | D100: =IF(B100="","",IFERROR(VLOOKUP(B100,'👥 MEMBRES'!A:C,3,0),"?")) | G100: =IF(F100="","",IF(F100="Retard cotisation",'⚙️ PARAMÈTRES'!B8,IF(F100="Absence réunion",'⚙️ PARAMÈTRES'!B9,0))) | I100: =IF(G100="",0,IF(H100="Oui",0,G100)) -> 0
...

Sheet 🏧 CAISSE
A1: 🏧 JOURNAL DE CAISSE — TONTINE SOLIDARITÉ PLUS 2027
A2: 📅 SOLDE INITIAL (FCFA) | D2: 0 | E2: ← Saisir le solde d'ouverture ici
A3: ID_TXN | B3: DATE | C3: TYPE | D3: DESCRIPTION | E3: ENTRÉE (FCFA) | F3: SORTIE (FCFA) | G3: SOLDE (FCFA) | H3: RÉFÉRENCE | I3: ORIGINE | J3: SAISI PAR
A4: TXN-2027-0001 | G4: =D2+E4-F4 -> 0
A5: TXN-2027-0002 | G5: =G4+E5-F5 -> 0
A6: TXN-2027-0003 | G6: =G5+E6-F6 -> 0
A7: TXN-2027-0004 | G7: =G6+E7-F7 -> 0
A8: TXN-2027-0005 | G8: =G7+E8-F8 -> 0
A9: TXN-2027-0006 | G9: =G8+E9-F9 -> 0
A10: TXN-2027-0007 | G10: =G9+E10-F10 -> 0
A11: TXN-2027-0008 | G11: =G10+E11-F11 -> 0
A12: TXN-2027-0009 | G12: =G11+E12-F12 -> 0
A13: TXN-2027-0010 | G13: =G12+E13-F13 -> 0
A14: TXN-2027-0011 | G14: =G13+E14-F14 -> 0
A15: TXN-2027-0012 | G15: =G14+E15-F15 -> 0
A16: TXN-2027-0013 | G16: =G15+E16-F16 -> 0
... A503: TXN-2027-0500 | G503: =G502+E503-F503 -> 0

Sheet 📋 SOLDE MEMBRES
A1: 📋 SOLDE GLOBAL PAR MEMBRE — TONTINE SOLIDARITÉ PLUS 2027
A2: Données liées automatiquement aux onglets COTISATIONS, PRÊTS et PÉNALITÉS
A3: # | B3: ID_MEMBRE | C3: NOM | D3: PRÉNOMS | E3: TOTAL COTISÉ (FCFA) | F3: PÉNALITÉS DUES (FCFA) | G3: PRÊTS EN COURS (FCFA) | H3: SOLDE NET (FCFA) | I3: STATUT
A4: 1 | B4: ='👥 MEMBRES'!A5 -> TSP-2027-001 | C4: ='👥 MEMBRES'!B5 -> 0 | D4: ='👥 MEMBRES'!C5 -> 0 | E4: =IFERROR('💰 COTISATIONS'!BE4,0) -> 0 | F4: =SUMIF('⚠️ PÉNALITÉS'!B:B,B4,'⚠️ PÉNALITÉS'!I:I) -> 0 | G4: =SUMIF('🏦 PRÊTS'!B:B,B4,'🏦 PRÊTS'!Q:Q) -> 0 | H4: =E4-F4-G4 -> 0 | I4: =IF(G4>0,"🔴 Prêt en cours",IF(F4>0,"⚠️ Pén. dues","✅ À jour")) -> ✅ À jour
A5: 2 | B5: ='👥 MEMBRES'!A6 -> TSP-2027-002 | C5: ='👥 MEMBRES'!B6 -> 0 | D5: ='👥 MEMBRES'!C6 -> 0 | E5: =IFERROR('💰 COTISATIONS'!BE5,0) -> 0 | F5: =SUMIF('⚠️ PÉNALITÉS'!B:B,B5,'⚠️ PÉNALITÉS'!I:I) -> 0 | G5: =SUMIF('🏦 PRÊTS'!B:B,B5,'🏦 PRÊTS'!Q:Q) -> 0 | H5: =E5-F5-G5 -> 0 | I5: =IF(G5>0,"🔴 Prêt en cours",IF(F5>0,"⚠️ Pén. dues","✅ À jour")) -> ✅ À jour
A6: 3 | B6: ='👥 MEMBRES'!A7 -> TSP-2027-003 | C6: ='👥 MEMBRES'!B7 -> 0 | D6: ='👥 MEMBRES'!C7 -> 0 | E6: =IFERROR('💰 COTISATIONS'!BE6,0) -> 0 | F6: =SUMIF('⚠️ PÉNALITÉS'!B:B,B6,'⚠️ PÉNALITÉS'!I:I) -> 0 | G6: =SUMIF('🏦 PRÊTS'!B:B,B6,'🏦 PRÊTS'!Q:Q) -> 0 | H6: =E6-F6-G6 -> 0 | I6: =IF(G6>0,"🔴 Prêt en cours",IF(F6>0,"⚠️ Pén. dues","✅ À jour")) -> ✅ À jour
A7: 4 | B7: ='👥 MEMBRES'!A8 -> TSP-2027-004 | C7: ='👥 MEMBRES'!B8 -> 0 | D7: ='👥 MEMBRES'!C8 -> 0 | E7: =IFERROR('💰 COTISATIONS'!BE7,0) -> 0 | F7: =SUMIF('⚠️ PÉNALITÉS'!B:B,B7,'⚠️ PÉNALITÉS'!I:I) -> 0 | G7: =SUMIF('🏦 PRÊTS'!B:B,B7,'🏦 PRÊTS'!Q:Q) -> 0 | H7: =E7-F7-G7 -> 0 | I7: =IF(G7>0,"🔴 Prêt en cours",IF(F7>0,"⚠️ Pén. dues","✅ À jour")) -> ✅ À jour
A8: 5 | B8: ='👥 MEMBRES'!A9 -> TSP-2027-005 | C8: ='👥 MEMBRES'!B9 -> 0 | D8: ='👥 MEMBRES'!C9 -> 0 | E8: =IFERROR('💰 COTISATIONS'!BE8,0) -> 0 | F8: =SUMIF('⚠️ PÉNALITÉS'!B:B,B8,'⚠️ PÉNALITÉS'!I:I) -> 0 | G8: =SUMIF('🏦 PRÊTS'!B:B,B8,'🏦 PRÊTS'!Q:Q) -> 0 | H8: =E8-F8-G8 -> 0 | I8: =IF(G8>0,"🔴 Prêt en cours",IF(F8>0,"⚠️ Pén. dues","✅ À jour")) -> ✅ À jour
A9: 6 | B9: ='👥 MEMBRES'!A10 -> TSP-2027-006 | C9: ='👥 MEMBRES'!B10 -> 0 | D9: ='👥 MEMBRES'!C10 -> 0 | E9: =IFERROR('💰 COTISATIONS'!BE9,0) -> 0 | F9: =SUMIF('⚠️ PÉNALITÉS'!B:B,B9,'⚠️ PÉNALITÉS'!I:I) -> 0 | G9: =SUMIF('🏦 PRÊTS'!B:B,B9,'🏦 PRÊTS'!Q:Q) -> 0 | H9: =E9-F9-G9 -> 0 | I9: =IF(G9>0,"🔴 Prêt en cours",IF(F9>0,"⚠️ Pén. dues","✅ À jour")) -> ✅ À jour
A10: 7 | B10: ='👥 MEMBRES'!A11 -> TSP-2027-007 | C10: ='👥 MEMBRES'!B11 -> 0 | D10: ='👥 MEMBRES'!C11 -> 0 | E10: =IFERROR('💰 COTISATIONS'!BE10,0) -> 0 | F10: =SUMIF('⚠️ PÉNALITÉS'!B:B,B10,'⚠️ PÉNALITÉS'!I:I) -> 0 | G10: =SUMIF('🏦 PRÊTS'!B:B,B10,'🏦 PRÊTS'!Q:Q) -> 0 | H10: =E10-F10-G10 -> 0 | I10: =IF(G10>0,"🔴 Prêt en cours",IF(F10>0,"⚠️ Pén. dues","✅ À jour")) -> ✅ À jour
A11: 8 | B11: ='👥 MEMBRES'!A12 -> TSP-2027-008 | C11: ='👥 MEMBRES'!B12 -> 0 | D11: ='👥 MEMBRES'!C12 -> 0 | E11: =IFERROR('💰 COTISATIONS'!BE11,0) -> 0 | F11: =SUMIF('⚠️ PÉNALITÉS'!B:B,B11,'⚠️ PÉNALITÉS'!I:I) -> 0 | G11: =SUMIF('🏦 PRÊTS'!B:B,B11,'🏦 PRÊTS'!Q:Q) -> 0 | H11: =E11-F11-G11 -> 0 | I11: =IF(G11>0,"🔴 Prêt en cours",IF(F11>0,"⚠️ Pén. dues","✅ À jour")) -> ✅ À jour
A12: 9 | B12: ='👥 MEMBRES'!A13 -> TSP-2027-009 | C12: ='👥 MEMBRES'!B13 -> 0 | D12: ='👥 MEMBRES'!C13 -> 0 | E12: =IFERROR('💰 COTISATIONS'!BE12,0) -> 0 | F12: =SUMIF('⚠️ PÉNALITÉS'!B:B,B12,'⚠️ PÉNALITÉS'!I:I) -> 0 | G12: =SUMIF('🏦 PRÊTS'!B:B,B12,'🏦 PRÊTS'!Q:Q) -> 0 | H12: =E12-F12-G12 -> 0 | I12: =IF(G12>0,"🔴 Prêt en cours",IF(F12>0,"⚠️ Pén. dues","✅ À jour")) -> ✅ À jour
A13: 10 | B13: ='👥 MEMBRES'!A14 -> TSP-2027-010 | C13: ='👥 MEMBRES'!B14 -> 0 | D13: ='👥 MEMBRES'!C14 -> 0 | E13: =IFERROR('💰 COTISATIONS'!BE13,0) -> 0 | F13: =SUMIF('⚠️ PÉNALITÉS'!B:B,B13,'⚠️ PÉNALITÉS'!I:I) -> 0 | G13: =SUMIF('🏦 PRÊTS'!B:B,B13,'🏦 PRÊTS'!Q:Q) -> 0 | H13: =E13-F13-G13 -> 0 | I13: =IF(G13>0,"🔴 Prêt en cours",IF(F13>0,"⚠️ Pén. dues","✅ À jour")) -> ✅ À jour
A14: 11 | B14: ='👥 MEMBRES'!A15 -> TSP-2027-011 | C14: ='👥 MEMBRES'!B15 -> 0 | D14: ='👥 MEMBRES'!C15 -> 0 | E14: =IFERROR('💰 COTISATIONS'!BE14,0) -> 0 | F14: =SUMIF('⚠️ PÉNALITÉS'!B:B,B14,'⚠️ PÉNALITÉS'!I:I) -> 0 | G14: =SUMIF('🏦 PRÊTS'!B:B,B14,'🏦 PRÊTS'!Q:Q) -> 0 | H14: =E14-F14-G14 -> 0 | I14: =IF(G14>0,"🔴 Prêt en cours",IF(F14>0,"⚠️ Pén. dues","✅ À jour")) -> ✅ À jour
A15: 12 | B15: ='👥 MEMBRES'!A16 -> TSP-2027-012 | C15: ='👥 MEMBRES'!B16 -> 0 | D15: ='👥 MEMBRES'!C16 -> 0 | E15: =IFERROR('💰 COTISATIONS'!BE15,0) -> 0 | F15: =SUMIF('⚠️ PÉNALITÉS'!B:B,B15,'⚠️ PÉNALITÉS'!I:I) -> 0 | G15: =SUMIF('🏦 PRÊTS'!B:B,B15,'🏦 PRÊTS'!Q:Q) -> 0 | H15: =E15-F15-G15 -> 0 | I15: =IF(G15>0,"🔴 Prêt en cours",IF(F15>0,"⚠️ Pén. dues","✅ À jour")) -> ✅ À jour
... A53: 50 | B53: ='👥 MEMBRES'!A54 -> TSP-2027-050 | C53: ='👥 MEMBRES'!B54 -> 0 | D53: ='👥 MEMBRES'!C54 -> 0 | E53: =IFERROR('💰 COTISATIONS'!BE53,0) -> 0 | F53: =SUMIF('⚠️ PÉNALITÉS'!B:B,B53,'⚠️ PÉNALITÉS'!I:I) -> 0 | G53: =SUMIF('🏦 PRÊTS'!B:B,B53,'🏦 PRÊTS'!Q:Q) -> 0 | H53: =E53-F53-G53 -> 0 | I53: =IF(G53>0,"🔴 Prêt en cours",IF(F53>0,"⚠️ Pén. dues","✅ À jour")) -> ✅ À jour
A54: TOTAUX | E54: =SUM(E4:E53) -> 0 | F54: =SUM(F4:F53) -> 0 | G54: =SUM(G4:G53) -> 0 | H54: =SUM(H4:H53) -> 0

Sheet 📜 CONTRATS
A1: 📜 MODÈLE DE CONTRAT DE PRÊT — TONTINE SOLIDARITÉ PLUS 2027
B2: Saisir ID_PRÊT ci-dessous pour pré-remplir automatiquement :
B4: N° Contrat | C4: =IF(B3="","— Saisir l'ID —",B3) -> — Saisir l'ID —
B5: Nom de l'emprunteur | C5: {=IF(B3="","",IFERROR(C4(B3,'🏦 PRÊTS'!A:C,3,0),""))}
B6: Prénoms | C6: =IF(B3="","",IFERROR(VLOOKUP(B3,'🏦 PRÊTS'!A:'📋 SOLDE MEMBRES'!J10,4,0),""))
B7: ID Membre | C7: =IF(B3="","",IFERROR(VLOOKUP(B3,'🏦 PRÊTS'!A:B,2,0),""))
B8: Date du prêt | C8: =IF(B3="","",IFERROR(VLOOKUP(B3,'🏦 PRÊTS'!A:E,5,0),""))
B9: Montant emprunté (FCFA) | C9: =IF(B3="","",IFERROR(VLOOKUP(B3,'🏦 PRÊTS'!A:F,6,0),""))
B10: Frais de retrait (FCFA) | C10: =IF(B3="","",IFERROR(VLOOKUP(B3,'🏦 PRÊTS'!A:G,7,0),""))
B11: Taux d'intérêt (1er mois) | C11: ='⚙️ PARAMÈTRES'!B4 -> 0.1
B12: Taux supplémentaire (>2 mois) | C12: ='⚙️ PARAMÈTRES'!B5 -> 0.015
B13: Date d'échéance | C13: =IF(B3="","",IFERROR(VLOOKUP(B3,'🏦 PRÊTS'!A:K,11,0),""))
B14: Montant total dû (FCFA) | C14: =IF(B3="","",IFERROR(VLOOKUP(B3,'🏦 PRÊTS'!A:O,15,0),""))
B15: Nom du témoin | C15: =IF(B3="","",IFERROR(VLOOKUP(B3,'🏦 PRÊTS'!A:H,8,0),""))
B16: Téléphone témoin | C16: =IF(B3="","",IFERROR(VLOOKUP(B3,'🏦 PRÊTS'!A:I,9,0),""))
B17: Adresse témoin | C17: =IF(B3="","",IFERROR(VLOOKUP(B3,'🏦 PRÊTS'!A:J,10,0),""))
B18: Statut actuel | C18: =IF(B3="","",IFERROR(VLOOKUP(B3,'🏦 PRÊTS'!A:R,18,0),""))
B21: Signature de l'emprunteur : __________________________ | C21: Signature du Trésorier / Président : __________________________

Sheet 📊 TABLEAU DE BORD
A1: 📊 TABLEAU DE BORD — TONTINE SOLIDARITÉ PLUS 2027
A2: ="Mis à jour le "&TEXT(TODAY(),"DD/MM/YYYY")&" | Exercice "&'⚙️ PARAMÈTRES'!B13 -> #VALUE!
A4: 💰 TRÉSORERIE DISPONIBLE | D4: 📤 COTISATIONS TOTALES | G4: 🏦 PRÊTS OCTROYÉS | J4: 📈 INTÉRÊTS GÉNÉRÉS
A5: =IFERROR('🏧 CAISSE'!G503,0) -> 0 | D5: =IFERROR(SUM('💰 COTISATIONS'!BE4:BE53),0) -> 0 | G5: =IFERROR(SUM('🏦 PRÊTS'!F4:F63),0) -> 0 | J5: =IFERROR(SUM('🏦 PRÊTS'!L4:L63)+SUM('🏦 PRÊTS'!M4:M63)+SUM('🏦 PRÊTS'!N4:N63),0) -> 0
A9: 👥 MEMBRES ACTIFS | D9: ⚙️ TAUX D'INTÉRÊT | G9: ⚠️ PÉNALITÉS NON RECOUVRÉES | J9: 📊 ENCOURS PRÊTS
A10: =COUNTIF('👥 MEMBRES'!J5:J54,"Actif") -> 50 | D10: ='⚙️ PARAMÈTRES'!B4 -> 0.1 | G10: =IFERROR('⚠️ PÉNALITÉS'!I304,0) -> 0 | J10: =IFERROR(SUM('🏦 PRÊTS'!Q4:Q63),0) -> 0
A16: 🏆 CLASSEMENT DES MEMBRES PAR COTISATION
A17: RANG | B17: ID_MEMBRE | C17: NOM | D17: PRÉNOMS | E17: TOTAL COTISÉ | F17: PÉNALITÉS DUES | G17: PRÊTS EN COURS | H17: SOLDE NET | I17: STATUT
A18: 1 | B18: ='📋 SOLDE MEMBRES'!B4 -> TSP-2027-001 | C18: ='📋 SOLDE MEMBRES'!C4 -> 0 | D18: ='📋 SOLDE MEMBRES'!D4 -> 0 | E18: ='📋 SOLDE MEMBRES'!E4 -> 0 | F18: ='📋 SOLDE MEMBRES'!F4 -> 0 | G18: ='📋 SOLDE MEMBRES'!G4 -> 0 | H18: ='📋 SOLDE MEMBRES'!H4 -> 0 | I18: ='📋 SOLDE MEMBRES'!I4 -> ✅ À jour
A19: 2 | B19: ='📋 SOLDE MEMBRES'!B5 -> TSP-2027-002 | C19: ='📋 SOLDE MEMBRES'!C5 -> 0 | D19: ='📋 SOLDE MEMBRES'!D5 -> 0 | E19: ='📋 SOLDE MEMBRES'!E5 -> 0 | F19: ='📋 SOLDE MEMBRES'!F5 -> 0 | G19: ='📋 SOLDE MEMBRES'!G5 -> 0 | H19: ='📋 SOLDE MEMBRES'!H5 -> 0 | I19: ='📋 SOLDE MEMBRES'!I5 -> ✅ À jour
A20: 3 | B20: ='📋 SOLDE MEMBRES'!B6 -> TSP-2027-003 | C20: ='📋 SOLDE MEMBRES'!C6 -> 0 | D20: ='📋 SOLDE MEMBRES'!D6 -> 0 | E20: ='📋 SOLDE MEMBRES'!E6 -> 0 | F20: ='📋 SOLDE MEMBRES'!F6 -> 0 | G20: ='📋 SOLDE MEMBRES'!G6 -> 0 | H20: ='📋 SOLDE MEMBRES'!H6 -> 0 | I20: ='📋 SOLDE MEMBRES'!I6 -> ✅ À jour
A21: 4 | B21: ='📋 SOLDE MEMBRES'!B7 -> TSP-2027-004 | C21: ='📋 SOLDE MEMBRES'!C7 -> 0 | D21: ='📋 SOLDE MEMBRES'!D7 -> 0 | E21: ='📋 SOLDE MEMBRES'!E7 -> 0 | F21: ='📋 SOLDE MEMBRES'!F7 -> 0 | G21: ='📋 SOLDE MEMBRES'!G7 -> 0 | H21: ='📋 SOLDE MEMBRES'!H7 -> 0 | I21: ='📋 SOLDE MEMBRES'!I7 -> ✅ À jour
A22: 5 | B22: ='📋 SOLDE MEMBRES'!B8 -> TSP-2027-005 | C22: ='📋 SOLDE MEMBRES'!C8 -> 0 | D22: ='📋 SOLDE MEMBRES'!D8 -> 0 | E22: ='📋 SOLDE MEMBRES'!E8 -> 0 | F22: ='📋 SOLDE MEMBRES'!F8 -> 0 | G22: ='📋 SOLDE MEMBRES'!G8 -> 0 | H22: ='📋 SOLDE MEMBRES'!H8 -> 0 | I22: ='📋 SOLDE MEMBRES'!I8 -> ✅ À jour
A23: 6 | B23: ='📋 SOLDE MEMBRES'!B9 -> TSP-2027-006 | C23: ='📋 SOLDE MEMBRES'!C9 -> 0 | D23: ='📋 SOLDE MEMBRES'!D9 -> 0 | E23: ='📋 SOLDE MEMBRES'!E9 -> 0 | F23: ='📋 SOLDE MEMBRES'!F9 -> 0 | G23: ='📋 SOLDE MEMBRES'!G9 -> 0 | H23: ='📋 SOLDE MEMBRES'!H9 -> 0 | I23: ='📋 SOLDE MEMBRES'!I9 -> ✅ À jour
A24: 7 | B24: ='📋 SOLDE MEMBRES'!B10 -> TSP-2027-007 | C24: ='📋 SOLDE MEMBRES'!C10 -> 0 | D24: ='📋 SOLDE MEMBRES'!D10 -> 0 | E24: ='📋 SOLDE MEMBRES'!E10 -> 0 | F24: ='📋 SOLDE MEMBRES'!F10 -> 0 | G24: ='📋 SOLDE MEMBRES'!G10 -> 0 | H24: ='📋 SOLDE MEMBRES'!H10 -> 0 | I24: ='📋 SOLDE MEMBRES'!I10 -> ✅ À jour
A25: 8 | B25: ='📋 SOLDE MEMBRES'!B11 -> TSP-2027-008 | C25: ='📋 SOLDE MEMBRES'!C11 -> 0 | D25: ='📋 SOLDE MEMBRES'!D11 -> 0 | E25: ='📋 SOLDE MEMBRES'!E11 -> 0 | F25: ='📋 SOLDE MEMBRES'!F11 -> 0 | G25: ='📋 SOLDE MEMBRES'!G11 -> 0 | H25: ='📋 SOLDE MEMBRES'!H11 -> 0 | I25: ='📋 SOLDE MEMBRES'!I11 -> ✅ À jour
A26: 9 | B26: ='📋 SOLDE MEMBRES'!B12 -> TSP-2027-009 | C26: ='📋 SOLDE MEMBRES'!C12 -> 0 | D26: ='📋 SOLDE MEMBRES'!D12 -> 0 | E26: ='📋 SOLDE MEMBRES'!E12 -> 0 | F26: ='📋 SOLDE MEMBRES'!F12 -> 0 | G26: ='📋 SOLDE MEMBRES'!G12 -> 0 | H26: ='📋 SOLDE MEMBRES'!H12 -> 0 | I26: ='📋 SOLDE MEMBRES'!I12 -> ✅ À jour
A27: 10 | B27: ='📋 SOLDE MEMBRES'!B13 -> TSP-2027-010 | C27: ='📋 SOLDE MEMBRES'!C13 -> 0 | D27: ='📋 SOLDE MEMBRES'!D13 -> 0 | E27: ='📋 SOLDE MEMBRES'!E13 -> 0 | F27: ='📋 SOLDE MEMBRES'!F13 -> 0 | G27: ='📋 SOLDE MEMBRES'!G13 -> 0 | H27: ='📋 SOLDE MEMBRES'!H13 -> 0 | I27: ='📋 SOLDE MEMBRES'!I13 -> ✅ À jour
A28: 11 | B28: ='📋 SOLDE MEMBRES'!B14 -> TSP-2027-011 | C28: ='📋 SOLDE MEMBRES'!C14 -> 0 | D28: ='📋 SOLDE MEMBRES'!D14 -> 0 | E28: ='📋 SOLDE MEMBRES'!E14 -> 0 | F28: ='📋 SOLDE MEMBRES'!F14 -> 0 | G28: ='📋 SOLDE MEMBRES'!G14 -> 0 | H28: ='📋 SOLDE MEMBRES'!H14 -> 0 | I28: ='📋 SOLDE MEMBRES'!I14 -> ✅ À jour
A29: 12 | B29: ='📋 SOLDE MEMBRES'!B15 -> TSP-2027-012 | C29: ='📋 SOLDE MEMBRES'!C15 -> 0 | D29: ='📋 SOLDE MEMBRES'!D15 -> 0 | E29: ='📋 SOLDE MEMBRES'!E15 -> 0 | F29: ='📋 SOLDE MEMBRES'!F15 -> 0 | G29: ='📋 SOLDE MEMBRES'!G15 -> 0 | H29: ='📋 SOLDE MEMBRES'!H15 -> 0 | I29: ='📋 SOLDE MEMBRES'!I15 -> ✅ À jour
... A67: 50 | B67: ='📋 SOLDE MEMBRES'!B53 -> TSP-2027-050 | C67: ='📋 SOLDE MEMBRES'!C53 -> 0 | D67: ='📋 SOLDE MEMBRES'!D53 -> 0 | E67: ='📋 SOLDE MEMBRES'!E53 -> 0 | F67: ='📋 SOLDE MEMBRES'!F53 -> 0 | G67: ='📋 SOLDE MEMBRES'!G53 -> 0 | H67: ='📋 SOLDE MEMBRES'!H53 -> 0 | I67: ='📋 SOLDE MEMBRES'!I53 -> ✅ À jour
A70: 📅 RÉSUMÉ DES COTISATIONS PAR MOIS
A71: JANV. | B71: FÉVR. | C71: MARS | D71: AVRIL | E71: MAI | F71: JUIN | G71: JUIL. | H71: AOÛT | I71: SEPT. | J71: OCT. | K71: NOV. | L71: DÉC.
A72: ='💰 COTISATIONS'!E54+'💰 COTISATIONS'!F54+'💰 COTISATIONS'!G54+'💰 COTISATIONS'!H54+'💰 COTISATIONS'!I54 -> 0 | B72: ='💰 COTISATIONS'!J54+'💰 COTISATIONS'!K54+'💰 COTISATIONS'!L54+'💰 COTISATIONS'!M54 -> 0 | C72: ='💰 COTISATIONS'!N54+'💰 COTISATIONS'!O54+'💰 COTISATIONS'!P54+'💰 COTISATIONS'!Q54 -> 0 | D72: ='💰 COTISATIONS'!R54+'💰 COTISATIONS'!S54+'💰 COTISATIONS'!T54+'💰 COTISATIONS'!U54 -> 0 | E72: ='💰 COTISATIONS'!V54+'💰 COTISATIONS'!W54+'💰 COTISATIONS'!X54+'💰 COTISATIONS'!Y54+'💰 COTISATIONS'!Z54 -> 0 | F72: ='💰 COTISATIONS'!AA54+'💰 COTISATIONS'!AB54+'💰 COTISATIONS'!AC54+'💰 COTISATIONS'!AD54 -> 0 | G72: ='💰 COTISATIONS'!AE54+'💰 COTISATIONS'!AF54+'💰 COTISATIONS'!AG54+'💰 COTISATIONS'!AH54 -> 0 | H72: ='💰 COTISATIONS'!AI54+'💰 COTISATIONS'!AJ54+'💰 COTISATIONS'!AK54+'💰 COTISATIONS'!AL54+'💰 COTISATIONS'!AM54 -> 0 | I72: ='💰 COTISATIONS'!AN54+'💰 COTISATIONS'!AO54+'💰 COTISATIONS'!AP54+'💰 COTISATIONS'!AQ54 -> 0 | J72: ='💰 COTISATIONS'!AR54+'💰 COTISATIONS'!AS54+'💰 COTISATIONS'!AT54+'💰 COTISATIONS'!AU54+'💰 COTISATIONS'!AV54 -> 0 | K72: ='💰 COTISATIONS'!AW54+'💰 COTISATIONS'!AX54+'💰 COTISATIONS'!AY54+'💰 COTISATIONS'!AZ54 -> 0 | L72: ='💰 COTISATIONS'!BA54+'💰 COTISATIONS'!BB54+'💰 COTISATIONS'!BC54+'💰 COTISATIONS'!BD54 -> 0

Sheet 🪪 IDENTITÉ
A1: 🪪 FICHE D'IDENTITÉ DES MEMBRES — TONTINE SOLIDARITÉ PLUS 2027
A3: # | B3: ID_MEMBRE | C3: NOM | D3: PRÉNOMS | E3: TÉLÉPHONE | F3: EMAIL | G3: SEXE | H3: N° CARTE CIP | I3: DATE NAISSANCE | J3: PROFESSION | K3: ADRESSE | L3: PROVENANCE
A4: 1 | B4: ='👥 MEMBRES'!A5 -> TSP-2027-001 | C4: ='👥 MEMBRES'!B5 -> 0 | D4: ='👥 MEMBRES'!C5 -> 0 | E4: ='👥 MEMBRES'!D5 -> 0 | F4: ='👥 MEMBRES'!E5 -> 0 | G4: ='👥 MEMBRES'!F5 -> 0 | H4: ='👥 MEMBRES'!G5 -> 0 | I4: ='👥 MEMBRES'!H5 -> 0 | J4: ='👥 MEMBRES'!M5 -> 0 | K4: ='👥 MEMBRES'!L5 -> 0 | L4: ='👥 MEMBRES'!M5 -> 0
A5: 2 | B5: ='👥 MEMBRES'!A6 -> TSP-2027-002 | C5: ='👥 MEMBRES'!B6 -> 0 | D5: ='👥 MEMBRES'!C6 -> 0 | E5: ='👥 MEMBRES'!D6 -> 0 | F5: ='👥 MEMBRES'!E6 -> 0 | G5: ='👥 MEMBRES'!F6 -> 0 | H5: ='👥 MEMBRES'!G6 -> 0 | I5: ='👥 MEMBRES'!H6 -> 0 | J5: ='👥 MEMBRES'!M6 -> 0 | K5: ='👥 MEMBRES'!L6 -> 0 | L5: ='👥 MEMBRES'!M6 -> 0
A6: 3 | B6: ='👥 MEMBRES'!A7 -> TSP-2027-003 | C6: ='👥 MEMBRES'!B7 -> 0 | D6: ='👥 MEMBRES'!C7 -> 0 | E6: ='👥 MEMBRES'!D7 -> 0 | F6: ='👥 MEMBRES'!E7 -> 0 | G6: ='👥 MEMBRES'!F7 -> 0 | H6: ='👥 MEMBRES'!G7 -> 0 | I6: ='👥 MEMBRES'!H7 -> 0 | J6: ='👥 MEMBRES'!M7 -> 0 | K6: ='👥 MEMBRES'!L7 -> 0 | L6: ='👥 MEMBRES'!M7 -> 0
A7: 4 | B7: ='👥 MEMBRES'!A8 -> TSP-2027-004 | C7: ='👥 MEMBRES'!B8 -> 0 | D7: ='👥 MEMBRES'!C8 -> 0 | E7: ='👥 MEMBRES'!D8 -> 0 | F7: ='👥 MEMBRES'!E8 -> 0 | G7: ='👥 MEMBRES'!F8 -> 0 | H7: ='👥 MEMBRES'!G8 -> 0 | I7: ='👥 MEMBRES'!H8 -> 0 | J7: ='👥 MEMBRES'!M8 -> 0 | K7: ='👥 MEMBRES'!L8 -> 0 | L7: ='👥 MEMBRES'!M8 -> 0
A8: 5 | B8: ='👥 MEMBRES'!A9 -> TSP-2027-005 | C8: ='👥 MEMBRES'!B9 -> 0 | D8: ='👥 MEMBRES'!C9 -> 0 | E8: ='👥 MEMBRES'!D9 -> 0 | F8: ='👥 MEMBRES'!E9 -> 0 | G8: ='👥 MEMBRES'!F9 -> 0 | H8: ='👥 MEMBRES'!G9 -> 0 | I8: ='👥 MEMBRES'!H9 -> 0 | J8: ='👥 MEMBRES'!M9 -> 0 | K8: ='👥 MEMBRES'!L9 -> 0 | L8: ='👥 MEMBRES'!M9 -> 0
A9: 6 | B9: ='👥 MEMBRES'!A10 -> TSP-2027-006 | C9: ='👥 MEMBRES'!B10 -> 0 | D9: ='👥 MEMBRES'!C10 -> 0 | E9: ='👥 MEMBRES'!D10 -> 0 | F9: ='👥 MEMBRES'!E10 -> 0 | G9: ='👥 MEMBRES'!F10 -> 0 | H9: ='👥 MEMBRES'!G10 -> 0 | I9: ='👥 MEMBRES'!H10 -> 0 | J9: ='👥 MEMBRES'!M10 -> 0 | K9: ='👥 MEMBRES'!L10 -> 0 | L9: ='👥 MEMBRES'!M10 -> 0
A10: 7 | B10: ='👥 MEMBRES'!A11 -> TSP-2027-007 | C10: ='👥 MEMBRES'!B11 -> 0 | D10: ='👥 MEMBRES'!C11 -> 0 | E10: ='👥 MEMBRES'!D11 -> 0 | F10: ='👥 MEMBRES'!E11 -> 0 | G10: ='👥 MEMBRES'!F11 -> 0 | H10: ='👥 MEMBRES'!G11 -> 0 | I10: ='👥 MEMBRES'!H11 -> 0 | J10: ='👥 MEMBRES'!M11 -> 0 | K10: ='👥 MEMBRES'!L11 -> 0 | L10: ='👥 MEMBRES'!M11 -> 0
A11: 8 | B11: ='👥 MEMBRES'!A12 -> TSP-2027-008 | C11: ='👥 MEMBRES'!B12 -> 0 | D11: ='👥 MEMBRES'!C12 -> 0 | E11: ='👥 MEMBRES'!D12 -> 0 | F11: ='👥 MEMBRES'!E12 -> 0 | G11: ='👥 MEMBRES'!F12 -> 0 | H11: ='👥 MEMBRES'!G12 -> 0 | I11: ='👥 MEMBRES'!H12 -> 0 | J11: ='👥 MEMBRES'!M12 -> 0 | K11: ='👥 MEMBRES'!L12 -> 0 | L11: ='👥 MEMBRES'!M12 -> 0
A12: 9 | B12: ='👥 MEMBRES'!A13 -> TSP-2027-009 | C12: ='👥 MEMBRES'!B13 -> 0 | D12: ='👥 MEMBRES'!C13 -> 0 | E12: ='👥 MEMBRES'!D13 -> 0 | F12: ='👥 MEMBRES'!E13 -> 0 | G12: ='👥 MEMBRES'!F13 -> 0 | H12: ='👥 MEMBRES'!G13 -> 0 | I12: ='👥 MEMBRES'!H13 -> 0 | J12: ='👥 MEMBRES'!M13 -> 0 | K12: ='👥 MEMBRES'!L13 -> 0 | L12: ='👥 MEMBRES'!M13 -> 0
A13: 10 | B13: ='👥 MEMBRES'!A14 -> TSP-2027-010 | C13: ='👥 MEMBRES'!B14 -> 0 | D13: ='👥 MEMBRES'!C14 -> 0 | E13: ='👥 MEMBRES'!D14 -> 0 | F13: ='👥 MEMBRES'!E14 -> 0 | G13: ='👥 MEMBRES'!F14 -> 0 | H13: ='👥 MEMBRES'!G14 -> 0 | I13: ='👥 MEMBRES'!H14 -> 0 | J13: ='👥 MEMBRES'!M14 -> 0 | K13: ='👥 MEMBRES'!L14 -> 0 | L13: ='👥 MEMBRES'!M14 -> 0
A14: 11 | B14: ='👥 MEMBRES'!A15 -> TSP-2027-011 | C14: ='👥 MEMBRES'!B15 -> 0 | D14: ='👥 MEMBRES'!C15 -> 0 | E14: ='👥 MEMBRES'!D15 -> 0 | F14: ='👥 MEMBRES'!E15 -> 0 | G14: ='👥 MEMBRES'!F15 -> 0 | H14: ='👥 MEMBRES'!G15 -> 0 | I14: ='👥 MEMBRES'!H15 -> 0 | J14: ='👥 MEMBRES'!M15 -> 0 | K14: ='👥 MEMBRES'!L15 -> 0 | L14: ='👥 MEMBRES'!M15 -> 0
A15: 12 | B15: ='👥 MEMBRES'!A16 -> TSP-2027-012 | C15: ='👥 MEMBRES'!B16 -> 0 | D15: ='👥 MEMBRES'!C16 -> 0 | E15: ='👥 MEMBRES'!D16 -> 0 | F15: ='👥 MEMBRES'!E16 -> 0 | G15: ='👥 MEMBRES'!F16 -> 0 | H15: ='👥 MEMBRES'!G16 -> 0 | I15: ='👥 MEMBRES'!H16 -> 0 | J15: ='👥 MEMBRES'!M16 -> 0 | K15: ='👥 MEMBRES'!L16 -> 0 | L15: ='👥 MEMBRES'!M16 -> 0
... A53: 50 | B53: ='👥 MEMBRES'!A54 -> TSP-2027-050 | C53: ='👥 MEMBRES'!B54 -> 0 | D53: ='👥 MEMBRES'!C54 -> 0 | E53: ='👥 MEMBRES'!D54 -> 0 | F53: ='👥 MEMBRES'!E54 -> 0 | G53: ='👥 MEMBRES'!F54 -> 0 | H53: ='👥 MEMBRES'!G54 -> 0 | I53: ='👥 MEMBRES'!H54 -> 0 | J53: ='👥 MEMBRES'!M54 -> 0 | K53: ='👥 MEMBRES'!L54 -> 0 | L53: ='👥 MEMBRES'!M54 -> 0
