Workbook

Sheet 🏠 ACCUEIL
A1: 🏦 TONTINE SOLIDARITÉ PLUS 2027
A2: Système de Gestion Financière Professionnelle
A3: Bienvenue dans votre espace de gestion de tontine. Naviguez via les onglets ci-dessous.
B6: 👥 MEMBRES | D6: 💰 COTISATIONS | F6: 🏦 PRÊTS | H6: ⚠️ PÉNALITÉS | J6: 📊 TABLEAU DE BORD
B8: 📋 MODULES DISPONIBLES • Gestion des membres & identités • Suivi hebdomadaire des cotisations • Gestion des prêts & remboursements • Calcul automatique des pénalités • Tableau de bord dynamique | F8: ⚙️ PARAMÈTRES CLÉS • Taux d'intérêt : 12% (modifiable) • Cotisation standard : 2 500 FCFA/semaine • Pénalité retard : 100: FCFA • Pénalité absence : 500 FCFA • 23 membres actifs
B12: 💡 MODE D'EMPLOI : Toutes les feuilles sont interconnectées par ID_MEMBRE. Ne jamais modifier les IDs. Les formules se recalculent automatiquement.
B15: Fichier généré le 13/03/2026 | Version 2.0 Professionnelle

Sheet ⚙️ PARAMÈTRES
A1: ⚙️ PARAMÈTRES SYSTÈME – TONTINE SOLIDARITÉ PLUS 2027
A2: Modifiez UNIQUEMENT les cellules en bleu (colonne VALEUR). Toutes les formules se mettront à jour automatiquement.
A3: PARAMÈTRE | B3: VALEUR | C3: UNITÉ | D3: DESCRIPTION | E3: MODIFIÉ PAR
A4: Taux d'Intérêt | B4: 0.12 | C4: % | D4: Taux appliqué à TOUS les prêts | E4: Trésorier
A5: Cotisation Hebdo Standard | B5: 2500 | C5: FCFA | D5: Montant standard de cotisation/semaine | E5: Bureau
A6: Pénalité Retard Cotisation | B6: 100 | C6: FCFA | D6: Pénalité par semaine de retard | E6: Bureau
A7: Pénalité Absence Réunion | B7: 1000 | C7: FCFA | D7: Pénalité par absence réunion mensuelle | E7: Bureau
A8: Frais de Retrait Prêt | B8: 0.02 | C8: % | D8: Frais appliqués au montant du prêt | E8: Bureau
A9: Durée Max Prêt (semaines) | B9: 12 | C9: semaines | D9: Durée maximale autorisée pour un prêt | E9: Bureau
A10: Nombre de Membres | B10: 23 | C10: membres | D10: Mis à jour automatiquement | E10: Automatique
A11: Année en cours | B11: 2027 | C11: année | D11: Exercice financier | E11: Bureau
A13: 📌 RÉFÉRENCES : Taux intérêt = cellule B4 | Cotisation standard = B5 | Pénalité retard = B6 | Pénalité absence = B7 | Frais retrait = B8

Sheet 👥 MEMBRES
A1: 👥 REGISTRE DES MEMBRES – TONTINE SOLIDARITÉ PLUS 2027
A2: Total membres : 23 | Mis à jour le 13/03/2026
A4: ID | B4: NOM | C4: PRÉNOMS | D4: TÉLÉPHONE | E4: EMAIL | F4: SEXE | G4: N° CIP | H4: DATE NAISSANCE | I4: DATE ADHÉSION | J4: STATUT
A5: 1 | J5: Actif
A6: 2 | J6: Actif
A7: 3 | J7: Actif
A8: 4 | J8: Actif
A9: 5 | J9: Actif
A10: 6 | J10: Actif
A11: 7 | J11: Actif
A12: 8 | J12: Actif
A13: 9 | J13: Actif
A14: 10 | J14: Actif
A15: 11 | J15: Actif
A16: 12 | J16: Actif
... A27: 23 | J27: Actif
A28: TOTAL MEMBRES ACTIFS | J28: =COUNTIF(J5:J27,"Actif") -> 23

Sheet 💰 COTISATIONS
A1: 💰 REGISTRE DES COTISATIONS HEBDOMADAIRES – TONTINE SOLIDARITÉ PLUS 2026
A2: Saisir les montants en FCFA | Cellules vides = absence | TOTAL calculé automatiquement
E3: JANVIER | J3: FÉVRIER | N3: MARS | R3: AVRIL | V3: MAI | AA3: JUIN | AE3: JUILLET | AI3: AOÛT | AN3: SEPTEMBRE | AR3: OCTOBRE | AW3: NOVEMBRE | BA3: DÉCEMBRE
A4: ID | B4: NOM | C4: PRÉNOMS | D4: CIBLE /SEM. | E4: 46390 | F4: 46032 | G4: 46404 | H4: 46411 | I4: 46418 | J4: 46425 | K4: 46432 | L4: 46439 | M4: 46446 | N4: 46453 | O4: 46460 | P4: 46467 | Q4: 46474 | R4: 46481 | S4: 46488 | T4: 46495 | U4: 46502 | V4: 46509 | W4: 46516 | X4: 46523 | Y4: 46530 | Z4: 46537 | AA4: 46544 | AB4: 46551 | AC4: 46558 | AD4: 46565 | AE4: 46572 | AF4: 46579 | AG4: 46586 | AH4: 46593 | AI4: 46600 | AJ4: 46607 | AK4: 46614 | AL4: 46621 | AM4: 46628 | AN4: 46635 | AO4: 46642 | AP4: 46649 | AQ4: 46656 | AR4: 46663 | AS4: 46670 | AT4: 46677 | AU4: 46319 | AV4: 46326 | AW4: 46333 | AX4: 46340 | AY4: 46347 | AZ4: 46354 | BA4: 46361 | BB4: 46368 | BC4: 46375 | BD4: 46382 | BE4: TOTAL COTISÉ (FCFA) | BF4: SEMAINES PAYÉES | BG4: STATUT
A5: 1 | BE5: =SUM(E5:BD5) -> 0 | BF5: =COUNTA(E5:BD5) -> 0 | BG5: =IF(BE5=0,"⬜ Aucun",IF(BE5>=D5*10,"✅ À jour","⚠️ Retard")) -> ⬜ Aucun
A6: 2 | BE6: =SUM(E6:BD6) -> 0 | BF6: =COUNTA(E6:BD6) -> 0 | BG6: =IF(BE6=0,"⬜ Aucun",IF(BE6>=D6*10,"✅ À jour","⚠️ Retard")) -> ⬜ Aucun
A7: 3 | BE7: =SUM(E7:BD7) -> 0 | BF7: =COUNTA(E7:BD7) -> 0 | BG7: =IF(BE7=0,"⬜ Aucun",IF(BE7>=D7*10,"✅ À jour","⚠️ Retard")) -> ⬜ Aucun
A8: 4 | BE8: =SUM(E8:BD8) -> 0 | BF8: =COUNTA(E8:BD8) -> 0 | BG8: =IF(BE8=0,"⬜ Aucun",IF(BE8>=D8*10,"✅ À jour","⚠️ Retard")) -> ⬜ Aucun
A9: 5 | BE9: =SUM(E9:BD9) -> 0 | BF9: =COUNTA(E9:BD9) -> 0 | BG9: =IF(BE9=0,"⬜ Aucun",IF(BE9>=D9*10,"✅ À jour","⚠️ Retard")) -> ⬜ Aucun
A10: 6 | BE10: =SUM(E10:BD10) -> 0 | BF10: =COUNTA(E10:BD10) -> 0 | BG10: =IF(BE10=0,"⬜ Aucun",IF(BE10>=D10*10,"✅ À jour","⚠️ Retard")) -> ⬜ Aucun
A11: 7 | BE11: =SUM(E11:BD11) -> 0 | BF11: =COUNTA(E11:BD11) -> 0 | BG11: =IF(BE11=0,"⬜ Aucun",IF(BE11>=D11*10,"✅ À jour","⚠️ Retard")) -> ⬜ Aucun
A12: 8 | BE12: =SUM(E12:BD12) -> 0 | BF12: =COUNTA(E12:BD12) -> 0 | BG12: =IF(BE12=0,"⬜ Aucun",IF(BE12>=D12*10,"✅ À jour","⚠️ Retard")) -> ⬜ Aucun
A13: 9 | BE13: =SUM(E13:BD13) -> 0 | BF13: =COUNTA(E13:BD13) -> 0 | BG13: =IF(BE13=0,"⬜ Aucun",IF(BE13>=D13*10,"✅ À jour","⚠️ Retard")) -> ⬜ Aucun
A14: 10 | BE14: =SUM(E14:BD14) -> 0 | BF14: =COUNTA(E14:BD14) -> 0 | BG14: =IF(BE14=0,"⬜ Aucun",IF(BE14>=D14*10,"✅ À jour","⚠️ Retard")) -> ⬜ Aucun
A15: 11 | BE15: =SUM(E15:BD15) -> 0 | BF15: =COUNTA(E15:BD15) -> 0 | BG15: =IF(BE15=0,"⬜ Aucun",IF(BE15>=D15*10,"✅ À jour","⚠️ Retard")) -> ⬜ Aucun
A16: 12 | BE16: =SUM(E16:BD16) -> 0 | BF16: =COUNTA(E16:BD16) -> 0 | BG16: =IF(BE16=0,"⬜ Aucun",IF(BE16>=D16*10,"✅ À jour","⚠️ Retard")) -> ⬜ Aucun
... A27: 23 | BE27: =SUM(E27:BD27) -> 0 | BF27: =COUNTA(E27:BD27) -> 0 | BG27: =IF(BE27=0,"⬜ Aucun",IF(BE27>=D27*10,"✅ À jour","⚠️ Retard")) -> ⬜ Aucun
A28: 🏦 TOTAL GÉNÉRAL | E28: =SUM(E5:E27) -> 0 | F28: =SUM(F5:F27) -> 0 | G28: =SUM(G5:G27) -> 0 | I28: =SUM(I5:I27) -> 0 | J28: =SUM(J5:J27) -> 0 | K28: =SUM(K5:K27) -> 0 | L28: =SUM(L5:L27) -> 0 | M28: =SUM(M5:M27) -> 0 | N28: =SUM(N5:N27) -> 0 | O28: =SUM(O5:O27) -> 0 | P28: =SUM(P5:P27) -> 0 | ... AT28: =SUM(AT5:AT27) -> 0 | AV28: =SUM(AV5:AV27) -> 0 | AW28: =SUM(AW5:AW27) -> 0 | AX28: =SUM(AX5:AX27) -> 0 | AY28: =SUM(AY5:AY27) -> 0 | AZ28: =SUM(AZ5:AZ27) -> 0 | BA28: =SUM(BA5:BA27) -> 0 | BB28: =SUM(BB5:BB27) -> 0 | BC28: =SUM(BC5:BC27) -> 0 | ... BE28: =SUM(BE5:BE27) -> 0

Sheet 🏦 PRÊTS
A1: 🏦 REGISTRE DES PRÊTS – TONTINE SOLIDARITÉ PLUS 2027
A2: Taux d'intérêt lié à l'onglet PARAMÈTRES (cellule B4) – Mise à jour automatique
A3: ⚙️ TAUX D'INTÉRÊT ACTUEL : | G3: ='⚙️ PARAMÈTRES'!B4 -> 0.12
A4: ID | B4: ID_MEMBRE | C4: NOM | D4: PRÉNOMS | E4: DATE DU PRÊT | F4: MONTANT (FCFA) | G4: FRAIS RETRAIT | H4: GARANTIE | I4: DATE ÉCHÉANCE | J4: INTÉRÊTS (FCFA) | K4: MONTANT DÛ TOTAL | L4: STATUT
A5: 1 | L5: En cours
A6: 2 | L6: En cours
A7: 3 | L7: En cours
A8: 4 | L8: En cours
A9: 5 | L9: En cours
J13: =IF(F13="","",F13*'⚙️ PARAMÈTRES'!$B$4) | K13: =IF(F13="","",F13+G13+J13)
J14: =IF(F14="","",F14*'⚙️ PARAMÈTRES'!$B$4) | K14: =IF(F14="","",F14+G14+J14)
J15: =IF(F15="","",F15*'⚙️ PARAMÈTRES'!$B$4) | K15: =IF(F15="","",F15+G15+J15)
J16: =IF(F16="","",F16*'⚙️ PARAMÈTRES'!$B$4) | K16: =IF(F16="","",F16+G16+J16)
J17: =IF(F17="","",F17*'⚙️ PARAMÈTRES'!$B$4) | K17: =IF(F17="","",F17+G17+J17)
J18: =IF(F18="","",F18*'⚙️ PARAMÈTRES'!$B$4) | K18: =IF(F18="","",F18+G18+J18)
J19: =IF(F19="","",F19*'⚙️ PARAMÈTRES'!$B$4) | K19: =IF(F19="","",F19+G19+J19)
J20: =IF(F20="","",F20*'⚙️ PARAMÈTRES'!$B$4) | K20: =IF(F20="","",F20+G20+J20)
J21: =IF(F21="","",F21*'⚙️ PARAMÈTRES'!$B$4) | K21: =IF(F21="","",F21+G21+J21)
J22: =IF(F22="","",F22*'⚙️ PARAMÈTRES'!$B$4) | K22: =IF(F22="","",F22+G22+J22)
J23: =IF(F23="","",F23*'⚙️ PARAMÈTRES'!$B$4) | K23: =IF(F23="","",F23+G23+J23)
J24: =IF(F24="","",F24*'⚙️ PARAMÈTRES'!$B$4) | K24: =IF(F24="","",F24+G24+J24)
... J34: =IF(F34="","",F34*'⚙️ PARAMÈTRES'!$B$4) | K34: =IF(F34="","",F34+G34+J34)
A35: 🏦 TOTAUX | F35: =SUM(F5:F34) -> 0 | G35: =SUM(G5:G34) -> 0 | J35: =SUM(J5:J34) -> 0 | K35: =SUM(K5:K34) -> 0

Sheet 🔄 REMBOURSEMENTS
A1: 🔄 SUIVI DES REMBOURSEMENTS – TONTINE SOLIDARITÉ PLUS 2027
A2: Chaque remboursement est lié au prêt via ID_PRÊT | Solde recalculé automatiquement
A4: ID_REM | B4: ID_PRÊT | C4: NOM | D4: PRÉNOMS | E4: DATE REMB. | F4: MONTANT (FCFA) | G4: CAPITAL | H4: INTÉRÊTS | I4: SOLDE RESTANT | J4: STATUT
I9: =IF(B9="","",_xludf.XLOOKUP(B9,'🏦 PRÊTS'!A$5:A$34,'🏦 PRÊTS'!K$5:K$34,"")-SUMIF(B$5:B9,B9,F$5:F9))
I10: =IF(B10="","",_xludf.XLOOKUP(B10,'🏦 PRÊTS'!A$5:A$34,'🏦 PRÊTS'!K$5:K$34,"")-SUMIF(B$5:B10,B10,F$5:F10))
I11: =IF(B11="","",_xludf.XLOOKUP(B11,'🏦 PRÊTS'!A$5:A$34,'🏦 PRÊTS'!K$5:K$34,"")-SUMIF(B$5:B11,B11,F$5:F11))
I12: =IF(B12="","",_xludf.XLOOKUP(B12,'🏦 PRÊTS'!A$5:A$34,'🏦 PRÊTS'!K$5:K$34,"")-SUMIF(B$5:B12,B12,F$5:F12))
I13: =IF(B13="","",_xludf.XLOOKUP(B13,'🏦 PRÊTS'!A$5:A$34,'🏦 PRÊTS'!K$5:K$34,"")-SUMIF(B$5:B13,B13,F$5:F13))
I14: =IF(B14="","",_xludf.XLOOKUP(B14,'🏦 PRÊTS'!A$5:A$34,'🏦 PRÊTS'!K$5:K$34,"")-SUMIF(B$5:B14,B14,F$5:F14))
I15: =IF(B15="","",_xludf.XLOOKUP(B15,'🏦 PRÊTS'!A$5:A$34,'🏦 PRÊTS'!K$5:K$34,"")-SUMIF(B$5:B15,B15,F$5:F15))
I16: =IF(B16="","",_xludf.XLOOKUP(B16,'🏦 PRÊTS'!A$5:A$34,'🏦 PRÊTS'!K$5:K$34,"")-SUMIF(B$5:B16,B16,F$5:F16))
I17: =IF(B17="","",_xludf.XLOOKUP(B17,'🏦 PRÊTS'!A$5:A$34,'🏦 PRÊTS'!K$5:K$34,"")-SUMIF(B$5:B17,B17,F$5:F17))
I18: =IF(B18="","",_xludf.XLOOKUP(B18,'🏦 PRÊTS'!A$5:A$34,'🏦 PRÊTS'!K$5:K$34,"")-SUMIF(B$5:B18,B18,F$5:F18))
I19: =IF(B19="","",_xludf.XLOOKUP(B19,'🏦 PRÊTS'!A$5:A$34,'🏦 PRÊTS'!K$5:K$34,"")-SUMIF(B$5:B19,B19,F$5:F19))
I20: =IF(B20="","",_xludf.XLOOKUP(B20,'🏦 PRÊTS'!A$5:A$34,'🏦 PRÊTS'!K$5:K$34,"")-SUMIF(B$5:B20,B20,F$5:F20))
... I49: =IF(B49="","",_xludf.XLOOKUP(B49,'🏦 PRÊTS'!A$5:A$34,'🏦 PRÊTS'!K$5:K$34,"")-SUMIF(B$5:B49,B49,F$5:F49))

Sheet ⚠️ PÉNALITÉS
A1: ⚠️ REGISTRE DES PÉNALITÉS – TONTINE SOLIDARITÉ PLUS 2027
A2: Pénalité retard : 100 FCFA/sem | Absence réunion : 1 000 FCFA — liées aux PARAMÈTRES
A4: ID_PEN | B4: ID_MEM | C4: NOM | D4: PRÉNOMS | E4: DATE | F4: MOTIF | G4: MONTANT (FCFA) | H4: PAYÉ ? | I4: SOLDE PEN.
I13: =IF(H13="","",IF(H13="Oui",0,IF(H13="Non",G13,G13/2)))
I14: =IF(H14="","",IF(H14="Oui",0,IF(H14="Non",G14,G14/2)))
I15: =IF(H15="","",IF(H15="Oui",0,IF(H15="Non",G15,G15/2)))
I16: =IF(H16="","",IF(H16="Oui",0,IF(H16="Non",G16,G16/2)))
I17: =IF(H17="","",IF(H17="Oui",0,IF(H17="Non",G17,G17/2)))
I18: =IF(H18="","",IF(H18="Oui",0,IF(H18="Non",G18,G18/2)))
I19: =IF(H19="","",IF(H19="Oui",0,IF(H19="Non",G19,G19/2)))
I20: =IF(H20="","",IF(H20="Oui",0,IF(H20="Non",G20,G20/2)))
I21: =IF(H21="","",IF(H21="Oui",0,IF(H21="Non",G21,G21/2)))
I22: =IF(H22="","",IF(H22="Oui",0,IF(H22="Non",G22,G22/2)))
I23: =IF(H23="","",IF(H23="Oui",0,IF(H23="Non",G23,G23/2)))
I24: =IF(H24="","",IF(H24="Oui",0,IF(H24="Non",G24,G24/2)))
... I59: =IF(H59="","",IF(H59="Oui",0,IF(H59="Non",G59,G59/2)))
A60: TOTAL PÉNALITÉS NON RECOUVRÉES | G60: =SUM(G5:G59) -> 0 | I60: =SUM(I5:I59) -> 0

Sheet 🏧 CAISSE
A1: 🏧 JOURNAL DE CAISSE – TONTINE SOLIDARITÉ PLUS 2027
A2: Toutes les entrées et sorties | Solde calculé automatiquement après chaque opération
A3: 📅 SOLDE INITIAL (FCFA) | D3: 0 | H3: ← Saisir le solde d'ouverture
A4: ID_TXN | B4: DATE | C4: TYPE | D4: DESCRIPTION | E4: ENTRÉE (FCFA) | F4: SORTIE (FCFA) | G4: SOLDE (FCFA) | H4: RÉFÉRENCE | I4: ORIGINE | J4: SAISI PAR
A5: 1 | B5: 04/01/2026 | C5: Entrée | D5: Cotisations semaine 1 | E5: 14500 | F5: 0 | G5: =D$3+E5-F5 -> 14500 | H5: Cotisation | I5: Trésorier
A6: 2 | B6: 11/01/2026 | C6: Entrée | D6: Cotisations semaine 2 | E6: 22000 | F6: 0 | G6: =G5+E6-F6 -> 36500 | H6: Cotisation | I6: Trésorier
A7: 3 | B7: 18/01/2026 | C7: Entrée | D7: Cotisations semaine 3 | E7: 22000 | F7: 0 | G7: =G6+E7-F7 -> 58500 | H7: Cotisation | I7: Trésorier
A8: 4 | B8: 25/01/2026 | C8: Entrée | D8: Cotisations semaine 4 | E8: 22000 | F8: 0 | G8: =G7+E8-F8 -> 80500 | H8: Cotisation | I8: Trésorier
A9: 5 | B9: 04/01/2026 | C9: Sortie | D9: Prêt AGBLE Vidéhou - ID#1 | E9: 0 | F9: 30850 | G9: =G8+E9-F9 -> 49650 | H9: Prêt octroyé | I9: Trésorier
A10: 6 | B10: 11/01/2026 | C10: Sortie | D10: Prêt AGBLE Josias - ID#2 | E10: 0 | F10: 15100 | G10: =G9+E10-F10 -> 34550 | H10: Prêt octroyé | I10: Trésorier
A11: 7 | B11: 18/01/2026 | C11: Sortie | D11: Prêt AHOUANDJINOU P. - ID#3 | E11: 0 | F11: 4000 | G11: =G10+E11-F11 -> 30550 | H11: Prêt octroyé | I11: Trésorier
A12: 8 | B12: 01/02/2026 | C12: Sortie | D12: Prêt OKPE Mathilde - ID#4 | E12: 0 | F12: 20100 | G12: =G11+E12-F12 -> 10450 | H12: Prêt octroyé | I12: Trésorier
G17: =IF(AND(E17=0,F17=0),"",G16+E17-F17)
G18: =IF(AND(E18=0,F18=0),"",G17+E18-F18)
G19: =IF(AND(E19=0,F19=0),"",G18+E19-F19)
G20: =IF(AND(E20=0,F20=0),"",G19+E20-F20)
G21: =IF(AND(E21=0,F21=0),"",G20+E21-F21)
G22: =IF(AND(E22=0,F22=0),"",G21+E22-F22)
G23: =IF(AND(E23=0,F23=0),"",G22+E23-F23)
G24: =IF(AND(E24=0,F24=0),"",G23+E24-F24)
G25: =IF(AND(E25=0,F25=0),"",G24+E25-F25)
G26: =IF(AND(E26=0,F26=0),"",G25+E26-F26)
G27: =IF(AND(E27=0,F27=0),"",G26+E27-F27)
G28: =IF(AND(E28=0,F28=0),"",G27+E28-F28)
... G149: =IF(AND(E149=0,F149=0),"",G148+E149-F149)

Sheet 📋 SOLDE MEMBRES
A1: 📋 SOLDE GLOBAL PAR MEMBRE – TONTINE SOLIDARITÉ PLUS 2027
A2: Données liées automatiquement aux onglets COTISATIONS, PRÊTS et PÉNALITÉS
A3: # | B3: ID_MEM | C3: NOM | D3: PRÉNOMS | E3: TOTAL COTISÉ (FCFA) | F3: PÉNALITÉS DUES (FCFA) | G3: PRÊTS EN COURS (FCFA) | H3: SOLDE NET (FCFA) | I3: STATUT
A4: 1 | I4: =IF(F4>0,"⚠️ Pénalités",IF(G4>0,"🏦 Prêt actif","✅ À jour")) -> ✅ À jour
A5: 2 | I5: =IF(F5>0,"⚠️ Pénalités",IF(G5>0,"🏦 Prêt actif","✅ À jour")) -> ✅ À jour
A6: 3 | I6: =IF(F6>0,"⚠️ Pénalités",IF(G6>0,"🏦 Prêt actif","✅ À jour")) -> ✅ À jour
A7: 4 | I7: =IF(F7>0,"⚠️ Pénalités",IF(G7>0,"🏦 Prêt actif","✅ À jour")) -> ✅ À jour
A8: 5 | I8: =IF(F8>0,"⚠️ Pénalités",IF(G8>0,"🏦 Prêt actif","✅ À jour")) -> ✅ À jour
A9: 6 | I9: =IF(F9>0,"⚠️ Pénalités",IF(G9>0,"🏦 Prêt actif","✅ À jour")) -> ✅ À jour
A10: 7 | I10: =IF(F10>0,"⚠️ Pénalités",IF(G10>0,"🏦 Prêt actif","✅ À jour")) -> ✅ À jour
A11: 8 | I11: =IF(F11>0,"⚠️ Pénalités",IF(G11>0,"🏦 Prêt actif","✅ À jour")) -> ✅ À jour
A12: 9 | I12: =IF(F12>0,"⚠️ Pénalités",IF(G12>0,"🏦 Prêt actif","✅ À jour")) -> ✅ À jour
A13: 10 | I13: =IF(F13>0,"⚠️ Pénalités",IF(G13>0,"🏦 Prêt actif","✅ À jour")) -> ✅ À jour
A14: 11 | I14: =IF(F14>0,"⚠️ Pénalités",IF(G14>0,"🏦 Prêt actif","✅ À jour")) -> ✅ À jour
A15: 12 | I15: =IF(F15>0,"⚠️ Pénalités",IF(G15>0,"🏦 Prêt actif","✅ À jour")) -> ✅ À jour
... A26: 23 | I26: =IF(F26>0,"⚠️ Pénalités",IF(G26>0,"🏦 Prêt actif","✅ À jour")) -> ✅ À jour
A27: TOTAUX | E27: =SUM(E4:E26) -> 0 | F27: =SUM(F4:F26) -> 0 | G27: =SUM(G4:G26) -> 0 | H27: =SUM(H4:H26) -> 0

Sheet 📊 TABLEAU DE BORD
A1: 📊 TABLEAU DE BORD – TONTINE SOLIDARITÉ PLUS 2027
A2: Mise à jour automatique en temps réel | Données liées à tous les onglets
A4: 💰 TOTAL EN CAISSE | D4: 📤 COTISATIONS TOTALES | G4: 🏦 PRÊTS OCTROYÉS | J4: 📈 INTÉRÊTS GÉNÉRÉS
A5: ='🏧 CAISSE'!G14 -> 0 | D5: ='💰 COTISATIONS'!BE28 -> 0 | G5: ='🏦 PRÊTS'!F35 -> 0 | J5: ='🏦 PRÊTS'!J35 -> 0
A8: 👥 MEMBRES ACTIFS | D8: ⚙️ TAUX D'INTÉRÊT | G8: ⚠️ PÉNALITÉS NON RECOUVRÉES | J8: 📊 MONTANT DÛ TOTAL (PRÊTS)
A9: ='👥 MEMBRES'!J28 -> 23 | D9: ='⚙️ PARAMÈTRES'!B4 -> 0.12 | G9: ='⚠️ PÉNALITÉS'!I60 -> 0 | J9: ='🏦 PRÊTS'!K35 -> 0
A11: 🏆 CLASSEMENT DES MEMBRES PAR COTISATION
A12: RANG | B12: NOM | C12: PRÉNOMS | D12: TOTAL COTISÉ | E12: PÉNALITÉS DUES | F12: PRÊTS EN COURS | G12: SOLDE NET | H12: STATUT
A13: 1 | B13: ='📋 SOLDE MEMBRES'!C4 -> 0 | C13: ='📋 SOLDE MEMBRES'!D4 -> 0 | D13: ='📋 SOLDE MEMBRES'!E4 -> 0 | E13: ='📋 SOLDE MEMBRES'!F4 -> 0 | F13: ='📋 SOLDE MEMBRES'!G4 -> 0 | G13: ='📋 SOLDE MEMBRES'!H4 -> 0 | H13: ='📋 SOLDE MEMBRES'!I4 -> ✅ À jour
A14: 2 | B14: ='📋 SOLDE MEMBRES'!C5 -> 0 | C14: ='📋 SOLDE MEMBRES'!D5 -> 0 | D14: ='📋 SOLDE MEMBRES'!E5 -> 0 | E14: ='📋 SOLDE MEMBRES'!F5 -> 0 | F14: ='📋 SOLDE MEMBRES'!G5 -> 0 | G14: ='📋 SOLDE MEMBRES'!H5 -> 0 | H14: ='📋 SOLDE MEMBRES'!I5 -> ✅ À jour
A15: 3 | B15: ='📋 SOLDE MEMBRES'!C6 -> 0 | C15: ='📋 SOLDE MEMBRES'!D6 -> 0 | D15: ='📋 SOLDE MEMBRES'!E6 -> 0 | E15: ='📋 SOLDE MEMBRES'!F6 -> 0 | F15: ='📋 SOLDE MEMBRES'!G6 -> 0 | G15: ='📋 SOLDE MEMBRES'!H6 -> 0 | H15: ='📋 SOLDE MEMBRES'!I6 -> ✅ À jour
A16: 4 | B16: ='📋 SOLDE MEMBRES'!C7 -> 0 | C16: ='📋 SOLDE MEMBRES'!D7 -> 0 | D16: ='📋 SOLDE MEMBRES'!E7 -> 0 | E16: ='📋 SOLDE MEMBRES'!F7 -> 0 | F16: ='📋 SOLDE MEMBRES'!G7 -> 0 | G16: ='📋 SOLDE MEMBRES'!H7 -> 0 | H16: ='📋 SOLDE MEMBRES'!I7 -> ✅ À jour
A17: 5 | B17: ='📋 SOLDE MEMBRES'!C8 -> 0 | C17: ='📋 SOLDE MEMBRES'!D8 -> 0 | D17: ='📋 SOLDE MEMBRES'!E8 -> 0 | E17: ='📋 SOLDE MEMBRES'!F8 -> 0 | F17: ='📋 SOLDE MEMBRES'!G8 -> 0 | G17: ='📋 SOLDE MEMBRES'!H8 -> 0 | H17: ='📋 SOLDE MEMBRES'!I8 -> ✅ À jour
A18: 6 | B18: ='📋 SOLDE MEMBRES'!C9 -> 0 | C18: ='📋 SOLDE MEMBRES'!D9 -> 0 | D18: ='📋 SOLDE MEMBRES'!E9 -> 0 | E18: ='📋 SOLDE MEMBRES'!F9 -> 0 | F18: ='📋 SOLDE MEMBRES'!G9 -> 0 | G18: ='📋 SOLDE MEMBRES'!H9 -> 0 | H18: ='📋 SOLDE MEMBRES'!I9 -> ✅ À jour
A19: 7 | B19: ='📋 SOLDE MEMBRES'!C10 -> 0 | C19: ='📋 SOLDE MEMBRES'!D10 -> 0 | D19: ='📋 SOLDE MEMBRES'!E10 -> 0 | E19: ='📋 SOLDE MEMBRES'!F10 -> 0 | F19: ='📋 SOLDE MEMBRES'!G10 -> 0 | G19: ='📋 SOLDE MEMBRES'!H10 -> 0 | H19: ='📋 SOLDE MEMBRES'!I10 -> ✅ À jour
A20: 8 | B20: ='📋 SOLDE MEMBRES'!C11 -> 0 | C20: ='📋 SOLDE MEMBRES'!D11 -> 0 | D20: ='📋 SOLDE MEMBRES'!E11 -> 0 | E20: ='📋 SOLDE MEMBRES'!F11 -> 0 | F20: ='📋 SOLDE MEMBRES'!G11 -> 0 | G20: ='📋 SOLDE MEMBRES'!H11 -> 0 | H20: ='📋 SOLDE MEMBRES'!I11 -> ✅ À jour
A21: 9 | B21: ='📋 SOLDE MEMBRES'!C12 -> 0 | C21: ='📋 SOLDE MEMBRES'!D12 -> 0 | D21: ='📋 SOLDE MEMBRES'!E12 -> 0 | E21: ='📋 SOLDE MEMBRES'!F12 -> 0 | F21: ='📋 SOLDE MEMBRES'!G12 -> 0 | G21: ='📋 SOLDE MEMBRES'!H12 -> 0 | H21: ='📋 SOLDE MEMBRES'!I12 -> ✅ À jour
A22: 10 | B22: ='📋 SOLDE MEMBRES'!C13 -> 0 | C22: ='📋 SOLDE MEMBRES'!D13 -> 0 | D22: ='📋 SOLDE MEMBRES'!E13 -> 0 | E22: ='📋 SOLDE MEMBRES'!F13 -> 0 | F22: ='📋 SOLDE MEMBRES'!G13 -> 0 | G22: ='📋 SOLDE MEMBRES'!H13 -> 0 | H22: ='📋 SOLDE MEMBRES'!I13 -> ✅ À jour
A23: 11 | B23: ='📋 SOLDE MEMBRES'!C14 -> 0 | C23: ='📋 SOLDE MEMBRES'!D14 -> 0 | D23: ='📋 SOLDE MEMBRES'!E14 -> 0 | E23: ='📋 SOLDE MEMBRES'!F14 -> 0 | F23: ='📋 SOLDE MEMBRES'!G14 -> 0 | G23: ='📋 SOLDE MEMBRES'!H14 -> 0 | H23: ='📋 SOLDE MEMBRES'!I14 -> ✅ À jour
A24: 12 | B24: ='📋 SOLDE MEMBRES'!C15 -> 0 | C24: ='📋 SOLDE MEMBRES'!D15 -> 0 | D24: ='📋 SOLDE MEMBRES'!E15 -> 0 | E24: ='📋 SOLDE MEMBRES'!F15 -> 0 | F24: ='📋 SOLDE MEMBRES'!G15 -> 0 | G24: ='📋 SOLDE MEMBRES'!H15 -> 0 | H24: ='📋 SOLDE MEMBRES'!I15 -> ✅ À jour
... A35: 23 | B35: ='📋 SOLDE MEMBRES'!C26 -> 0 | C35: ='📋 SOLDE MEMBRES'!D26 -> 0 | D35: ='📋 SOLDE MEMBRES'!E26 -> 0 | E35: ='📋 SOLDE MEMBRES'!F26 -> 0 | F35: ='📋 SOLDE MEMBRES'!G26 -> 0 | G35: ='📋 SOLDE MEMBRES'!H26 -> 0 | H35: ='📋 SOLDE MEMBRES'!I26 -> ✅ À jour
A38: 📅 RÉSUMÉ DES COTISATIONS PAR MOIS
A39: JANV. | B39: FÉVR. | C39: MARS | D39: AVRIL | E39: MAI | F39: JUIN | G39: JUIL. | H39: AOÛT | I39: SEPT. | J39: OCT. | K39: NOV. | L39: DÉC.
A40: =SUM('💰 COTISATIONS'!E28:I28) -> 0 | B40: =SUM('💰 COTISATIONS'!J28:M28) -> 0 | C40: =SUM('💰 COTISATIONS'!N28:Q28) -> 0 | D40: =SUM('💰 COTISATIONS'!R28:T28) -> 0 | E40: =SUM('💰 COTISATIONS'!U28:X28) -> 0 | F40: =SUM('💰 COTISATIONS'!Y28:AB28) -> 0 | G40: =SUM('💰 COTISATIONS'!AC28:AF28) -> 0 | H40: =SUM('💰 COTISATIONS'!AG28:AJ28) -> 0 | I40: =SUM('💰 COTISATIONS'!AK28:AN28) -> 0 | J40: =SUM('💰 COTISATIONS'!AO28:AR28) -> 0 | K40: =SUM('💰 COTISATIONS'!AS28:AW28) -> 0 | L40: =SUM('💰 COTISATIONS'!AX28:AZ28) -> 0

Sheet 🪪 IDENTITÉ
A1: 🪪 IDENTITÉ DES MEMBRES – TONTINE SOLIDARITÉ PLUS 2027
A2: # | B2: ID_MEM | C2: NOM | D2: PRÉNOMS | E2: TÉLÉPHONE | F2: EMAIL | G2: SEXE | H2: N° CARTE CIP | I2: DATE NAISSANCE | J2: PROVENANCE
A3: 1
A4: 2
A5: 3
A6: 4
A7: 5
A8: 6
A9: 7
A10: 8
A11: 9
A12: 10
A13: 11
A14: 12
... A25: 23
